Workbook
Name _: #REF!
Name __: #REF!
Name ___: #REF!
Name ____: #REF!
Name _____: #REF!
Name ______: #REF!
Name _______: #REF!
Name ________: #REF!
Name _________: #REF!
Name __________: #REF!
Name ___________: #REF!
Name ____________: #REF!
Name _____________: #REF!
Name ______________: #REF!
Name _______________: #REF!
Name ________________: #REF!
Name _________________: #REF!
Name __________________: #REF!
Name ___________________: #REF!
Name ____________________: #REF!
Name _____________________: #REF!
Name A: [1]Data!$A$1
Name aaaaa: #REF!
Name AB: #REF!
Name ABC: #REF!
Name AD: #REF!
Name AS: #REF!
Name B: [2]Data!$A$1
Name BC: #REF!
Name compactées: #REF!
Name Currency: [3]StdInput!$A$5:$A$23
Name Dat: #REF!
Name Divisions: [3]StdInput!$E$21:$H$21
Name DJHGK: #REF!
Name FFFF: #REF!
Name InvestType: [3]StdInput!$D$22:$D$32
Name Print_Area_0: #REF!
Name Print_Area_1: #REF!
Name Print_Area_10: #REF!
Name Print_Area_11: #REF!
Name Print_Area_12: #REF!
Name Print_Area_13: #REF!
Name Print_Area_14: #REF!
Name Print_Area_15: #REF!
Name Print_Area_16: #REF!
Name Print_Area_17: #REF!
Name Print_Area_18: #REF!
Name Print_Area_19: #REF!
Name Print_Area_2: #REF!
Name Print_Area_20: #REF!
Name Print_Area_21: #REF!
Name Print_Area_3: #REF!
Name Print_Area_5: #REF!
Name Print_Area_6: #REF!
Name Print_Area_7: #REF!
Name Print_Area_8: #REF!
Name Print_Area_9: #REF!
Name QQ: #REF!
Name qqqq: #REF!
Name Query2: #REF!

Sheet Summary-HC
B1: 46204
B2: Description | C2: HC Allocation | D2: HC Physicaly req @ line | E2: Assembly Lines | F2: Assembly hrs
A3: Manufacturing | B3: Crew required for BK cable Assembly with supporting crew | C3: ='PN-workout file'!Q3+'PN-workout file'!Q4+'PN-workout file'!Q5+'PN-workout file'!Q6+'PN-workout file'!Q7+'PN-workout file'!Q35+'PN-workout file'!Q37+'PN-workout file'!Q39+'PN-workout file'!Q40+'PN-workout file'!Q41+'PN-workout file'!Q42+'PN-workout file'!Q44+'PN-workout file'!Q45+'Supporting HC details'!H12 -> 1135.1669 | D3: =C3*0.88 -> 998.94691 | F3: Semi-Auto | G3: Manual-Hrs | H3: Insp. & Pack-Hrs | I3: Total | J3: Total Hrs | K3: Per day Hrs | L3: DL % | M3: LR@0.12 | N3: HC/Line
B4: Crew required for ACWHIP with supporting crew | C4: ='PN-workout file'!Q26+'PN-workout file'!Q27+'PN-workout file'!Q28+'PN-workout file'!Q30+'PN-workout file'!Q31+'PN-workout file'!Q32+'PN-workout file'!Q46+'PN-workout file'!Q47+'PN-workout file'!Q48+'PN-workout file'!Q49+'PN-workout file'!Q50+'PN-workout file'!Q51+'PN-workout file'!Q52+'PN-workout file'!Q53+'Supporting HC details'!I12 -> 528.39491 | D4: =C4*0.88 -> 464.98752 | E4: Assembly Line-Core | F4: 2034 | G4: 275741.83 | H4: 93510.476 | I4: =SUM(F4:H4) -> 371286.3 | J4: =I4 -> 371286.3 | K4: =J4/26/7 -> 2040.0346 | L4: =K4/0.88 -> 2318.2212 | M4: =(L4*0.12)+45 -> 323.18654 | N4: =L4+M4 -> 2641.4077
B5: Crew required for Connector with supporting crew | C5: ='PN-workout file'!Q8+'PN-workout file'!Q9+'PN-workout file'!Q10+'PN-workout file'!Q11+'PN-workout file'!Q12+'PN-workout file'!Q13+'PN-workout file'!Q14+'PN-workout file'!Q16+'PN-workout file'!Q17+'PN-workout file'!Q18+'PN-workout file'!Q19+'PN-workout file'!Q20+'PN-workout file'!Q21+'PN-workout file'!Q22+'PN-workout file'!Q25+'Supporting HC details'!J12+PB!M15 -> 329.31295 | D5: =C5*0.88 -> 289.79539 | J5: =I5 -> 0 | K5: =J5/26/7 -> 0 | L5: =K5/0.88 -> 0 | M5: =(L5*0.12) -> 0 | N5: =SUM(L5:M5) -> 0
B6: Crew required in bench | C6: 50 | D6: =C6*0.88 -> 44 | E6: Legacy Power | F6: 1750 | G6: 32307 | H6: 6239 | I6: =SUM(F6:H6) -> 40296 | J6: =I6 -> 40296 | K6: =J6/26/7 -> 221.40659 | L6: =K6/1 -> 221.40659 | M6: =(L6*0.1) -> 22.140659 | N6: =SUM(L6:M6) -> 243.54725
B7: Crew required for EV (Plant 2 & 3) | C7: 199 | D7: =C7*0.88 -> 175.12 | J7: =I7 -> 0 | K7: =J7/26/7 -> 0 | L7: =K7/0.88 -> 0 | M7: =(L7*0.12)+39 -> 39 | N7: =L7+M7 -> 39
B9: Total Crew for Manufacturing | C9: =SUM(C3:C7) -> 2241.8748 | D9: =SUM(D3:D8) -> 1972.8498 | E9: Total Hrs | F9: =SUM(F4:F8) -> 3784 | G9: =SUM(G4:G8) -> 308048.83 | H9: =SUM(H4:H8) -> 99749.476
B10: HC as on June 25th | C10: 2103 | D10: 1860 | F10: =F9+G9+H9 -> 411582.3
B11: Gap | C11: =C10-C9 -> -138.8748 | D11: =D10-D9 -> -112.84982
A12: QA | B12: Crew for QA | C12: 102 | F12: =SUM(F9:H9) -> 411582.3
A13: NPI | B13: Crew for NPI | C13: 156
B14: Total required for July 26 | C14: =SUM(C3:C7)+C12+C13 -> 2499.8748
B15: HC as on June 28th | C15: 2103 | E15: Description | F15: 46199 | G15: 46229 | H15: % of Increase
B16: Balance crew required for production July 26 | C16: =C10-C9 -> -138.8748 | E16: Revenue-($K) | F16: 35200 | G16: 42211 | H16: =(G16-F16)/G16 -> 0.16609415
B17: Revenue planned for July-26 | C17: $40 M | E17: HC | F17: 2012.0434 | G17: =C9 -> 2241.8748 | H17: =(G17-F17)/G17 -> 0.10251748
E18: Revenue/HC ($K) | F18: =F16/F17 -> 17.494652 | G18: =G16/G17 -> 18.828438 | H18: =(G18-F18)/G18 -> 0.070838888

Sheet Sheet8
E4: Capacity Estimate
E5: Bottleneck | F5: Splice crimping
E6: Splice crimp CT | F6: 32
E7: Shift Output | F7: =(3600/F6)*7*0.85/8 -> 83.671875
E8: Daily Output | F8: =F7*3 -> 251.01562

Sheet Sheet1
A3: Row Labels | B3: Sum of Qty Open | C3: Promised Date
A4: 10130664-1RF474HF BK200 IO CABLE ASSY | B4: 3620 | C4: 45560
A5: 10130664-9B0319HLF BARKLIP CABLE ASSEMBLY | B5: 27200 | C5: 25200 in 11th Oct, 2200 in 1st Nov
A6: 10130664-9D0354LF BARKLIP CABLE ASSY-196MM | B6: 2880 | C6: 720 in 9th Oct, 2160 in 18th Oct
A7: 10130664-9D0355LF BARKLIP CABLE ASSY-135MM | B7: 4320 | C7: 720 in 9th Oct, 720 in 9th Oct, 2880 in 8th Nov
A8: 10130664-9D0356LF BARKLIP CABLE ASSY-82MM | B8: 2880 | C8: 720 in 25th Oct, 2160 in 8th Nov
A9: 10130664-9SF463LF BK200 I/O Cable Assembly | B9: 500
A10: 10150562-001 HOUSING RPS04HBR01F | B10: 35000
A11: 10158287-9RF034HF BK 300 CABLE ASSY | B11: 35000 | C11: 10000 in 18th Oct, 25000 in 25th Oct
A12: 10162405-1S2009LF BARKLIP CABLE ASSEMBLY | B12: 52300 | C12: 25K for 4th Oct, 12300 for 18th Oct, 15k for 25th Oct
A13: 10165987-101LF 2POS RAPID LOCK CNR KIT | B13: 20000
A14: (blank)
A15: Grand Total | B15: 183700

Sheet Data (2)
A1: Site | B1: Order | C1: Line | D1: Sold-To | E1: Ship-To | F1: Cust Sort Name | G1: Shipto Sort Name | H1: Purchase Order | I1: Order Date | J1: Customer Item | K1: Item Number | L1: UM | M1: Item Description | N1: HPL | O1: SOP | P1: Item Group | Q1: Required Date | R1: Due Date | S1: Promised Due Date | T1: Lead Time | U1: Available Qty On Hand | V1: Not Avail QOH | W1: QOH (OTHER SITES) | X1: Qty Ordered | Y1: Quantity Allocated | Z1: Quantity Picked | AA1: Qty Shipped | AB1: Quantity Invoiced | AC1: Qty Open | AD1: Price | AE1: Total Line | AF1: Currency | AG1: Actual Exchange Rate | AH1: Base Currency Amount | AI1: Category | AJ1: Modified Date
A2: 49560 | B2: ET105455 | C2: 1 | D2: EACA05 | E2: EACA0503 | F2: AVNET ASIA PTE Ltd | G2: EACA05 | H2: 6208662616 | I2: 45484 | J2: 10162405-1S2009LF | K2: 10162405-1S2009LF | L2: EA | M2: 10162405-1S2009LF BARKLIP CABLE ASSEMBLY | N2: 355 | O2: 20GF | P2: 503BRKCA | Q2: 45569 | R2: 45569 | S2: 45569 | T2: 0 | U2: 4400 | V2: 3308 | W2: 0 | X2: 15000 | Y2: 0 | Z2: 0 | AA2: 0 | AB2: 0 | AC2: 15000 | AD2: 10.86 | AE2: 162900 | AF2: USD | AG2: 84.03361 | AH2: 13574999 | AJ2: 45484
A3: 49560 | B3: ET105395 | C3: 2 | D3: EACA05 | E3: EACA0503 | F3: AVNET ASIA PTE Ltd | G3: EACA05 | H3: 6208588520 | I3: 45447 | J3: 10162405-1S2009LF | K3: 10162405-1S2009LF | L3: EA | M3: 10162405-1S2009LF BARKLIP CABLE ASSEMBLY | N3: 355 | O3: 20GF | P3: 503BRKCA | Q3: 45569 | R3: 45569 | S3: 45569 | T3: 0 | U3: 4400 | V3: 3308 | W3: 0 | X3: 10000 | Y3: 0 | Z3: 0 | AA3: 0 | AB3: 0 | AC3: 10000 | AD3: 10.86 | AE3: 108600 | AF3: USD | AG3: 84.03361 | AH3: 9049999.6 | AJ3: 45447
A4: 49560 | B4: EF101973 | C4: 1 | D4: US10 | E4: 314601 | F4: FCI USA LLC | G4: FCI Electronics | H4: 408701 | I4: 45488 | J4: 10130664-9D0355LF | K4: 10130664-9D0355LF | L4: EA | M4: 10130664-9D0355LF BARKLIP CABLE ASSY-135MM | N4: 355 | O4: 22EF | P4: 503BRKCA | Q4: 45574 | R4: 45574 | S4: 45574 | T4: 0 | U4: 0 | V4: 0 | W4: 0 | X4: 720 | Y4: 0 | Z4: 0 | AA4: 0 | AB4: 0 | AC4: 720 | AD4: 5.6232 | AE4: 4048.7 | AF4: USD | AG4: 84.03361 | AH4: 337391.99
A5: 49560 | B5: EF101973 | C5: 2 | D5: US10 | E5: 314601 | F5: FCI USA LLC | G5: FCI Electronics | H5: 408701 | I5: 45488 | J5: 10130664-9D0354LF | K5: 10130664-9D0354LF | L5: EA | M5: 10130664-9D0354LF BARKLIP CABLE ASSY-196MM | N5: 355 | O5: 22EF | P5: 503BRKCA | Q5: 45574 | R5: 45574 | S5: 45574 | T5: 0 | U5: 312 | V5: 0 | W5: 0 | X5: 720 | Y5: 0 | Z5: 0 | AA5: 0 | AB5: 0 | AC5: 720 | AD5: 5.7816 | AE5: 4162.8 | AF5: USD | AG5: 84.03361 | AH5: 346895.99
A6: 49560 | B6: EF102298 | C6: 1 | D6: CN43 | E6: CN43 | F6: FCI NANTONG LTD. | G6: FCI NANTONG LTD. | H6: IN56CW12 | I6: 45525 | J6: 10165987-101LF | K6: 10165987-101LF | L6: EA | M6: 10165987-101LF 2POS RAPID LOCK CNR KIT | N6: 503 | O6: 22ZS | P6: 5031ASM | Q6: 45569 | R6: 45576 | S6: 45576 | T6: -7 | U6: 0 | V6: 0 | W6: 0 | X6: 20000 | Y6: 0 | Z6: 0 | AA6: 0 | AB6: 0 | AC6: 20000 | AD6: 4.57045 | AE6: 91409 | AF6: USD | AG6: 84.03361 | AH6: 7681428.3
A7: 49560 | B7: EF102263 | C7: 1 | D7: CN43 | E7: CN43 | F7: FCI NANTONG LTD. | G7: FCI NANTONG LTD. | H7: IN56CX17 | I7: 45519 | J7: 10150562-001 | K7: 10150562-001 | L7: EA | M7: 10150562-001 HOUSING RPS04HBR01F | N7: 503 | O7: 22ZS | P7: 503BRKCA | Q7: 45576 | R7: 45576 | S7: 45576 | T7: 0 | U7: 0 | V7: 0 | W7: 0 | X7: 15000 | Y7: 0 | Z7: 0 | AA7: 0 | AB7: 0 | AC7: 15000 | AD7: 0.26688 | AE7: 4003.2 | AF7: USD | AG7: 84.03361 | AH7: 336403.35
A8: 49560 | B8: ET105556 | C8: 1 | D8: EACV02 | E8: EACV0206 | F8: VSELL ENTERPRISE CO. | G8: EACV02 | H8: 400004792 | I8: 45518 | J8: 10130664-9B0319HLF[AMPHENOL] | K8: 10130664-9B0319HLF | L8: EA | M8: 10130664-9B0319HLF BARKLIP CABLE ASSEMBLY | N8: 355 | O8: 22EF | P8: 503BRKCA | Q8: 45569 | R8: 45576 | S8: 45576 | T8: -7 | U8: 9840 | V8: 2180 | W8: 0 | X8: 25000 | Y8: 0 | Z8: 0 | AA8: 0 | AB8: 0 | AC8: 25000 | AD8: 22.92 | AE8: 573000 | AF8: USD | AG8: 84.03361 | AH8: 48151259 | AJ8: 45518
A9: 49560 | B9: EF102131 | C9: 6 | D9: US10 | E9: 31461 | F9: FCI USA LLC | G9: SANMINA SCI | H9: 410017 | I9: 45506 | J9: 10130664-9D0355LF | K9: 10130664-9D0355LF | L9: EA | M9: 10130664-9D0355LF BARKLIP CABLE ASSY-135MM | N9: 355 | O9: 22EF | P9: 503BRKCA | Q9: 45576 | R9: 45576 | S9: 45576 | T9: 0 | U9: 0 | V9: 0 | W9: 0 | X9: 720 | Y9: 0 | Z9: 0 | AA9: 0 | AB9: 0 | AC9: 720 | AD9: 5.6232 | AE9: 4048.7 | AF9: USD | AG9: 84.03361 | AH9: 340227.21
A10: 49560 | B10: ET105587 | C10: 1 | D10: EACV02 | E10: EACV0203 | F10: VSELL ENTERPRISE CO. | G10: EACV02 | H10: 400005117 | I10: 45538 | J10: 10162405-1S2009LF[AMPHENOL] | K10: 10162405-1S2009LF | L10: EA | M10: 10162405-1S2009LF BARKLIP CABLE ASSEMBLY | N10: 355 | O10: 20GF | P10: 503BRKCA | Q10: 45576 | R10: 45583 | S10: 45583 | T10: -7 | U10: 4400 | V10: 3308 | W10: 0 | X10: 2300 | Y10: 0 | Z10: 0 | AA10: 0 | AB10: 0 | AC10: 2300 | AD10: 10.43 | AE10: 23989 | AF10: USD | AG10: 84.03361 | AH10: 2015882.3 | AJ10: 45538
A11: 49560 | B11: EI33615 | C11: 10 | D11: EACA05 | E11: EACA0504 | F11: AVNET ASIA PTE Ltd | G11: Ingrasys Technology Mexi | H11: 6208763304 | I11: 45537 | J11: 35108WR00-245-G | K11: 10158287-9RF034HF | L11: EA | M11: 10158287-9RF034HF BK 300 CABLE ASSY | N11: 355 | O11: 22EF | P11: 503BRKCA | Q11: 45561 | R11: 45583 | S11: 45583 | T11: -22 | U11: 640 | V11: 700 | W11: 0 | X11: 10000 | Y11: 0 | Z11: 0 | AA11: 0 | AB11: 0 | AC11: 10000 | AD11: 14.11 | AE11: 141100 | AF11: USD | AG11: 84.03361 | AH11: 11857142
A12: 49560 | B12: EF102274 | C12: 3 | D12: US10 | E12: 314601 | F12: FCI USA LLC | G12: FCI Electronics | H12: 410896 | I12: 45521 | J12: 10130664-9D0354LF | K12: 10130664-9D0354LF | L12: EA | M12: 10130664-9D0354LF BARKLIP CABLE ASSY-196MM | N12: 355 | O12: 22EF | P12: 503BRKCA | Q12: 45583 | R12: 45583 | S12: 45583 | T12: 0 | U12: 312 | V12: 0 | W12: 0 | X12: 2160 | Y12: 0 | Z12: 0 | AA12: 0 | AB12: 0 | AC12: 2160 | AD12: 5.7816 | AE12: 12488 | AF12: USD | AG12: 84.03361 | AH12: 1049433.2
A13: 49560 | B13: EI32990 | C13: 10 | D13: EACA05 | E13: EACA0503 | F13: AVNET ASIA PTE Ltd | G13: EACA05 | H13: 6208716672 | I13: 45517 | J13: FCI10158287-9RF03> | K13: 10158287-9RF034HF | L13: EA | M13: 10158287-9RF034HF BK 300 CABLE ASSY | N13: 355 | O13: 22EF | P13: 503BRKCA | Q13: 45547 | R13: 45583 | S13: 45583 | T13: -36 | U13: 640 | V13: 700 | W13: 0 | X13: 10000 | Y13: 0 | Z13: 0 | AA13: 0 | AB13: 0 | AC13: 10000 | AD13: 14.11 | AE13: 141100 | AF13: USD | AG13: 84.03361 | AH13: 11857142
A14: 49560 | B14: ET105456 | C14: 1 | D14: EACA05 | E14: EACA0503 | F14: AVNET ASIA PTE Ltd | G14: EACA05 | H14: 6208662618 | I14: 45484 | J14: 10162405-1S2009LF | K14: 10162405-1S2009LF | L14: EA | M14: 10162405-1S2009LF BARKLIP CABLE ASSEMBLY | N14: 355 | O14: 20GF | P14: 503BRKCA | Q14: 45583 | R14: 45583 | S14: 45583 | T14: 0 | U14: 4400 | V14: 3308 | W14: 0 | X14: 10000 | Y14: 0 | Z14: 0 | AA14: 0 | AB14: 0 | AC14: 10000 | AD14: 10.86 | AE14: 108600 | AF14: USD | AG14: 84.03361 | AH14: 9049999.6 | AJ14: 45484
A15: 49560 | B15: EI34065 | C15: 10 | D15: EACA05 | E15: EACA0503 | F15: AVNET ASIA PTE Ltd | G15: EACA05 | H15: 6208794006 | I15: 45554 | J15: FCI10130664-1RF>B> | K15: 10130664-1RF474HF | L15: EA | M15: 10130664-1RF474HF BK200 IO CABLE ASSY | N15: 355 | O15: 22EF | P15: 355BRKCA | Q15: 45561 | R15: 45590 | S15: 45590 | T15: -29 | U15: 60 | V15: 0 | W15: 0 | X15: 1620 | Y15: 0 | Z15: 0 | AA15: 0 | AB15: 0 | AC15: 1620 | AD15: 30.37 | AE15: 49199 | AF15: USD | AG15: 84.03361 | AH15: 4134403.2
A16: 49560 | B16: EF102131 | C16: 7 | D16: US10 | E16: 31461 | F16: FCI USA LLC | G16: SANMINA SCI | H16: 410017 | I16: 45506 | J16: 10130664-9D0356LF | K16: 10130664-9D0356LF | L16: EA | M16: 10130664-9D0356LF BARKLIP CABLE ASSY-82MM | N16: 355 | O16: 22EF | P16: 503BRKCA | Q16: 45590 | R16: 45590 | S16: 45590 | T16: 0 | U16: 0 | V16: 96 | W16: 0 | X16: 720 | Y16: 0 | Z16: 0 | AA16: 0 | AB16: 0 | AC16: 720 | AD16: 5.4 | AE16: 3888 | AF16: USD | AG16: 84.03361 | AH16: 326722.68
A17: 49560 | B17: ET105497 | C17: 1 | D17: EUCF02 | E17: EUCF0201 | F17: FLEXTRONICS INTERNATIONA | G17: EUCF02 | H17: 269P18095 | I17: 45502 | J17: AMZ-216-003899-001 | K17: 10130664-1RF474HF | L17: EA | M17: 10130664-1RF474HF BK200 IO CABLE ASSY | N17: 355 | O17: 22EF | P17: 355BRKCA | Q17: 45590 | R17: 45590 | S17: 45590 | T17: 0 | U17: 60 | V17: 0 | W17: 0 | X17: 1000 | Y17: 0 | Z17: 0 | AA17: 0 | AB17: 0 | AC17: 1000 | AD17: 34.93 | AE17: 34930 | AF17: USD | AG17: 84.03361 | AH17: 2910833.2 | AJ17: 45502
A18: 49560 | B18: EI32675 | C18: 10 | D18: EACA05 | E18: EACA0503 | F18: AVNET ASIA PTE Ltd | G18: EACA05 | H18: 6208691032 | I18: 45499 | J18: FCI10162405-1S2>>> | K18: 10162405-1S2009LF | L18: EA | M18: 10162405-1S2009LF BARKLIP CABLE ASSEMBLY | N18: 355 | O18: 20GF | P18: 503BRKCA | Q18: 45590 | R18: 45590 | S18: 45590 | T18: 0 | U18: 4400 | V18: 3308 | W18: 0 | X18: 15000 | Y18: 0 | Z18: 0 | AA18: 0 | AB18: 0 | AC18: 15000 | AD18: 10.86 | AE18: 162900 | AF18: USD | AG18: 84.03361 | AH18: 13574999
A19: 49560 | B19: ET105478 | C19: 10 | D19: EUCF02 | E19: EUCF0201 | F19: FLEXTRONICS INTERNATIONA | G19: EUCF02 | H19: 269P18066 | I19: 45495 | J19: AMZ-216-003899-001 | K19: 10130664-1RF474HF | L19: EA | M19: 10130664-1RF474HF BK200 IO CABLE ASSY | N19: 355 | O19: 22EF | P19: 355BRKCA | Q19: 45590 | R19: 45590 | S19: 45590 | T19: 0 | U19: 60 | V19: 0 | W19: 0 | X19: 1000 | Y19: 0 | Z19: 0 | AA19: 0 | AB19: 0 | AC19: 1000 | AD19: 34.93 | AE19: 34930 | AF19: USD | AG19: 84.03361 | AH19: 2910833.2 | AJ19: 45495
A20: 49560 | B20: EF100293 | C20: 4 | D20: TW00 | E20: 460010 | F20: FCI TAIWAN | G20: QUADREP ELECTRONICS LTD | H20: N6Q41167 | I20: 45308 | J20: 10158287-9RF034HF | K20: 10158287-9RF034HF | L20: EA | M20: 10158287-9RF034HF BK 300 CABLE ASSY | N20: 355 | O20: 22EF | P20: 503BRKCA | Q20: 45590 | R20: 45590 | S20: 45590 | T20: 0 | U20: 640 | V20: 700 | W20: 0 | X20: 15000 | Y20: 0 | Z20: 0 | AA20: 0 | AB20: 0 | AC20: 15000 | AD20: 14.84547 | AE20: 222682 | AF20: USD | AG20: 84.03361 | AH20: 18556837
A21: 49560 | B21: DISP0067 | C21: 1 | D21: IBCA51 | E21: IBCA5102 | F21: Avnet India Pvt. Ltd | G21: AVNET INDIA PVT LTD | H21: 6208790310 | I21: 45558 | K21: 10130664-9SF463LF | L21: EA | M21: 10130664-9SF463LF BK200 I/O Cable Assembly | N21: 355 | O21: 22EF | P21: 355BRKCA | Q21: 45569 | R21: 54700 | S21: 54700 | T21: -9131 | U21: 0 | V21: 0 | W21: 0 | X21: 100 | Y21: 0 | Z21: 0 | AA21: 0 | AB21: 0 | AC21: 100 | AD21: 4627.26 | AE21: 462726 | AF21: INR | AG21: 1 | AH21: 462726 | AJ21: 45558
A22: 49560 | B22: DISP0066 | C22: 1 | D22: IBCA51 | E22: IBCA5102 | F22: Avnet India Pvt. Ltd | G22: AVNET INDIA PVT LTD | H22: 6208790311 | I22: 45558 | K22: 10130664-9SF463LF | L22: EA | M22: 10130664-9SF463LF BK200 I/O Cable Assembly | N22: 355 | O22: 22EF | P22: 355BRKCA | Q22: 45569 | R22: 54700 | S22: 54700 | T22: -9131 | U22: 0 | V22: 0 | W22: 0 | X22: 400 | Y22: 0 | Z22: 0 | AA22: 0 | AB22: 0 | AC22: 400 | AD22: 4627.26 | AE22: 1850904 | AF22: INR | AG22: 1 | AH22: 1850904 | AJ22: 45558
A23: 49560 | B23: ET105546 | C23: 1 | D23: EACV03 | E23: EACV0301 | F23: VSELL ENTERPRISE CO. | G23: EACV03 | H23: 400004677 | I23: 45509 | J23: B50.0260X.0021 | K23: 10130664-9B0319HLF | L23: EA | M23: 10130664-9B0319HLF BARKLIP CABLE ASSEMBLY | N23: 355 | O23: 22EF | P23: 503BRKCA | Q23: 45597 | R23: 45597 | S23: 45597 | T23: 0 | U23: 10080 | V23: 1940 | W23: 0 | X23: 2200 | Y23: 0 | Z23: 0 | AA23: 0 | AB23: 0 | AC23: 2200 | AD23: 22.92 | AE23: 50424 | AF23: USD | AG23: 84.03361 | AH23: 4237310.8 | AJ23: 45509
A24: 49560 | B24: EF102491 | C24: 2 | D24: CN43 | E24: CN43 | F24: FCI NANTONG LTD. | G24: FCI NANTONG LTD. | H24: IN24CT01 | I24: 45542 | J24: 10150562-001 | K24: 10150562-001 | L24: EA | M24: 10150562-001 HOUSING RPS04HBR01F | N24: 503 | O24: 22ZS | P24: 503BRKCA | Q24: 45604 | R24: 45604 | S24: 45604 | T24: 0 | U24: 0 | V24: 0 | W24: 0 | X24: 10000 | Y24: 0 | Z24: 0 | AA24: 0 | AB24: 0 | AC24: 10000 | AD24: 0.26688 | AE24: 2668.8 | AF24: USD | AG24: 84.03361 | AH24: 224268.9
A25: 49560 | B25: EF102491 | C25: 1 | D25: CN43 | E25: CN43 | F25: FCI NANTONG LTD. | G25: FCI NANTONG LTD. | H25: IN24CT01 | I25: 45542 | J25: 10150562-001 | K25: 10150562-001 | L25: EA | M25: 10150562-001 HOUSING RPS04HBR01F | N25: 503 | O25: 22ZS | P25: 503BRKCA | Q25: 45597 | R25: 45604 | S25: 45604 | T25: -7 | U25: 0 | V25: 0 | W25: 0 | X25: 10000 | Y25: 0 | Z25: 0 | AA25: 0 | AB25: 0 | AC25: 10000 | AD25: 0.26688 | AE25: 2668.8 | AF25: USD | AG25: 84.03361 | AH25: 224268.9
A26: 49560 | B26: EF102274 | C26: 4 | D26: US10 | E26: 314601 | F26: FCI USA LLC | G26: FCI Electronics | H26: 410896 | I26: 45521 | J26: 10130664-9D0355LF | K26: 10130664-9D0355LF | L26: EA | M26: 10130664-9D0355LF BARKLIP CABLE ASSY-135MM | N26: 355 | O26: 22EF | P26: 503BRKCA | Q26: 45604 | R26: 45604 | S26: 45604 | T26: 0 | U26: 0 | V26: 0 | W26: 0 | X26: 2880 | Y26: 0 | Z26: 0 | AA26: 0 | AB26: 0 | AC26: 2880 | AD26: 5.6232 | AE26: 16195 | AF26: USD | AG26: 84.03361 | AH26: 1360908.9
A27: 49560 | B27: EF102274 | C27: 5 | D27: US10 | E27: 314601 | F27: FCI USA LLC | G27: FCI Electronics | H27: 410896 | I27: 45521 | J27: 10130664-9D0356LF | K27: 10130664-9D0356LF | L27: EA | M27: 10130664-9D0356LF BARKLIP CABLE ASSY-82MM | N27: 355 | O27: 22EF | P27: 503BRKCA | Q27: 45604 | R27: 45604 | S27: 45604 | T27: 0 | U27: 0 | V27: 96 | W27: 0 | X27: 2160 | Y27: 0 | Z27: 0 | AA27: 0 | AB27: 0 | AC27: 2160 | AD27: 5.4 | AE27: 11664 | AF27: USD | AG27: 84.03361 | AH27: 980168.03
AH28: =SUM(AH2:AH27) -> 1.6740339e+08
AH29: =AH28/(84.03361*1000) -> 1992.1004

Sheet PN-workout file
A1: Lines | B1: Item Number | C1: Description | D1: Qty. | E1: CT | I1: Hrs. | N1: HC/ Day | O1: Sunday working-HC | P1: LR @12% | R1: Remarks
E2: MA | F2: MA | G2: I&P | H2: Total | I2: MA | J2: I&P | K2: Total | M2: Target/day | Q2: Total HC | S2: Wire cutting | T2: Cropping | U2: Welding | V2: Sum
A3: BK Cable | B3: 10130664-9RF438LF | C3: Meta/Amazon | D3: 79720 | E3: =0.15-(V3) -> 0.12083333 | F3: 0.21 | G3: 0.03125 | H3: =E3+G3 -> 0.15208333 | I3: =F3*D3 -> 16741.2 | J3: =G3*D3 -> 2491.25 | K3: =SUM(I3:J3) -> 19232.45 | M3: =D3/$X$5 -> 2952.5926 | N3: =D3*H3/$X$5/7.05/$X$4 -> 70.770705 | P3: =N3*0.12 -> 8.4924846 | Q3: =N3+O3+P3 -> 79.26319 | S3: =20/3600 -> 0.0055555556 | T3: =20/3600 -> 0.0055555556 | U3: =65/3600 -> 0.018055556 | V3: =SUM(S3:U3) -> 0.029166667
B4: 10158287-1RF057HF | C4: BK300 | D4: 34000 | E4: =(0.225)-(V4) -> 0.16361111 | F4: =0.225 -> 0.225 | G4: =0.0413888*0.8 -> 0.03311104 | H4: =E4+G4 -> 0.19672215 | I4: =F4*D4 -> 7650 | J4: =G4*D4 -> 1125.7754 | K4: =SUM(I4:J4) -> 8775.7754 | M4: =D4/$X$5 -> 1259.2593 | N4: =D4*H4/$X$5/7.05/$X$4 -> 39.042426 | P4: =N4*0.12 -> 4.6850911 | Q4: =N4+O4+P4 -> 43.727517 | S4: =31/3600 -> 0.0086111111 | T4: =10/3600 -> 0.0027777778 | U4: =180/3600 -> 0.05 | V4: =SUM(S4:U4) -> 0.061388889 | W4: DL % | X4: 0.9
B5: 10162405-1S2009LF | C5: BK50 | D5: 38000 | E5: 0.099 | F5: =0.1 -> 0.1 | G5: 0.00807 | H5: =E5+G5 -> 0.10707 | I5: =F5*D5 -> 3800 | J5: =G5*D5 -> 306.66 | K5: =SUM(I5:J5) -> 4106.66 | M5: =D5/$X$5 -> 1407.4074 | N5: =D5*H5/$X$5/7.05/$X$4 -> 23.749584 | P5: =(N5*0.12) -> 2.8499501 | Q5: =N5+O5+P5 -> 26.599534 | W5: Working days | X5: 27
B6: 10130664-9D0354LF | C6: TESLA | D6: 9840 | E6: =0.17-V6 -> 0.15194444 | F6: 0.17 | G6: 0.03 | H6: =E6+G6 -> 0.18194444 | I6: =F6*D6 -> 1672.8 | J6: =G6*D6 -> 295.2 | K6: =SUM(I6:J6) -> 1968 | M6: =D6/$X$5 -> 364.44444 | N6: =D6*H6/$X$5/7.05/$X$4 -> 10.450535 | P6: =N6*0.12 -> 1.2540642 | Q6: =N6+O6+P6 -> 11.704599 | S6: =15/3600 -> 0.0041666667 | T6: =10/3600 -> 0.0027777778 | U6: =40/3600 -> 0.011111111 | V6: =SUM(S6:U6) -> 0.018055556
B7: 10170425-9SF025LF | C7: TETON2 | D7: 150000 | E7: =(1300/3600)-V7 -> 0.25277778 | F7: =1200/3600 -> 0.33333333 | G7: =150/3600 -> 0.041666667 | H7: =E7+G7 -> 0.29444444 | I7: =F7*D7 -> 50000 | J7: =G7*D7 -> 6250 | K7: =SUM(I7:J7) -> 56250 | M7: =D7/$X$5 -> 5555.5556 | N7: =D7*H7/$X$5/7.05/$X$4 -> 257.80969 | O7: =N7/6 -> 42.968281 | P7: =N7*0.12 -> 30.937163 | Q7: =N7+O7+P7 -> 331.71513 | S7: =70/3600 -> 0.019444444 | T7: =70/3600 -> 0.019444444 | U7: =250/3600 -> 0.069444444 | V7: =SUM(S7:U7) -> 0.10833333
A8: Connector | B8: 10165987-101LF | C8: ASM | D8: 500000 | E8: 0.0079861 | G8: 0.0053833 | H8: =SUM(E8:G8) -> 0.0133694 | I8: =E8*D8 -> 3993.05 | J8: =G8*D8 -> 2691.65 | K8: =SUM(I8:J8) -> 6684.7 | M8: =D8/$X$5 -> 18518.519 | N8: =D8*H8/$X$5/7.05/$X$4 -> 39.019934 | P8: =N8*0.12 -> 4.6823921 | Q8: =N8+O8+P8 -> 43.702326 | S8: =16*4 -> 64
B9: 10168675-001LF | C9: Lockpin | D9: 462000 | E9: 0.000905 | G9: 0.0053833 | H9: =SUM(E9:G9) -> 0.0062883 | I9: =E9*D9 -> 418.11 | J9: =G9*D9 -> 2487.0846 | K9: =SUM(I9:J9) -> 2905.1946 | M9: =D9/$X$5 -> 17111.111 | N9: =D9*H9/$X$5/7.05/$X$4 -> 16.958203 | P9: =ROUNDUP(N9*0.12,0) -> 3 | Q9: =N9+O9+P9 -> 19.958203
B10: 10174922-001LF | C10: Z2/Z4 | E10: 0.0079861 | G10: 0.0053833 | H10: =SUM(E10:G10) -> 0.0133694 | I10: =E10*D10 -> 0 | J10: =G10*D10 -> 0 | K10: =SUM(I10:J10) -> 0 | M10: =D10/$X$5 -> 0 | N10: =D10*H10/$X$5/7.05/$X$4 -> 0 | P10: =ROUNDUP(N10*0.12,0) -> 0 | Q10: =N10+O10+P10 -> 0
B11: 10157266-001LF | C11: BK200 XP | D11: 25000 | E11: 0.01818 | G11: 0.00964 | H11: =SUM(E11:G11) -> 0.02782 | I11: =E11*D11 -> 454.5 | J11: =G11*D11 -> 241 | K11: =SUM(I11:J11) -> 695.5 | M11: =D11/$X$5 -> 925.92593 | N11: =D11*H11/$X$5/7.05/$X$4 -> 4.0597729 | P11: =N11*0.12 -> 0.48717275 | Q11: =N11+O11+P11 -> 4.5469457
B12: HPG36P14SRT051TH07 | C12: EEX | D12: 1500 | E12: =150/3600 -> 0.041666667 | G12: 0.013 | H12: =E12+G12 -> 0.054666667 | I12: =E12*D12 -> 62.5 | J12: =G12*D12 -> 19.5 | K12: =SUM(I12:J12) -> 82 | M12: =D12/$X$5 -> 55.555556 | N12: =D12*H12/$X$5/7.05/$X$4 -> 0.47865044 | P12: =N12*0.12 -> 0.057438053 | Q12: =N12+O12+P12 -> 0.53608849
B13: 10173947-100012LF | C13: 48V Connector | D13: 102328 | E13: =23/3600 -> 0.0063888889 | G13: 0.0048 | H13: =E13+G13 -> 0.011188889 | I13: =E13*D13 -> 653.76222 | J13: =G13*D13 -> 491.1744 | K13: =SUM(I13:J13) -> 1144.9366 | M13: =D13/$X$5 -> 3789.9259 | N13: =D13*H13/$X$5/7.05/$X$4 -> 6.6832246 | P13: =N13*0.12 -> 0.80198695 | Q13: =N13+O13+P13 -> 7.4852116
B14: 10170827-07P003 | C14: ORV3-Connector | D14: 62154 | E14: =150/3600 -> 0.041666667 | G14: 0.032 | H14: =E14+G14 -> 0.073666667 | I14: =E14*D14 -> 2589.75 | J14: =G14*D14 -> 1988.928 | K14: =SUM(I14:J14) -> 4578.678 | M14: =D14/$X$5 -> 2302 | N14: =D14*H14/$X$5/7.05/$X$4 -> 26.726661 | P14: =N14*0.12 -> 3.2071994 | Q14: =N14+O14+P14 -> 29.933861
E15: 0.033 | G15: 0.008 | H15: =E15+G15 -> 0.041 | I15: =E15*D15 -> 0 | J15: =G15*D15 -> 0 | K15: =SUM(I15:J15) -> 0 | M15: =D15/$X$5 -> 0 | N15: =D15*H15/$X$5/7.05/$X$4 -> 0 | P15: =N15*0.12 -> 0 | Q15: =N15+O15+P15 -> 0
B16: 10170820-001LF | C16: IPC Battery | D16: 2000 | E16: 0.004 | G16: 0.0025 | H16: =E16+G16 -> 0.0065 | I16: =E16*D16 -> 8 | J16: =G16*D16 -> 5 | K16: =SUM(I16:J16) -> 13 | M16: =D16/$X$5 -> 74.074074 | N16: =D16*H16/$X$5/7.05/$X$4 -> 0.075883606 | P16: =N16*0.12 -> 0.0091060327 | Q16: =N16+O16+P16 -> 0.084989639
B17: C10176572-B000R | C17: CSD | D17: 40000 | E17: =0.05225 -> 0.05225 | G17: =80/3600 -> 0.022222222 | H17: =E17+G17 -> 0.074472222 | I17: =E17*D17 -> 2090 | J17: =G17*D17 -> 888.88889 | K17: =SUM(I17:J17) -> 2978.8889 | M17: =D17/$X$5 -> 1481.4815 | N17: =D17*H17/$X$5/7.05/$X$4 -> 17.388372 | P17: =N17*0.12 -> 2.0866046 | Q17: =N17+O17+P17 -> 19.474976
B18: 10174780-001LF | C18: ET30 | D18: =18000+29110 -> 47110 | E18: 0.016 | G18: 0.005 | H18: =E18+G18 -> 0.021 | I18: =E18*D18 -> 753.76 | J18: =G18*D18 -> 235.55 | K18: =SUM(I18:J18) -> 989.31 | M18: =D18/$X$5 -> 1744.8148 | N18: =D18*H18/$X$5/7.05/$X$4 -> 5.7748008 | P18: =N18*0.12 -> 0.6929761 | Q18: =N18+O18+P18 -> 6.4677769
C19: FIT30 | E19: 0.0472222 | G19: 0.0107639 | H19: =E19+G19 -> 0.0579861 | I19: =E19*D19 -> 0 | J19: =G19*D19 -> 0 | K19: =SUM(I19:J19) -> 0 | M19: =D19/$X$5 -> 0 | N19: =D19*H19/$X$5/7.05/$X$4 -> 0 | P19: =N19*0.12 -> 0 | Q19: =N19+O19+P19 -> 0
B20: PWRMRA028 | C20: ET20 | D20: 66400 | E20: =70/3600 -> 0.019444444 | G20: 0.0079861 | H20: =E20+G20 -> 0.027430544 | I20: =E20*D20 -> 1291.1111 | J20: =G20*D20 -> 530.27704 | K20: =SUM(I20:J20) -> 1821.3882 | M20: =D20/$X$5 -> 2459.2593 | N20: =D20*H20/$X$5/7.05/$X$4 -> 10.631808 | P20: =N20*0.12 -> 1.2758169 | Q20: =N20+O20+P20 -> 11.907625
C21: BK350 | D21: 136584 | E21: 0.0100694 | G21: 0.0041667 | H21: =E21+G21 -> 0.0142361 | I21: =E21*D21 -> 1375.3189 | J21: =G21*D21 -> 569.10455 | K21: =SUM(I21:J21) -> 1944.4235 | M21: =D21/$X$5 -> 5058.6667 | N21: =D21*H21/$X$5/7.05/$X$4 -> 11.34999 | P21: =N21*0.12 -> 1.3619988 | Q21: =N21+O21+P21 -> 12.711988
B22: 10170775-170502 | C22: ORV3 CONNECTOR | D22: 15008 | E22: =200/3600 -> 0.055555556 | G22: 0.009 | H22: =E22+G22 -> 0.064555556 | I22: =E22*D22 -> 833.77778 | J22: =G22*D22 -> 135.072 | K22: =SUM(I22:J22) -> 968.84978 | M22: =D22/$X$5 -> 555.85185 | N22: =D22*H22/$X$5/7.05/$X$4 -> 5.6553704 | P22: =N22*0.12 -> 0.67864445 | Q22: =N22+O22+P22 -> 6.3340148
B23: 10182948-Q50001 | C23: ACWHIP Qseries | E23: 0.56 | G23: 0.14 | H23: =E23+G23 -> 0.7 | I23: =E23*D23 -> 0 | J23: =G23*D23 -> 0 | K23: =SUM(I23:J23) -> 0 | M23: =D23/$X$5 -> 0 | N23: =D23*H23/$X$5/7.05/$X$4 -> 0 | P23: =N23*0.12 -> 0 | Q23: =N23+O23+P23 -> 0
B24: 10178161-C7A303 (30 Amps) | C24: ORV3 | E24: =1400/3600 -> 0.38888889 | F24: 0.58 | G24: 0.145 | H24: =E24+G24 -> 0.53388889 | I24: =E24*D24 -> 0 | J24: =G24*D24 -> 0 | K24: =SUM(I24:J24) -> 0 | M24: =D24/$X$5 -> 0 | N24: =D24*H24/$X$5/7.05/$X$4 -> 0 | O24: =N24*(1/6) -> 0 | P24: =(N24+O24)*0.12 -> 0 | Q24: =N24+O24+P24 -> 0
B25: 10176859-001LF | C25: Energypole | D25: 31000 | E25: =84/3600 -> 0.023333333 | G25: 0.03 | H25: =E25+G25 -> 0.053333333 | I25: =E25*D25 -> 723.33333 | J25: =G25*D25 -> 930 | K25: =SUM(I25:J25) -> 1653.3333 | M25: =D25/$X$5 -> 1148.1481 | N25: =D25*H25/$X$5/7.05/$X$4 -> 9.6508381 | P25: =N25*0.12 -> 1.1581006 | Q25: =N25+O25+P25 -> 10.808939
A26: ACWHIP | B26: RPS07007X9-004 (20 Amps) | C26: ORV3 | D26: 15425 | E26: =1000/3600 -> 0.27777778 | G26: =300/3600 -> 0.083333333 | H26: =E26+G26 -> 0.36111111 | I26: =E26*D26 -> 4284.7222 | J26: =G26*D26 -> 1285.4167 | K26: =SUM(I26:J26) -> 5570.1389 | M26: =D26/$X$5 -> 571.2963 | N26: =D26*H26/$X$5/7.05/$X$4 -> 32.514017 | P26: =N26*0.12 -> 3.9016821 | Q26: =N26+O26+P26 -> 36.415699
B27: 10180876-E7C01 | C27: ORV3 | D27: 25092 | E27: =1200/3600 -> 0.33333333 | F27: 0.65 | G27: 0.1453 | H27: =E27+G27 -> 0.47863333 | I27: =E27*D27 -> 8364 | J27: =G27*D27 -> 3645.8676 | K27: =SUM(I27:J27) -> 12009.868 | M27: =D27/$X$5 -> 929.33333 | N27: =D27*H27/$X$5/7.05/$X$4 -> 70.104005 | P27: =N27*0.12 -> 8.4124806 | Q27: =N27+O27+P27 -> 78.516485
B28: 10188304-054F01 | C28: ORV3-100A | D28: 1000 | E28: 0.38 | F28: 0.46 | G28: =500/3600 -> 0.13888889 | H28: =E28+G28 -> 0.51888889 | I28: =E28*D28 -> 380 | J28: =G28*D28 -> 138.88889 | K28: =SUM(I28:J28) -> 518.88889 | M28: =D28/$X$5 -> 37.037037 | N28: =D28*H28/$X$5/7.05/$X$4 -> 3.0288585 | P28: =N28*0.12 -> 0.36346302 | Q28: =N28+O28+P28 -> 3.3923215
B29: 10182665-3RF001LF | C29: ORV3 | E29: 0.065 | G29: 0.009 | H29: =E29+G29 -> 0.074 | I29: =E29*D29 -> 0 | J29: =G29*D29 -> 0 | K29: =SUM(I29:J29) -> 0 | M29: =D29/$X$5 -> 0 | N29: =D29*H29/$X$5/7.05/$X$4 -> 0 | P29: =N29*0.12 -> 0 | Q29: =N29+O29+P29 -> 0
B30: 1018106X-K7000X (K series) | C30: ORV3 | D30: 60000 | E30: =1000/3600 -> 0.27777778 | F30: 0.61 | G30: =280/3600 -> 0.077777778 | H30: =E30+G30 -> 0.35555556 | I30: =E30*D30 -> 16666.667 | J30: =G30*D30 -> 4666.6667 | K30: =SUM(I30:J30) -> 21333.333 | M30: =D30/$X$5 -> 2222.2222 | N30: =D30*H30/$X$5/7.05/$X$4 -> 124.52694 | P30: =(N30+O30)*0.12 -> 14.943233 | Q30: =N30+O30+P30 -> 139.47018
B31: 10176873-19-F140LF | C31: ORV3-60A | D31: 8510 | E31: =3000/3600 -> 0.83333333 | F31: 0.8 | G31: =500/3600 -> 0.13888889 | H31: =E31+G31 -> 0.97222222 | I31: =E31*D31 -> 7091.6667 | J31: =G31*D31 -> 1181.9444 | K31: =SUM(I31:J31) -> 8273.6111 | M31: =D31/$X$5 -> 315.18519 | N31: =D31*H31/$X$5/7.05/$X$4 -> 48.294727 | P31: =N31*0.12 -> 5.7953672 | Q31: =N31+O31+P31 -> 54.090094
B32: 10187162-002LF | C32: ORV3-60A- IC | D32: 14140 | E32: 0.123 | F32: 0.123 | G32: 0.319 | H32: =E32+G32 -> 0.442 | I32: =E32*D32 -> 1739.22 | J32: =G32*D32 -> 4510.66 | K32: =SUM(I32:J32) -> 6249.88 | M32: =D32/$X$5 -> 523.7037 | N32: =D32*H32/$X$5/7.05/$X$4 -> 36.481803 | P32: =N32*0.12 -> 4.3778163 | Q32: =N32+O32+P32 -> 40.859619
B33: 10176873-37-F247LF | C33: ORV3-60A | E33: 0.7 | G33: 0.32 | H33: =E33+G33 -> 1.02 | I33: =E33*D33 -> 0 | J33: =G33*D33 -> 0 | K33: =SUM(I33:J33) -> 0 | M33: =D33/$X$5 -> 0 | N33: =D33*H33/$X$5/7.05/$X$4 -> 0 | P33: =N33*0.12 -> 0 | Q33: =N33+O33+P33 -> 0
B34: 10176873-18-F126LF | C34: ORV3-60A | E34: 0.61 | G34: 0.31 | H34: =E34+G34 -> 0.92 | I34: =E34*D34 -> 0 | J34: =G34*D34 -> 0 | K34: =SUM(I34:J34) -> 0 | M34: =D34/$X$5 -> 0 | N34: =D34*H34/$X$5/7.05/$X$4 -> 0 | P34: =N34*0.12 -> 0 | Q34: =N34+O34+P34 -> 0
A35: BK Cable | B35: 10146534-1EP063LF | C35: BK 100 Cable | D35: 20814 | E35: =0.065-V35 -> 0.046944444 | F35: 0.065 | G35: 0.022 | H35: =E35+G35 -> 0.068944444 | I35: =F35*D35 -> 1352.91 | J35: =G35*D35 -> 457.908 | K35: =SUM(I35:J35) -> 1810.818 | M35: =D35/$X$5 -> 770.88889 | N35: =D35*H35/$X$5/7.05/$X$4 -> 8.3764391 | P35: =N35*0.12 -> 1.0051727 | Q35: =N35+O35+P35 -> 9.3816118 | S35: =15/3600 -> 0.0041666667 | T35: =10/3600 -> 0.0027777778 | U35: =2*20/3600 -> 0.011111111 | V35: =SUM(S35:U35) -> 0.018055556
B36: 10174690-1UF026LF | C36: Oracle | E36: 0.295472 | G36: 0.0277778 | H36: =E36+G36 -> 0.3232498 | I36: =E36*D36 -> 0 | J36: =G36*D36 -> 0 | K36: =SUM(I36:J36) -> 0 | M36: =D36/$X$5 -> 0 | N36: =D36*H36/$X$5/7.05/$X$4 -> 0 | P36: =N36*0.12 -> 0 | Q36: =N36+O36+P36 -> 0
B37: 10170425-9B0040LF | C37: BK350 | D37: 23600 | E37: 0.145 | G37: 0.008 | H37: =E37+G37 -> 0.153 | I37: =E37*D37 -> 3422 | J37: =G37*D37 -> 188.8 | K37: =SUM(I37:J37) -> 3610.8 | M37: =D37/$X$5 -> 874.07407 | N37: =D37*H37/$X$5/7.05/$X$4 -> 21.076963 | P37: =N37*0.12 -> 2.5292356 | Q37: =N37+O37+P37 -> 23.606199
B38: 10174690-1UF011LF | C38: BK220 I/O Cable Assembly | E38: =0.24-V38 -> 0.19333333 | F38: 0.24 | G38: 0.02 | H38: =E38+G38 -> 0.21333333 | I38: =F38*D38 -> 0 | J38: =G38*D38 -> 0 | K38: =SUM(I38:J38) -> 0 | M38: =D38/$X$5 -> 0 | N38: =D38*H38/$X$5/7.05/$X$4 -> 0 | P38: =N38*0.12 -> 0 | Q38: =N38+O38+P38 -> 0 | S38: =36/3600 -> 0.01 | U38: =22*6/3600 -> 0.036666667 | V38: =SUM(S38:U38) -> 0.046666667
B39: 10146534-9B0001LF | C39: BK ZOID | D39: 67000 | E39: =0.302-0.017 -> 0.285 | F39: 0.322 | G39: 0.04 | H39: =E39+G39 -> 0.325 | I39: =F39*D39 -> 21574 | J39: =G39*D39 -> 2680 | K39: =SUM(I39:J39) -> 24254 | M39: =D39/$X$5 -> 2481.4815 | N39: =D39*H39/$X$5/7.05/$X$4 -> 127.10504 | P39: =N39*0.12 -> 15.252605 | Q39: =N39+O39+P39 -> 142.35765
B40: 10170744-9D0001LF | C40: BK250 | D40: 21000 | E40: =0.26-V40 -> 0.20555556 | F40: 0.28 | G40: 0.03 | H40: =E40+G40 -> 0.23555556 | I40: =F40*D40 -> 5880 | J40: =G40*D40 -> 630 | K40: =SUM(I40:J40) -> 6510 | M40: =D40/$X$5 -> 777.77778 | N40: =D40*H40/$X$5/7.05/$X$4 -> 28.874685 | P40: =N40*0.12 -> 3.4649622 | Q40: =N40+O40+P40 -> 32.339647 | S40: =36/3600 -> 0.01 | U40: =20*8/3600 -> 0.044444444 | V40: =SUM(S40:U40) -> 0.054444444
B41: 10174690-1WF149LF | C41: BK220 | D41: 225 | E41: =0.176-V41 -> 0.11711111 | F41: 0.176 | G41: 0.029 | H41: =E41+G41 -> 0.14611111 | I41: =F41*D41 -> 39.6 | J41: =G41*D41 -> 6.525 | K41: =SUM(I41:J41) -> 46.125 | M41: =D41/$X$5 -> 8.3333333 | N41: =D41*H41/$X$5/7.05/$X$4 -> 0.19189797 | P41: =N41*0.12 -> 0.023027756 | Q41: =N41+O41+P41 -> 0.21492572 | S41: =36/3600 -> 0.01 | U41: =22*8/3600 -> 0.048888889 | V41: =SUM(S41:U41) -> 0.058888889
B42: 10172495-1F0139LF | C42: 48V Cable assembly | D42: 27001 | E42: =0.76-V42 -> 0.66111111 | F42: 0.76 | G42: =511/3600 -> 0.14194444 | H42: =E42+G42 -> 0.80305556 | I42: =F42*D42 -> 20520.76 | J42: =G42*D42 -> 3832.6419 | K42: =SUM(I42:J42) -> 24353.402 | M42: =D42/$X$5 -> 1000.037 | N42: =D42*H42/$X$5/7.05/$X$4 -> 126.56979 | O42: =N42/6 -> 21.094964 | P42: =N42*0.12 -> 15.188374 | Q42: =N42+O42+P42 -> 162.85313 | S42: =36/3600 -> 0.01 | U42: =20*16/3600 -> 0.088888889 | V42: =SUM(S42:U42) -> 0.098888889
B43: 10130664-9C0151QLF | C43: BK 200 IO | E43: 0.141 | F43: =E43 -> 0.141 | G43: =120/3600 -> 0.033333333 | H43: =E43+G43 -> 0.17433333 | I43: =F43*D43 -> 0 | J43: =G43*D43 -> 0 | K43: =SUM(I43:J43) -> 0 | M43: =D43/$X$5 -> 0 | N43: =D43*H43/$X$5/7.05/$X$4 -> 0 | P43: =N43*0.12 -> 0 | Q43: =N43+O43+P43 -> 0
B44: 10173913-002LF | C44: Megaflex | D44: 14500 | E44: 0.040972 | F44: =E44 -> 0.040972 | G44: 0.009 | H44: =E44+G44 -> 0.049972 | I44: =F44*D44 -> 594.094 | J44: =G44*D44 -> 130.5 | K44: =SUM(I44:J44) -> 724.594 | M44: =D44/$X$5 -> 537.03704 | N44: =D44*H44/$X$5/7.05/$X$4 -> 4.2296004 | P44: =N44*0.12 -> 0.50755205 | Q44: =N44+O44+P44 -> 4.7371525
B45: Machine Crew (Cutting, Cropping, Welding) | N45: ='Machine crew-Cable'!F13 -> 172 | O45: ='Machine crew-Cable'!G14 -> 28.666667 | P45: ='Machine crew-Cable'!G16 -> 25 | Q45: =N45+O45+P45 -> 225.66667
A46: NPI | B46: 10178119-05P001 | C46: ORV3 8 Cable Assembly | D46: 3000 | E46: 0.54 | G46: =150/3600 -> 0.041666667 | H46: =E46+G46 -> 0.58166667 | I46: =E46*D46 -> 1620 | J46: =G46*D46 -> 125 | K46: =SUM(I46:J46) -> 1745 | M46: =D46/$X$5 -> 111.11111 | N46: =D46*H46/$X$5/7.05/$X$4 -> 10.185915 | P46: =N46*0.12 -> 1.2223098 | Q46: =N46+O46+P46 -> 11.408225
B47: 10194040-C56B09LF | C47: ACWHIP int 60A | E47: 0.74 | G47: =150/3600 -> 0.041666667 | H47: =E47+G47 -> 0.78166667 | I47: =E47*D47 -> 0 | J47: =G47*D47 -> 0 | K47: =SUM(I47:J47) -> 0 | M47: =D47/$X$5 -> 0 | N47: =D47*H47/$X$5/7.05/$X$4 -> 0 | P47: =N47*0.12 -> 0 | Q47: =N47+O47+P47 -> 0
B48: 10185200-D01LF | C48: 5034P2SI | D48: 2000 | E48: 0.277 | G48: =150/3600 -> 0.041666667 | H48: =E48+G48 -> 0.31866667 | I48: =E48*D48 -> 554 | J48: =G48*D48 -> 83.333333 | K48: =SUM(I48:J48) -> 637.33333 | M48: =D48/$X$5 -> 74.074074 | N48: =D48*H48/$X$5/7.05/$X$4 -> 3.7202424 | P48: =N48*0.12 -> 0.44642909 | Q48: =N48+O48+P48 -> 4.1666715
B49: 10173750-04PR01 | C49: 60A Connector | D49: 1500 | E49: 0.026 | G49: =150/3600 -> 0.041666667 | H49: =E49+G49 -> 0.067666667 | I49: =E49*D49 -> 39 | J49: =G49*D49 -> 62.5 | K49: =SUM(I49:J49) -> 101.5 | M49: =D49/$X$5 -> 55.555556 | N49: =D49*H49/$X$5/7.05/$X$4 -> 0.59247585 | P49: =N49*0.12 -> 0.071097102 | Q49: =N49+O49+P49 -> 0.66357295
B50: 10182665-4RF001LF | C50: 60A 5P Connector | D50: 8980 | E50: 0.06 | G50: 0.11 | H50: =E50+G50 -> 0.17 | I50: =E50*D50 -> 538.8 | J50: =G50*D50 -> 987.8 | K50: =SUM(I50:J50) -> 1526.6 | M50: =D50/$X$5 -> 332.59259 | N50: =D50*H50/$X$5/7.05/$X$4 -> 8.9110703 | P50: =N50*0.12 -> 1.0693284 | Q50: =N50+O50+P50 -> 9.9803987
B51: 10178501-100A01LF | C51: Bone crisher | E51: 0.23 | G51: 0.015 | H51: =E51+G51 -> 0.245 | I51: =E51*D51 -> 0 | J51: =G51*D51 -> 0 | K51: =SUM(I51:J51) -> 0 | M51: =D51/$X$5 -> 0 | N51: =D51*H51/$X$5/7.05/$X$4 -> 0 | P51: =N51*0.12 -> 0 | Q51: =N51+O51+P51 -> 0
B52: 10185581-02-002LF | C52: ACWHIP 60A 4P | D52: 8536 | E52: 0.97 | G52: =200/3600 -> 0.055555556 | H52: =E52+G52 -> 1.0255556 | I52: =E52*D52 -> 8279.92 | J52: =G52*D52 -> 474.22222 | K52: =SUM(I52:J52) -> 8754.1422 | M52: =D52/$X$5 -> 316.14815 | N52: =D52*H52/$X$5/7.05/$X$4 -> 51.099683 | P52: =N52*0.12 -> 6.131962 | Q52: =N52+O52+P52 -> 57.231645
B53: 10183597-2-005B1LF | C53: DCWHIP | D53: 1542 | E53: =5900/3600 -> 1.6388889 | G53: 0.11 | H53: =E53+G53 -> 1.7488889 | I53: =E53*D53 -> 2527.1667 | J53: =G53*D53 -> 169.62 | K53: =SUM(I53:J53) -> 2696.7867 | M53: =D53/$X$5 -> 57.111111 | N53: 60 | P53: =N53*0.12 -> 7.2 | Q53: =N53+O53+P53 -> 67.2
B55: Total | I55: =SUM(I3:I37) -> 138412.16 | J55: =SUM(J3:J37) -> 37758.267 | K55: =SUM(K3:K37) -> 176170.43 | N55: =SUM(N3:N53) -> 1494.1606 | O55: =SUM(O3:O53) -> 92.729912 | P55: =SUM(P3:P53) -> 184.62429
N56: =N55+O55+P55 -> 1771.5148 | Q56: =SUM(Q3:Q55) -> 1771.5148
G65: 81
G66: =160-19 -> 141

Sheet Sheet7

Sheet Machine crew-Cable
D3: Sunday working
D5: Operator | E5: 35 | F5: =E5*3 -> 105
D6: Twisting | E6: 3 | F6: 18
D7: cable cutting | F7: 6 | I7: Teton | J7: 18
D8: Cropping | F8: 8 | I8: BK300 | J8: 3
D9: Support | F9: =J11 -> 35 | I9: Meta | J9: 2
I10: 48v/ Nvdia | J10: 12
J11: =SUM(J5:J10) -> 35
F13: =SUM(F5:F12) -> 172
F14: Sunday | G14: =(F13)/6 -> 28.666667
F15: total | G15: =ROUNDUP(G14+F13,0) -> 201
F16: LR | G16: =ROUNDUP(G15*0.12,0) -> 25
F17: total incl LR | G17: =G16+G15 -> 226

Sheet Supporting HC details
F5: Supporting DL
G6: BK Cable | H6: BK Revised | I6: AC Cable | J6: Connector
F7: Lead | G7: 15 | H7: 20 | I7: 12 | J7: 8 | M7: =2100/55 -> 38.181818
F8: Store work | G8: 6 | H8: 10 | J8: 3
F9: Technician | G9: 4 | H9: 4 | I9: 6 | J9: 12
F10: Scrap work and data entry | G10: 7 | H10: 7 | I10: 7 | J10: 3
F12: Supp: Total | G12: =SUM(G7:G11) -> 32 | H12: =SUM(H7:H11) -> 41 | I12: =SUM(I7:I11) -> 25 | J12: =SUM(J7:J11) -> 26 | K12: =SUM(H12:J12) -> 92
F14: Total | G14: =K12 -> 92

Sheet Capacity
A1: Current capacity
A2: BK300 | B2: Weld type | C2: Qty/FG | E2: CT | G2: Total CT | H2: No: of M/c | I2: O/t-Shift | J2: O/t-Day | K2: FG/Day | L2: Monthly capacity
B3: Metal welding | C3: 4 | E3: 15 | G3: =E3*C3 -> 60 | H3: 2 | I3: =8/(G3/3600)*H3 -> 960 | J3: =I3*3*0.8 -> 2304 | K3: =MIN(J3:J5) -> 1645.7143 | L3: =K3*25 -> 41142.857
B4: Wire welding | C4: 4 | E4: 15 | G4: =E4*C4 -> 60 | H4: 2 | I4: =8/(G4/3600)*H4 -> 960 | J4: =I4*3*0.8 -> 2304
B5: Z welding | C5: 4 | E5: 21 | G5: =E5*C5 -> 84 | H5: 2 | I5: =8/(G5/3600)*H5 -> 685.71429 | J5: =I5*3*0.8 -> 1645.7143
A6: Teton | B6: Wire welding | C6: 4 | E6: 20 | G6: =C6*E6 -> 80 | I6: =8/(G6/3600)*H6 -> 0 | J6: =I6*3*0.8 -> 0 | K6: =MIN(J6:J7) -> 0 | L6: =K6*26 -> 0
B7: Metal welding | C7: 4 | E7: 15 | G7: =C7*E7 -> 60 | I7: =8/(G7/3600)*H7 -> 0 | J7: =I7*3*0.8 -> 0
A8: Meta-Facebook | B8: Metal welding | C8: 2 | E8: 13 | G8: =E8*C8 -> 26 | H8: 1 | I8: =8/(G8/3600)*H8 -> 1107.6923 | J8: =I8*3*0.8 -> 2658.4615 | K8: =MIN(J8:J9) -> 2658.4615 | L8: =K8*26 -> 69120
B9: 5 Wire welding | C9: 2 | E9: 25 | G9: =E9*C9 -> 50 | H9: 2 | I9: =8/(G9/3600)*H9 -> 1152 | J9: =I9*3*0.8 -> 2764.8
A10: Tesla | B10: Wire welding | C10: 1 | E10: 40 | G10: =E10*C10 -> 40 | H10: 2 | I10: =8/(G10/3600)*H10 -> 1440 | J10: =I10*3*0.8 -> 3456 | K10: =J10 -> 3456 | L10: =K10*26 -> 89856
A12: Total | H12: =SUM(H3:H11) -> 11 | L12: =SUM(L3:L11) -> 200118.86
A15: Capacity by Q4-2024
A16: BK300 | B16: Weld type | C16: Qty/FG | E16: CT | G16: Total CT | H16: No: of M/c | I16: O/t-Shift | J16: O/t-Day | K16: FG/Day | L16: Monthly capacity
B17: Metal welding | C17: 4 | E17: 15 | G17: =E17*C17 -> 60 | H17: 2 | I17: =8/(G17/3600)*H17 -> 960 | J17: =I17*3*0.8 -> 2304 | K17: =MIN(J17:J19) -> 1920 | L17: =K17*26 -> 49920 | N17: =L26-L12 -> -4156.6753
B18: Wire welding | C18: 4 | E18: 15 | G18: =E18*C18 -> 60 | H18: 2 | I18: =8/(G18/3600)*H18 -> 960 | J18: =I18*3*0.8 -> 2304 | N18: =N17/L12 -> -0.020771033
B19: Z welding | C19: 4 | E19: 18 | G19: =E19*C19 -> 72 | H19: 2 | I19: =8/(G19/3600)*H19 -> 800 | J19: =I19*3*0.8 -> 1920 | N19: =N18 -> -0.020771033
A20: Teton | B20: Wire welding | C20: 4 | E20: 20 | G20: =C20*E20 -> 80 | H20: 1 | I20: =8/(G20/3600)*H20 -> 360 | J20: =I20*3*0.8 -> 864 | K20: =MIN(J20:J21) -> 864 | L20: =K20*26 -> 22464
B21: Metal welding | C21: 4 | E21: 15 | G21: =C21*E21 -> 60 | H21: 1 | I21: =8/(G21/3600)*H21 -> 480 | J21: =I21*3*0.8 -> 1152
A22: Meta-Facebook | B22: Metal welding | C22: 2 | E22: 13 | G22: =E22*C22 -> 26 | H22: 1 | I22: =8/(G22/3600)*H22 -> 1107.6923 | J22: =I22*3*0.8 -> 2658.4615 | K22: =MIN(J22:J23) -> 2658.4615 | L22: =K22*26 -> 69120
B23: 5 Wire welding | C23: 2 | E23: 25 | G23: =E23*C23 -> 50 | H23: 2 | I23: =8/(G23/3600)*H23 -> 1152 | J23: =I23*3*0.8 -> 2764.8
A24: Tesla | B24: Wire welding | C24: 1 | E24: 33 | G24: =E24*C24 -> 33 | H24: 1 | I24: =8/(G24/3600)*H24 -> 872.72727 | J24: =I24*3*0.8 -> 2094.5455 | K24: =J24 -> 2094.5455 | L24: =K24*26 -> 54458.182
A26: Total | H26: =SUM(H17:H25) -> 12 | L26: =SUM(L17:L25) -> 195962.18
A28: Capacity by Q2-2025
A29: BK300 | B29: Weld type | C29: Qty/FG | D29: Old-CT | E29: New-CT | F29: CT Improvement | G29: Total CT | H29: No: of M/c | I29: O/t-Shift | J29: O/t-Day | K29: FG/Day | L29: Monthly capacity | M29: Remark | N29: June -Plan
B30: Metal welding | C30: 4 | D30: 12 | E30: 9 | F30: =(D30-E30)/D30 -> 0.25 | G30: =E30*C30 -> 36 | H30: 2.5 | I30: =8/(G30/3600)*H30 -> 2000 | J30: =I30*3*0.8 -> 4800 | K30: =MIN(J30:J32) -> 2541.1765 | L30: =K30*30 -> 76235.294 | M30: Machine running 24x7 | N30: 70000
B31: Wire welding | C31: 4 | D31: 25 | E31: 17 | F31: =(D31-E31)/D31 -> 0.32 | G31: =E31*C31 -> 68 | H31: 2.5 | I31: =8/(G31/3600)*H31 -> 1058.8235 | J31: =I31*3*0.8 -> 2541.1765
B32: Z welding | C32: 4 | D32: 18 | E32: 17 | F32: =(D32-E32)/D32 -> 0.055555556 | G32: =E32*C32 -> 68 | H32: 3 | I32: =8/(G32/3600)*H32 -> 1270.5882 | J32: =I32*3*0.8 -> 3049.4118
A33: Meta | B33: Metal welding | C33: 2 | D33: 12 | E33: 9 | F33: =(D33-E33)/D33 -> 0.25 | G33: =E33*C33 -> 18 | H33: 1 | I33: =8/(G33/3600)*H33 -> 1600 | J33: =I33*3*0.75 -> 3600 | K33: =MIN(J33:J34) -> 1800 | L33: =K33*30 -> 54000 | M33: Machine sharing for Meta and 438LF.Machine running 24x7 | N33: 53400
B34: 5 Wire welding | C34: 2 | D34: 18 | E34: 18 | F34: =(D34-E34)/D34 -> 0 | G34: =E34*C34 -> 36 | H34: 1 | I34: =8/(G34/3600)*H34 -> 800 | J34: =I34*3*0.75 -> 1800
B35: Wire welding | C35: 1 | E35: 33 | G35: =E35*C35 -> 33 | I35: =8/(G35/3600)*H35 -> 0 | J35: =I35*3*0.8 -> 0 | K35: =J35 -> 0 | L35: =K35*25 -> 0 | M35: Starting from Mar-13th after completion of Meta-2000/day. | N35: 31680 | O35: =N35/3600 -> 8.8
A37: Teton 2 | B37: LP welding | C37: 16 | D37: 16 | E37: 12 | F37: =(D37-E37)/D37 -> 0.25 | G37: =E37*C37 -> 192 | H37: 4 | I37: =8/(G37/3600)*H37 -> 600 | J37: =I37*3*0.8 -> 1440 | K37: =MIN(J37:J38) -> 1440 | L37: =K37*30 -> 43200 | M37: Machine running 24x7 | N37: 40000
B38: HP welding | C38: 4 | D38: 53 | E38: 22 | F38: =(D38-E38)/D38 -> 0.58490566 | G38: =E38*C38 -> 88 | H38: 2 | I38: =8/(G38/3600)*H38 -> 654.54545 | J38: =I38*3*0.8 -> 1570.9091
A39: Tesla | B39: Wire to metal welding | C39: 1 | E39: 15 | F39: =(D39-E39)/D39 -> #DIV/0! | G39: =E39*C39 -> 15 | H39: 0.5 | I39: =8/(G39/3600)*H39 -> 960 | J39: =I39*3*0.8 -> 2304 | K39: =MIN(J39:J40) -> 1728 | L39: =K39*26 -> 44928 | M39: Machine sharing for Tesla,1QLF,NPD | N39: 32000
B40: Wire to metal welding | C40: 1 | E40: 20 | F40: =(D40-E40)/D40 -> #DIV/0! | G40: =E40*C40 -> 20 | H40: 0.5 | I40: =8/(G40/3600)*H40 -> 720 | J40: =I40*3*0.8 -> 1728
A41: Total | H41: =SUM(H30:H40) -> 17 | L41: =SUM(L30:L40) -> 218363.29
A43: Additional points
A44: 17 Welding machine considered
A45: All machine need to run 24x7
A51: Capacity by Q2-2025
A52: BK300 | B52: Weld type | C52: Qty/FG | D52: Old-ct | E52: CT | F52: CT Improvement | G52: Total CT | H52: No: of M/c | I52: O/t-Shift | J52: O/t-Day | K52: FG/Day | L52: Monthly capacity
B53: Metal welding | C53: 4 | D53: 12 | E53: 12 | F53: =(D53-E53)/D53 -> 0 | G53: =E53*C53 -> 48 | H53: 2 | I53: =8/(G53/3600)*H53 -> 1200 | J53: =I53*3*0.8 -> 2880 | K53: =MIN(J53:J55) -> 2304 | L53: =K53*25 -> 57600
B54: Wire welding | C54: 4 | D54: 25 | E54: 15 | F54: =(D54-E54)/D54 -> 0.4 | G54: =E54*C54 -> 60 | H54: 2 | I54: =8/(G54/3600)*H54 -> 960 | J54: =I54*3*0.8 -> 2304
B55: Z welding | C55: 4 | D55: 18 | E55: 15 | F55: =(D55-E55)/D55 -> 0.16666667 | G55: =E55*C55 -> 60 | H55: 3 | I55: =8/(G55/3600)*H55 -> 1440 | J55: =I55*3*0.8 -> 3456
A56: Meta | B56: Metal welding | C56: 2 | D56: 12 | E56: 9 | F56: =(D56-E56)/D56 -> 0.25 | G56: =E56*C56 -> 18 | H56: 1 | I56: =8/(G56/3600)*H56 -> 1600 | J56: =I56*3*0.8 -> 3840 | K56: =MIN(J56:J57) -> 2032.9412 | L56: =K56*26 -> 52856.471
B57: 5 Wire welding | C57: 2 | D57: 18 | E57: 17 | F57: =(D57-E57)/D57 -> 0.055555556 | G57: =E57*C57 -> 34 | H57: 1 | I57: =8/(G57/3600)*H57 -> 847.05882 | J57: =I57*3*0.8 -> 2032.9412
A58: Tesla | B58: Wire welding | C58: 1 | E58: 20 | G58: =E58*C58 -> 20 | I58: =8/(G58/3600)*H58 -> 0 | J58: =I58*3*0.8 -> 0 | K58: =J58 -> 0 | L58: =K58*25 -> 0
C59: 1 | E59: 20 | G59: 18 | I59: =8/(G59/3600)*H59 -> 0 | J59: =I59*3*0.8 -> 0
A60: Teton 2 | B60: LP welding | C60: 16 | D60: 16 | E60: 12 | F60: =(D60-E60)/D60 -> 0.25 | G60: =E60*C60 -> 192 | H60: 3 | I60: =8/(G60/3600)*H60 -> 450 | J60: =I60*3*0.85 -> 1147.5 | K60: =MIN(J60:J61) -> 1147.5 | L60: =K60*25 -> 28687.5
B61: HP welding | C61: 4 | D61: 53 | E61: 22 | F61: =(D61-E61)/D61 -> 0.58490566 | G61: =E61*C61 -> 88 | H61: 2 | I61: =8/(G61/3600)*H61 -> 654.54545 | J61: =I61*3*0.85 -> 1669.0909 | N61: =3600/56 -> 64.285714
A62: Nvidia | B62: LP welding | C62: 4 | E62: 17 | F62: =(D62-E62)/D62 -> #DIV/0! | G62: =E62*C62 -> 68 | I62: =8/(G62/3600)*H62 -> 0 | J62: =I62*3*0.8 -> 0 | K62: =MIN(J62:J63) -> 0 | L62: =K62*26 -> 0
B63: HP wedling | C63: 2 | E63: 17 | F63: =(D63-E63)/D63 -> #DIV/0! | G63: =E63*C63 -> 34 | I63: =8/(G63/3600)*H63 -> 0 | J63: =I63*3*0.8 -> 0
N64: =N61*7*3 -> 1350
A65: Total | H65: =SUM(H53:H64) -> 14 | N65: =N64*26 -> 35100
N66: =85000/N65 -> 2.4216524

Sheet Sheet4
A3: Row Labels | B3: Sum of Quantity
A4: 552PWBVR | B4: 96426
A5: Grand Total | B5: 96426
H6: PB+RAH | I6: =60000+40000 -> 100000 | J6: =I6/4500 -> 22.222222
H7: PB+VTR | I7: 15974 | J7: =I7/6000 -> 2.6623333
G8: 1 | H8: PBRAH | I8: =30000+111496 -> 141496 | J8: =I8/4500 -> 31.443556
G9: 1 | H9: PBVTR | I9: 96426 | J9: =I9/6000 -> 16.071
H10: PBRAR | I10: 30000

Sheet Sheet2
A3: Row Labels | B3: Sum of Quantity | C3: Sum of Value
A4: 346PB+RH | B4: 55906 | C4: 91.305192
A5: 346PB+VR | B5: 12446 | C5: 21.281308
A6: 352ACIPC | B6: 2464 | C6: 26.498214
A7: 355BK100 | B7: 58000 | C7: 220.51281
A8: 355BK300 | B8: 70000 | C8: 944.59726
A9: 355BK50C | B9: 27650 | C9: 294.5742
A10: 355BRKCA | B10: 81804 | C10: 321.73705
A11: 355METCA | B11: 3710 | C11: 85
A12: 355TSLCA | B12: 22040 | C12: 122.5776
A13: 355TT2CA | B13: 40000 | C13: 2059.2025
A14: 356ACICB | B14: 10000 | C14: 235.25216
A15: 356MC54I | B15: 5150 | C15: 2.1453156
... A33: 612FIT30 | B33: 2980 | C33: 16.395457
A34: (blank) | C34: 7230.8795
A35: Grand Total | B35: 1526794 | C35: 14461.759

Sheet PB
H1: =#REF!*2 -> #REF!
G2: Night Shift | H2: 8
G3: Total | H3: =H2+H1 -> #REF!
H4: =ROUNDUP(H3*0.12,0) -> #REF!
C5: ='PN-workout file'!#REF!+'PN-workout file'!#REF!+'PN-workout file'!#REF!+'PN-workout file'!#REF!+'PN-workout file'!N15+'PN-workout file'!P15+'PN-workout file'!#REF!+'PN-workout file'!#REF!+'PN-workout file'!N14+'PN-workout file'!P14+'PN-workout file'!N25+'PN-workout file'!P25+'PN-workout file'!#REF!+'PN-workout file'!#REF!+'PN-workout file'!N22+'PN-workout file'!P22+'PN-workout file'!#REF!+'PN-workout file'!N20+'PN-workout file'!P20+'PN-workout file'!N19+'PN-workout file'!P19+'PN-workout file'!P18+'PN-workout file'!N18+'PN-workout file'!N9+'PN-workout file'!P9+'PN-workout file'!N8+PB!A7 -> #REF! | H5: =H3+H4 -> #REF!
A7: Power Blade
A8: Sl. No. | B8: Machine | C8: Machine Operator | D8: Quality Control | E8: Grid Checker | F8: Vision System | G8: Packing | H8: Cover Assembly | I8: Shifts Operated | J8: Required HC | K8: Leave Reserve @ 10% | L8: Sunday working | M8: Total
A9: 1 | B9: PB + RAH | C9: 2 | D9: 1 | E9: 1 | F9: 1 | G9: 1 | H9: 2 | I9: 3 | J9: =(SUM(C9:F9)+G9+H9)*I9 -> 24 | K9: =J9*0.12 -> 2.88 | L9: =J9/6 -> 4 | M9: =J9+K9+L9 -> 30.88
A10: 2 | B10: PB RAH | C10: 2 | D10: 1 | E10: 1 | F10: 1 | I10: 3 | J10: =(SUM(C10:F10)+G9+H9)*I10 -> 24 | K10: =J10*0.12 -> 2.88 | L10: 0 | M10: =J10+K10+L10 -> 26.88
A11: 3 | B11: PB + VTR | C11: 2 | D11: 1 | E11: 1 | F11: 1 | G11: 1 | I11: 3 | J11: =(SUM(C11:F11)+G11+H9)*I11 -> 24 | K11: =J11*0.12 -> 2.88 | L11: =J11/6 -> 4 | M11: =J11+K11+L11 -> 30.88
A12: 4 | B12: PB VTR | C12: 2 | D12: 1 | E12: 1 | F12: 1 | I12: 2 | J12: =(SUM(C12:F12)+G9+H9)*I12 -> 16 | K12: =J12*0.12 -> 1.92 | L12: 0 | M12: =J12+K12+L12 -> 17.92
A13: 5 | B13: PBU RAR | C13: 2 | D13: 1 | E13: 1 | F13: 1 | I13: 3 | J13: =(SUM(C13:F13)+G10+H10)*I13 -> 15 | K13: =J13*0.12 -> 1.8 | L13: 0 | M13: =J13+K13+L13 -> 16.8
A14: 6 | B14: Airmax | C14: 6
A15: Total HC for PB | M15: =SUM(M9:M14)+C14 -> 129.36
O25: Power Blade
O26: Sl. No. | P26: Machine | Q26: Machine Operator | R26: Quality Control | S26: Grid Checker | T26: Vision System | U26: Packing | V26: Cover Assembly | W26: Shifts Operated | X26: Additional personnel for night Shift | Y26: Leave Reserve @ 10% | Z26: Remarks | AB26: Sunday working
O27: 1 | P27: PB + RAH | Q27: 2 | R27: 1 | S27: 1 | T27: 1 | U27: 1 | V27: 2 | W27: 2 | X27: =SUM(Q27:T28)+Q30+R30+S30+T30+U27+U29+V27 -> 19 | Y27: =ROUNDUP((SUM(Q27:V31)*2+X27)*0.12,0) -> 9
O28: 2 | P28: PB RAH | Q28: 2 | R28: 1 | S28: 1 | T28: 1
O29: 3 | P29: PB + VTR | Q29: 2 | R29: 1 | S29: 1 | T29: 1 | U29: 1 | W29: 1
O30: 4 | P30: PB VTR | Q30: 2 | R30: 1 | S30: 1 | T30: 1 | W30: 3
O31: 5 | P31: PB RAR
O32: Total HC for PB | AA32: =SUM(Q27:V30)*W27+X27+Y27+Q31 -> 76

Sheet PN-workout file (2)
A1: Item Number | B1: Description | C1: Qty. | D1: CT | H1: Hrs. | L1: HC/ Day | M1: Sunday working-HC | N1: LR @12% | P1: Remarks
D2: MA | E2: MA | F2: I&P | G2: Total | H2: MA | I2: I&P | J2: Total | K2: Target/day | O2: Total HC | Q2: Wire cutting | R2: Cropping | S2: Welding | T2: Sum
A3: 10130664-9RF438LF | B3: Meta/Amazon | C3: 28980 | D3: =0.18-(T3) -> 0.1425 | E3: =0.18 -> 0.18 | F3: 0.03125 | G3: =D3+F3 -> 0.17375 | H3: =E3*C3 -> 5216.4 | I3: =F3*C3 -> 905.625 | J3: =SUM(H3:I3) -> 6122.025 | K3: =C3/$X$5 -> 1207.5 | L3: =C3*G3/$X$5/7.05/$X$4 -> 33.817396 | N3: =L3*0.12 -> 4.0580875 | O3: =L3+M3+N3 -> 37.875484 | Q3: =50/3600 -> 0.013888889 | R3: =20/3600 -> 0.0055555556 | S3: =65/3600 -> 0.018055556 | T3: =SUM(Q3:S3) -> 0.0375
A4: 10158287-9RF034HF | B4: BK300 | C4: 47660 | D4: =(0.225)-(T4) -> 0.16361111 | E4: =0.225 -> 0.225 | F4: =0.0413888*0.8 -> 0.03311104 | G4: =D4+F4 -> 0.19672215 | H4: =E4*C4 -> 10723.5 | I4: =F4*C4 -> 1578.0722 | J4: =SUM(H4:I4) -> 12301.572 | K4: =C4/$X$5 -> 1985.8333 | L4: =C4*G4/$X$5/7.05/$X$4 -> 62.968634 | N4: =L4*0.12 -> 7.5562361 | O4: =L4+M4+N4 -> 70.52487 | Q4: =31/3600 -> 0.0086111111 | R4: =10/3600 -> 0.0027777778 | S4: =180/3600 -> 0.05 | T4: =SUM(Q4:S4) -> 0.061388889 | W4: DL % | X4: 0.88
A5: 10162405-1S2009LF | B5: BK50 | C5: 14700 | D5: 0.099 | E5: =0.1 -> 0.1 | F5: 0.00807 | G5: =D5+F5 -> 0.10707 | H5: =E5*C5 -> 1470 | I5: =F5*C5 -> 118.629 | J5: =SUM(H5:I5) -> 1588.629 | K5: =C5/$X$5 -> 612.5 | L5: =C5*G5/$X$5/7.05/$X$4 -> 10.57066 | N5: =(L5*0.12) -> 1.2684792 | O5: =L5+M5+N5 -> 11.839139 | W5: Wokring days | X5: 24
A6: RPS07007X9-004 (20 Amps) | B6: ORV3 | C6: =5600 -> 5600 | D6: =1000/3600 -> 0.27777778 | F6: =300/3600 -> 0.083333333 | G6: =D6+F6 -> 0.36111111 | H6: =D6*C6 -> 1555.5556 | I6: =F6*C6 -> 466.66667 | J6: =SUM(H6:I6) -> 2022.2222 | K6: =C6/$X$5 -> 233.33333 | L6: =C6*G6/$X$5/7.05/$X$4 -> 13.581441 | N6: =L6*0.12 -> 1.6297729 | O6: =L6+M6+N6 -> 15.211214
A7: 10165987-101LF | B7: socket body(Z4/Z2) | C7: 263000 | D7: 0.0079861 | F7: 0.0053833 | G7: =SUM(D7:F7) -> 0.0133694 | H7: =D7*C7 -> 2100.3443 | I7: =F7*C7 -> 1415.8079 | J7: =SUM(H7:I7) -> 3516.1522 | K7: =C7/$X$5 -> 10958.333 | L7: =C7*G7/$X$5/7.05/$X$4 -> 23.61482 | N7: =L7*0.12 -> 2.8337784 | O7: =L7+M7+N7 -> 26.448598
A8: 10166013-101LF | B8: Microsoft | D8: 0.0069861 | F8: 0.0009056 | G8: =SUM(D8:F8) -> 0.0078917 | H8: =D8*C8 -> 0 | I8: =F8*C8 -> 0 | J8: =SUM(H8:I8) -> 0 | K8: =C8/$X$5 -> 0 | L8: =C8*G8/$X$5/7.05/$X$4 -> 0 | N8: =ROUNDUP(L8*0.12,0) -> 0 | O8: =L8+M8+N8 -> 0
A9: 10157266-001LF | B9: BK200 XP | D9: 0.01818 | F9: 0.00964 | G9: =SUM(D9:F9) -> 0.02782 | H9: =D9*C9 -> 0 | I9: =F9*C9 -> 0 | J9: =SUM(H9:I9) -> 0 | K9: =C9/$X$5 -> 0 | L9: =C9*G9/$X$5/7.05/$X$4 -> 0 | N9: =L9*0.12 -> 0 | O9: =L9+M9+N9 -> 0
A10: 10130664-9D0354LF | B10: TESLA | C10: 16560 | D10: =0.17-T10 -> 0.15194444 | E10: 0.17 | F10: 0.03 | G10: =D10+F10 -> 0.18194444 | H10: =E10*C10 -> 2815.2 | I10: =F10*C10 -> 496.8 | J10: =SUM(H10:I10) -> 3312 | K10: =C10/$X$5 -> 690 | L10: =C10*G10/$X$5/7.05/$X$4 -> 20.235601 | N10: =L10*0.12 -> 2.4282721 | O10: =L10+M10+N10 -> 22.663873 | Q10: =15/3600 -> 0.0041666667 | R10: =10/3600 -> 0.0027777778 | S10: =40/3600 -> 0.011111111 | T10: =SUM(Q10:S10) -> 0.018055556
A11: 10170425-1RF033LF | B11: TETON2 | C11: 31700 | D11: =0.365-T11 -> 0.22888889 | E11: 0.395 | F11: 0.0611 | G11: =D11+F11 -> 0.28998889 | H11: =E11*C11 -> 12521.5 | I11: =F11*C11 -> 1936.87 | J11: =SUM(H11:I11) -> 14458.37 | K11: =C11/$X$5 -> 1320.8333 | L11: =C11*G11/$X$5/7.05/$X$4 -> 61.738715 | N11: =L11*0.12 -> 7.4086459 | O11: =L11+M11+N11 -> 69.147361 | Q11: =90/3600 -> 0.025 | R11: =100/3600 -> 0.027777778 | S11: =300/3600 -> 0.083333333 | T11: =SUM(Q11:S11) -> 0.13611111
A12: 10174780-001LF | B12: ET30 | D12: 0.016 | F12: 0.005 | G12: =SUM(D12:F12) -> 0.021 | H12: =D12*C12 -> 0 | I12: =F12*C12 -> 0 | J12: =SUM(H12:I12) -> 0 | K12: =C12/$X$5 -> 0 | L12: =C12*G12/$X$5/7.05/$X$4 -> 0 | N12: =L12*0.12 -> 0 | O12: =L12+M12+N12 -> 0
B13: FIT30 | D13: 0.0472222 | F13: 0.0107639 | G13: =SUM(D13:F13) -> 0.0579861 | H13: =D13*C13 -> 0 | I13: =F13*C13 -> 0 | J13: =SUM(H13:I13) -> 0 | K13: =C13/$X$5 -> 0 | L13: =C13*G13/$X$5/7.05/$X$4 -> 0 | N13: =L13*0.12 -> 0 | O13: =L13+M13+N13 -> 0
A14: PWRMRA028 | B14: ET20 | C14: =14400+4000 -> 18400 | D14: 0.0414028 | F14: 0.0079861 | G14: =SUM(D14:F14) -> 0.0493889 | H14: =D14*C14 -> 761.81152 | I14: =F14*C14 -> 146.94424 | J14: =SUM(H14:I14) -> 908.75576 | K14: =C14/$X$5 -> 766.66667 | L14: =C14*G14/$X$5/7.05/$X$4 -> 6.103292 | N14: =L14*0.12 -> 0.73239504 | O14: =L14+M14+N14 -> 6.835687
B15: BK350 | C15: 123000 | D15: 0.0100694 | F15: 0.0041667 | G15: =SUM(D15:F15) -> 0.0142361 | H15: =D15*C15 -> 1238.5362 | I15: =F15*C15 -> 512.5041 | J15: =SUM(H15:I15) -> 1751.0403 | K15: =C15/$X$5 -> 5125 | L15: =C15*G15/$X$5/7.05/$X$4 -> 11.760157 | N15: =L15*0.12 -> 1.4112188 | O15: =L15+M15+N15 -> 13.171376
A16: 10170775-170502 | B16: ORV3 CONNECTOR | C16: 20720 | D16: 0.05 | F16: 0.009 | G16: =SUM(D16:F16) -> 0.059 | H16: =D16*C16 -> 1036 | I16: =F16*C16 -> 186.48 | J16: =SUM(H16:I16) -> 1222.48 | K16: =C16/$X$5 -> 863.33333 | L16: =C16*G16/$X$5/7.05/$X$4 -> 8.2102944 | N16: =L16*0.12 -> 0.98523533 | O16: =L16+M16+N16 -> 9.1955298
A17: 10182948-Q50001 | B17: ACWHIP Qseries | D17: 0.56 | F17: 0.14 | G17: =SUM(D17:F17) -> 0.7 | H17: =D17*C17 -> 0 | I17: =F17*C17 -> 0 | J17: =SUM(H17:I17) -> 0 | K17: =C17/$X$5 -> 0 | L17: =C17*G17/$X$5/7.05/$X$4 -> 0 | N17: =L17*0.12 -> 0 | O17: =L17+M17+N17 -> 0
A18: 10178161-C7A303 (30 Amps) | B18: ORV3 | C18: =21648 -> 21648 | D18: =1400/3600 -> 0.38888889 | F18: 0.145 | G18: =SUM(D18:F18) -> 0.53388889 | H18: =D18*C18 -> 8418.6667 | I18: =F18*C18 -> 3138.96 | J18: =SUM(H18:I18) -> 11557.627 | K18: =C18/$X$5 -> 902 | L18: =C18*G18/$X$5/7.05/$X$4 -> 77.622143 | M18: =L18*(1/6) -> 12.937024 | N18: =(L18+M18)*0.12 -> 10.8671 | O18: =L18+M18+N18 -> 101.42627
A19: 10170827-07P002 | B19: ORV3 | C19: 0 | D19: 0.08 | F19: 0.03 | G19: =SUM(D19:F19) -> 0.11 | H19: =D19*C19 -> 0 | I19: =F19*C19 -> 0 | J19: =SUM(H19:I19) -> 0 | K19: =C19/$X$5 -> 0 | L19: =C19*G19/$X$5/7.05/$X$4 -> 0 | N19: =L19*0.12 -> 0 | O19: =L19+M19+N19 -> 0
A20: 10180876-E7C01 | B20: ORV3 | D20: 0.516 | F20: 0.1453 | G20: =SUM(D20:F20) -> 0.6613 | H20: =D20*C20 -> 0 | I20: =F20*C20 -> 0 | J20: =SUM(H20:I20) -> 0 | K20: =C20/$X$5 -> 0 | L20: =C20*G20/$X$5/7.05/$X$4 -> 0 | M20: =L20*(1/6) -> 0 | N20: =L20*0.12 -> 0 | O20: =L20+M20+N20 -> 0
A21: 10188304-054F01 | B21: ORV3-100A | C21: 1000 | D21: 0.42 | F21: =500/3600 -> 0.13888889 | G21: =SUM(D21:F21) -> 0.55888889 | H21: =D21*C21 -> 420 | I21: =F21*C21 -> 138.88889 | J21: =SUM(H21:I21) -> 558.88889 | K21: =C21/$X$5 -> 41.666667 | L21: =C21*G21/$X$5/7.05/$X$4 -> 3.7535521 | N21: =L21*0.12 -> 0.45042625 | O21: =L21+M21+N21 -> 4.2039783
A22: 10182476-71A801 | B22: ORV3 | C22: 16000 | D22: 0.3911 | F22: 0.0427 | G22: =SUM(D22:F22) -> 0.4338 | H22: =D22*C22 -> 6257.6 | I22: =F22*C22 -> 683.2 | J22: =SUM(H22:I22) -> 6940.8 | K22: =C22/$X$5 -> 666.66667 | L22: =C22*G22/$X$5/7.05/$X$4 -> 46.615087 | N22: =L22*0.12 -> 5.5938104 | O22: =L22+M22+N22 -> 52.208897
A23: 1018106X-K7000X (K series) | B23: ORV3 | C23: 19000 | D23: =1200/3600 -> 0.33333333 | F23: =280/3600 -> 0.077777778 | G23: =SUM(D23:F23) -> 0.41111111 | H23: =D23*C23 -> 6333.3333 | I23: =F23*C23 -> 1477.7778 | J23: =SUM(H23:I23) -> 7811.1111 | K23: =C23/$X$5 -> 791.66667 | L23: =C23*G23/$X$5/7.05/$X$4 -> 52.460181 | M23: 9 | N23: =(L23+M23)*0.12 -> 7.3752217 | O23: =L23+M23+N23 -> 68.835403
A24: 10176873-19-F140LF | B24: ORV3-60A | C24: 9284 | D24: =3300/3600 -> 0.91666667 | F24: =500/3600 -> 0.13888889 | G24: =SUM(D24:F24) -> 1.0555556 | H24: =D24*C24 -> 8510.3333 | I24: =F24*C24 -> 1289.4444 | J24: =SUM(H24:I24) -> 9799.7778 | K24: =C24/$X$5 -> 386.83333 | L24: =C24*G24/$X$5/7.05/$X$4 -> 65.81626 | M24: =L24*(1/6) -> 10.969377 | N24: =L24*0.12 -> 7.8979511 | O24: =L24+M24+N24 -> 84.683587
A25: 10176873-09-F044LF | B25: ORV3-60A | D25: 0.799 | F25: 0.319 | G25: =SUM(D25:F25) -> 1.118 | H25: =D25*C25 -> 0 | I25: =F25*C25 -> 0 | J25: =SUM(H25:I25) -> 0 | K25: =C25/$X$5 -> 0 | L25: =C25*G25/$X$5/7.05/$X$4 -> 0 | N25: =L25*0.12 -> 0 | O25: =L25+M25+N25 -> 0
A26: 10176873-37-F247LF | B26: ORV3-60A | D26: 0.7 | F26: 0.32 | G26: =SUM(D26:F26) -> 1.02 | H26: =D26*C26 -> 0 | I26: =F26*C26 -> 0 | J26: =SUM(H26:I26) -> 0 | K26: =C26/$X$5 -> 0 | L26: =C26*G26/$X$5/7.05/$X$4 -> 0 | N26: =L26*0.12 -> 0 | O26: =L26+M26+N26 -> 0
A27: 10176873-18-F126LF | B27: ORV3-60A | D27: 0.61 | F27: 0.31 | G27: =SUM(D27:F27) -> 0.92 | H27: =D27*C27 -> 0 | I27: =F27*C27 -> 0 | J27: =SUM(H27:I27) -> 0 | K27: =C27/$X$5 -> 0 | L27: =C27*G27/$X$5/7.05/$X$4 -> 0 | N27: =L27*0.12 -> 0 | O27: =L27+M27+N27 -> 0
A28: 10170827-07P003 | B28: ORV3-Connector | C28: 0 | D28: 0.08 | F28: 0.032 | G28: =SUM(D28:F28) -> 0.112 | H28: =D28*C28 -> 0 | I28: =F28*C28 -> 0 | J28: =SUM(H28:I28) -> 0 | K28: =C28/$X$5 -> 0 | L28: =C28*G28/$X$5/7.05/$X$4 -> 0 | N28: =L28*0.12 -> 0 | O28: =L28+M28+N28 -> 0
A29: 10146534-1EP063LF | B29: BK 100 Cable | C29: 18550 | D29: =0.065-T29 -> 0.035833333 | E29: 0.065 | F29: 0.022 | G29: =D29+F29 -> 0.057833333 | H29: =E29*C29 -> 1205.75 | I29: =F29*C29 -> 408.1 | J29: =SUM(H29:I29) -> 1613.85 | K29: =C29/$X$5 -> 772.91667 | L29: =C29*G29/$X$5/7.05/$X$4 -> 7.205085 | N29: =L29*0.12 -> 0.8646102 | O29: =L29+M29+N29 -> 8.0696952 | Q29: =15/3600 -> 0.0041666667 | R29: =10/3600 -> 0.0027777778 | S29: =2*40/3600 -> 0.022222222 | T29: =SUM(Q29:S29) -> 0.029166667
A30: 10172541-001LF | B30: BK25 | D30: 0.0409 | F30: 0.0065 | G30: =SUM(D30:F30) -> 0.0474 | H30: =D30*C30 -> 0 | I30: =F30*C30 -> 0 | J30: =SUM(H30:I30) -> 0 | K30: =C30/$X$5 -> 0 | L30: =C30*G30/$X$5/7.05/$X$4 -> 0 | N30: =L30*0.12 -> 0 | O30: =L30+M30+N30 -> 0
A31: 10174690-1UF026LF | B31: Oracle | D31: 0.295472 | F31: 0.0277778 | G31: =SUM(D31:F31) -> 0.3232498 | H31: =D31*C31 -> 0 | I31: =F31*C31 -> 0 | J31: =SUM(H31:I31) -> 0 | K31: =C31/$X$5 -> 0 | L31: =C31*G31/$X$5/7.05/$X$4 -> 0 | N31: =L31*0.12 -> 0 | O31: =L31+M31+N31 -> 0 | V31: Power Blade - Support. Staff
A32: 10170820-001LF | B32: IPC Battery | C32: 21000 | D32: 0.004 | F32: 0.0025 | G32: =SUM(D32:F32) -> 0.0065 | H32: =D32*C32 -> 84 | I32: =F32*C32 -> 52.5 | J32: =SUM(H32:I32) -> 136.5 | K32: =C32/$X$5 -> 875 | L32: =C32*G32/$X$5/7.05/$X$4 -> 0.91674726 | N32: =L32*0.12 -> 0.11000967 | O32: =L32+M32+N32 -> 1.0267569
A33: 10170425-9B0040LF | B33: BK350 | C33: 25902 | D33: 0.145 | F33: 0.008 | G33: =D33+F33 -> 0.153 | H33: =D33*C33 -> 3755.79 | I33: =F33*C33 -> 207.216 | J33: =SUM(H33:I33) -> 3963.006 | K33: =C33/$X$5 -> 1079.25 | L33: =C33*G33/$X$5/7.05/$X$4 -> 26.615933 | N33: =L33*0.12 -> 3.193912 | O33: =L33+M33+N33 -> 29.809845
A34: HPG36P14SRT051TH07 | B34: EEX | C34: =12200+7820 -> 20020 | D34: 0.066 | F34: 0.013 | G34: =SUM(D34:F34) -> 0.079 | H34: =D34*C34 -> 1321.32 | I34: =F34*C34 -> 260.26 | J34: =SUM(H34:I34) -> 1581.58 | K34: =C34/$X$5 -> 834.16667 | L34: =C34*G34/$X$5/7.05/$X$4 -> 10.622045 | N34: =L34*0.12 -> 1.2746454 | O34: =L34+M34+N34 -> 11.89669
A35: 10173947-100012LF | B35: 48V Connector | C35: 48500 | D35: 0.0104167 | F35: 0.0048 | G35: =SUM(D35:F35) -> 0.0152167 | H35: =D35*C35 -> 505.20995 | I35: =F35*C35 -> 232.8 | J35: =SUM(H35:I35) -> 738.00995 | K35: =C35/$X$5 -> 2020.8333 | L35: =C35*G35/$X$5/7.05/$X$4 -> 4.9565465 | N35: =L35*0.12 -> 0.59478558 | O35: =L35+M35+N35 -> 5.5513321
A36: 10174690-1UF011LF | B36: BK220 I/O Cable Assembly | C36: 2600 | D36: =0.24-T36 -> 0.19333333 | E36: 0.24 | F36: 0.02 | G36: =D36+F36 -> 0.21333333 | H36: =E36*C36 -> 624 | I36: =F36*C36 -> 52 | J36: =SUM(H36:I36) -> 676 | K36: =C36/$X$5 -> 108.33333 | L36: =C36*G36/$X$5/7.05/$X$4 -> 3.7251952 | N36: =L36*0.12 -> 0.44702343 | O36: =L36+M36+N36 -> 4.1722186 | Q36: =36/3600 -> 0.01 | S36: =22*6/3600 -> 0.036666667 | T36: =SUM(Q36:S36) -> 0.046666667
A37: 10146534-9B0001LF | B37: BK ZOID | C37: 621 | D37: 0.322 | E37: 0.322 | F37: 0.04 | G37: =D37+F37 -> 0.362 | H37: =E37*C37 -> 199.962 | I37: =F37*C37 -> 24.84 | J37: =SUM(H37:I37) -> 224.802 | K37: =C37/$X$5 -> 25.875 | L37: =C37*G37/$X$5/7.05/$X$4 -> 1.5097921 | N37: =L37*0.12 -> 0.18117505 | O37: =L37+M37+N37 -> 1.6909671
A38: 10170744-9D0001LF | B38: BK250 | C38: 10000 | D38: =0.26-T38 -> 0.20111111 | E38: 0.28 | F38: 0.03 | G38: =D38+F38 -> 0.23111111 | H38: =E38*C38 -> 2800 | I38: =F38*C38 -> 300 | J38: =SUM(H38:I38) -> 3100 | K38: =C38/$X$5 -> 416.66667 | L38: =C38*G38/$X$5/7.05/$X$4 -> 15.521647 | N38: =L38*0.12 -> 1.8625976 | O38: =L38+M38+N38 -> 17.384244 | Q38: =36/3600 -> 0.01 | S38: =22*8/3600 -> 0.048888889 | T38: =SUM(Q38:S38) -> 0.058888889
A39: 10174690-1WF149LF | B39: BK220 | C39: 1060 | D39: =0.176-T39 -> 0.11711111 | E39: 0.176 | F39: 0.029 | G39: =D39+F39 -> 0.14611111 | H39: =E39*C39 -> 186.56 | I39: =F39*C39 -> 30.74 | J39: =SUM(H39:I39) -> 217.3 | K39: =C39/$X$5 -> 44.166667 | L39: =C39*G39/$X$5/7.05/$X$4 -> 1.0401742 | N39: =L39*0.12 -> 0.1248209 | O39: =L39+M39+N39 -> 1.1649951 | Q39: =36/3600 -> 0.01 | S39: =22*8/3600 -> 0.048888889 | T39: =SUM(Q39:S39) -> 0.058888889
A40: C10176572-B000R | B40: CSD | C40: 10000 | D40: =228/3600 -> 0.063333333 | F40: =110/3600 -> 0.030555556 | G40: =SUM(D40:F40) -> 0.093888889 | H40: =D40*C40 -> 633.33333 | I40: =F40*C40 -> 305.55556 | J40: =SUM(H40:I40) -> 938.88889 | K40: =C40/$X$5 -> 416.66667 | L40: =C40*G40/$X$5/7.05/$X$4 -> 6.305669 | N40: =L40*0.12 -> 0.75668028 | O40: =L40+M40+N40 -> 7.0623493
A41: 10172495-1F0139LF | B41: 48V Cable assembly | C41: 2500 | D41: =0.76-T41 -> 0.66111111 | E41: 0.76 | F41: =511/3600 -> 0.14194444 | G41: =D41+F41 -> 0.80305556 | H41: =E41*C41 -> 1900 | I41: =F41*C41 -> 354.86111 | J41: =SUM(H41:I41) -> 2254.8611 | K41: =C41/$X$5 -> 104.16667 | L41: =C41*G41/$X$5/7.05/$X$4 -> 13.483498 | N41: =L41*0.12 -> 1.6180197 | O41: =L41+M41+N41 -> 15.101518 | Q41: =36/3600 -> 0.01 | S41: =20*16/3600 -> 0.088888889 | T41: =SUM(Q41:S41) -> 0.098888889
O42: =L42+M42+N42 -> 0
A43: Machine Crew (Cutting, Cropping, Welding) | L43: ='Machine crew-Cable'!F13 -> 172 | M43: ='Machine crew-Cable'!G14 -> 28.666667 | N43: ='Machine crew-Cable'!G16 -> 25 | O43: =L43+M43+N43 -> 225.66667
A44: Total | H44: =SUM(H3:H33) -> 74424.321 | I44: =SUM(I3:I33) -> 15160.486 | J44: =SUM(J3:J33) -> 89584.807 | L44: =SUM(L3:L43) -> 762.77056 | M44: =SUM(M3:M43) -> 61.573067 | N44: =SUM(N3:N43) -> 98.524911
L45: =L44+M44+N44 -> 922.86854 | O45: =SUM(O3:O44) -> 922.86854
O49: =L49+M49+N49 -> 0
O51: =L51+M51+N51 -> 0
O52: =L52+M52+N52 -> 0
O53: =L53+M53+N53 -> 0
L59: Lead | M59: 26
L60: Scrap entry | M60: 5
L61: Store/ework | M61: 6
L62: Store | M62: 8
L63: QA | M63: 40
M64: =SUM(M59:M63) -> 85

Sheet NPD crew details
F5: NPD Crew Details
F6: Team | G6: Nos
F7: QA/QC | G7: 19
F8: Technisian | G8: 1
F9: DL-Assembly | G9: 61
F10: Process Technisian | G10: 2
F11: Molding | G11: 3
F12: Stores | G12: 3
F13: NAPS-Lead | G13: 3
F15: Total | G15: =SUM(G7:G13) -> 92

Sheet Sheet6
D3: Assembly Lines | E3: HC Allocated by IE | F3: Present HC on Shop floor | G3: Gap
C4: Manufacturing | D4: Crew required for BK cable Assembly | E4: =(439.156635800463+32)*0.88 -> 414.61784 | H4: 0.88
D5: Crew required for ACWHIP | E5: =(400.584717386632+19)*0.88 -> 369.23455
D6: Crew required for Connector | E6: =(196.188319033121+26)*0.88 -> 195.52572
D7: Training crew | E7: 44
D8: Crew required for EV | E8: 198.88
D9: Total Crew for Manufacturing | E9: =SUM(E4:E8) -> 1222.2581 | F9: 1208 | G9: =F9-E9 -> -14.258112

Sheet Plan-Jan
A2: HPL | B2: Item group | C2: Row Labels | D2: Description | E2: Jan Plan | F2: Additional Expected
A3: 346 | B3: 346PB+RH | C3: 10106116-4000002LF | D3: Connector,PB+RH | E3: 2970
A4: 346 | B4: 346PB+RH | C4: 10106116-6000001LF | D4: Connector,PB+RH | E4: 1056
A5: 346 | B5: 346PB+RH | C5: 10106116-8000K01LF | D5: PwrBlade+ RAH STB | E5: 396
A6: 552 | B6: 552PB+VR | C6: 10106122-5004001LF | D6: PwrBlade+ VTR | E6: 2880
A7: 552 | B7: 552PB+RH | C7: 10106124-4006005LF | D7: PB+ RAH STB | E7: 792
A8: 346 | B8: 346PB+RH | C8: 10106124-8005003LF | D8: PwrBlade+ RAH | E8: 37790
A9: 346 | B9: 346PB+RH | C9: 10106124-9000002LF | D9: PwrBlade+ RAH STB | E9: 264
A10: 346 | B10: 346PB+RH | C10: 10106124-E000K01LF | D10: Connector,PB+RH | E10: 1056
A11: 346 | B11: 346PB+RH | C11: 10106124-E008001LF | D11: PwrBlade+ RAH | E11: 10032
A12: 346 | B12: 346PB+RH | C12: 10106124-F005K01LF | D12: PwrBlade+ RAH STB | E12: 5280
A13: 346 | B13: 346PB+VR | C13: 10106131-2202001LF | D13: PwrBlade+ VR PF | E13: 6264
A14: 346 | B14: 346PB+VR | C14: 10106131-4004001LF | D14: PwrBlade+ VR PF | E14: 11160
... A70: 519 | B70: 519B5080 | C70: 10169634-S01LF | D70: PLATED SENSOR CONTACTS | E70: 11679
A71: 352 | B71: 352ACIPC | C71: 10170775-170501 | D71: OCP AC_IN RKEY R-MALE | E71: 3472 | F71: 2240
A72: 352 | B72: 352ACIPC | C72: 10170775-170502 | D72: OCP AC_IN RKEY L-MALE | E72: 3920 | F72: 2240
A73: 329 | B73: 329IPC | C73: 10170818-S01LF | D73: IPC-S75/M50 10/12HDCT | E73: 81200
A74: 329 | B74: 329IPC | C74: 10170820-001LF | D74: IPC-M50 Gray Connector | E74: 40000
A75: 520 | B75: 356ACICB | C75: 10170827-07P002 | D75: AC 6P+1W CBL ASY RHT 90D | F75: 5000
A76: 520 | B76: 356ACICB | C76: 10170827-07P003 | D76: AC 6P+1W CBL ASY LFT 90D | F76: 5000
A77: 329 | B77: 329IPC | C77: 10171423-S02LF | D77: IPC-S175/M180 4CT | E77: 1000
A78: 329 | B78: 329IPC | C78: 10171423-S05LF | D78: IPC-S175/M180 1/0CT | E78: 600
A79: 329 | B79: 329IPC | C79: 10171426-001LF | D79: IPC-M175 Gray Connector | E79: 1000
A80: 329 | B80: 329IPC | C80: 10171426-003LF | D80: IPC-M175 Red Connector | E80: 1000
A81: 613 | B81: 61348VCA | C81: 10172495-1F0139LF | D81: 48V busbar cable assy | E81: 1920
A82: 519 | B82: 519BK25 | C82: 10172541-001LF | D82: BK25 BUSBAR WITH FERRITE | E82: 20970
A83: 613 | B83: 61348HDR | C83: 10173947-100012LF | D83: Header assembly 4 key | E83: 11680
A84: 613 | B84: 61348HDR | C84: 10173947-100015LF | D84: Header assembly 2 key | E84: 11680
A85: 355 | B85: 355NVICA | C85: 10174690-1UF011LF | D85: BK220 I/O Cable Assembly | E85: 24000
A86: 520 | B86: 520ET30H | C86: 10174780-001LF | D86: ET30 ELCON 3POS HDR CONN | E86: 22400
A87: 520 | B87: 520ET30H | C87: 10174781-001LF | D87: ET30 ELCON 6POS HDR CONN | E87: 14040
A88: 520 | B88: 520RLKT | C88: 10174922-001LF | D88: SZ4 CNR KIT RPD LK | E88: 46600
... A97: 356 | B97: 356EC60A | C97: 10176873-19-F140LF | D97: 60A 7P AC-IP WHIP ASSY | E97: 700
A98: 356 | B98: 356ORV3E | C98: 10178160-C7A302 | D98: OCP AC WHIP 78DEG 30A | E98: 10000 | F98: 5000
A99: 356 | B99: 356ORV3E | C99: 10178161-C7A302 | D99: OCP AC WHIP 35DEG 30A | E99: 3875
A100: 356 | B100: 356ORV3E | C100: 10178161-C7A304 | D100: OCP AC WHIP 35 ° 30A | E100: 3930
A101: 520 | B101: 520RLKT | C101: 10178823-001LF | D101: RAPIDLOCK PIN ASSEMBLY | E101: 16000
A102: 356 | B102: 356ORV3E | C102: 10180876-E7C01 | D102: AC WHIP IEC 32A STRAIGHT | E102: 6310 | F102: 12500
A103: 356 | B103: 356ORVM2 | C103: 10181064-K70006 | D103: ORV3 90-STRAIGHT 2500mm | E103: 200 | F103: 10000
A104: 356 | B104: 356ORVM2 | C104: 10181065-K70005 | D104: AC -AC WHIP STRAIGHT | E104: 1101
A105: 356 | B105: 356ORVM2 | C105: 10181065-K70007 | D105: AC -AC WHIP STRAIGHT | E105: 660
A106: 503 | B106: 356ORV3I | C106: 10182476-71A801 | D106: ORV3AC INTERCONNECTEXCAB | E106: 6810
A107: 356 | B107: 356ORVM2 | C107: 10182948-Q50001 | D107: AC -AC WHIP FEMALE-MALE | E107: 680
A108: 356 | B108: 356ORVM2 | C108: 10182948-Q50002 | D108: ORV3 FEMALE-MALE 1260mm | F108: 5000
A109: 613 | B109: 61348VCA | C109: 10183206-007LF | D109: 48V BUSBAR RA C/A 2.54M | E109: 10
A110: 356 | B110: 356EC100 | C110: 10188304-054F01 | D110: 100A AC WHIP IEC C/A | E110: 2000
A111: 355 | B111: 355BKZOD | C111: 10190265-9F0001LF | D111: BENCHTOP BUSBAR WITH C/A | E111: 547
A112: 552 | B112: 552PBRAH | C112: 51720-10201602AALF | D112: PwrBlade RAH STB | E112: 792
A113: 552 | B113: 552PBRAH | C113: 51720-10202402AALF | D113: PwrBlade RAH | E113: 528
A114: 552 | B114: 552PBRAH | C114: 51720-10404004AALF | D114: PwrBlade RAH | E114: 132
A115: 552 | B115: 552PBRAH | C115: 51721-10002406AALF | D115: PwrBlade RAH | E115: 594
A116: 552 | B116: 552PBRAH | C116: 51721-10003605AALF | D116: PwrBlade RAH | E116: 198
A117: 552 | B117: 552PBRAH | C117: 51723-10400000AALF | D117: PwrBlade RAH | E117: 660
A118: 552 | B118: 552PBRAH | C118: 51730-034LF | D118: PwrBlade RAH | E118: 264
A119: 552 | B119: 552PBRAH | C119: 51731-022LF | D119: PwrBlade RAH | E119: 462
A120: 552 | B120: 552PBRAH | C120: 51732-007LF | D120: PwrBlade RAH | E120: 660
... A156: 552 | B156: 552PWBVR | C156: 51967-10006000AALF | D156: PwrBlade VR | E156: 288
A157: 520 | B157: 520CSD | C157: C10176572-B000R | D157: Board Connector-CSD | E157: 8000 | F157: 10000
A158: 520 | B158: 520CSD | C158: C10176573-P500 | D158: Plug Connector-CSD | E158: 8000 | F158: 10000
A159: 520 | B159: 520CSD | C159: C10176574-001 | D159: CSD-DUST CAP | E159: 8000 | F159: 10000
A160: 517 | B160: 359EEXST | C160: HPG36P14SRT051TH07 | D160: 2.1MM,W/O RIB,W/ CVR | E160: 5480
A161: 612 | B161: 612ET20H | C161: PWRFST001 | D161: ET20-MINIPWR FEM HSG | E161: 4000
A162: 612 | B162: 612FIT30 | C162: PWRFST017 | D162: AC R/A CableRcp CNR | E162: 240
A163: 612 | B163: 612ET20H | C163: PWRMRA001 | D163: ET20-RA HDR CNR-20A | E163: 4800
A164: 612 | B164: 612ET20H | C164: PWRMRA025 | D164: ET20-RA HDR CNR | E164: 12000
A165: 520 | B165: 612ET20H | C165: PWRMRA028 | D165: ET20 2P RA PWR Connector | E165: 31000
A166: 519 | B166: 519BK350 | C166: RPS0112002 | D166: BK350 Au PLATING | E166: 89040
A167: 356 | B167: 356ORV3E | C167: RPS0700749-004 | D167: ORv3 cable Assy -NEMA | E167: 17010 | F167: 10800

Sheet To IE
G1: 25506.692
A2: HPL | B2: Item group | C2: Row Labels | D2: Description | E2: Sum of Qty Open | F2: Sum of Base Currency Amount | G2: Currency Amount inK$ | H2: Unit price inK $ | I2: Jan Plan | J2: Add. If Any (In Qty.-Pcs) | K2: semi | L2: ins
A3: 346 | B3: 346PB+RH | C3: 10106116-4000002LF | D3: Connector,PB+RH | E3: 3630 | F3: 762492.23 | G3: 8.6646844 | H3: 0.0023869654 | I3: 2970 | K3: =VLOOKUP(C3,'[4]PB Order'!$C$11:$G$120,5,0) -> 0.0017 | L3: =VLOOKUP(C3,'[4]PB Order'!$C$11:$F$120,4,0) -> 0.003 | M3: =I3*K3 -> 5.049 | N3: =I3*L3 -> 8.91
A4: 346 | B4: 346PB+RH | C4: 10106116-6000001LF | D4: Connector,PB+RH | E4: 1056 | F4: 245843.35 | G4: 2.7936744 | H4: 0.002645525 | I4: 1056 | K4: 0.0033 | L4: 0.003 | M4: =I4*K4 -> 3.4848 | N4: =I4*L4 -> 3.168
A5: 346 | B5: 346PB+RH | C5: 10106116-8000K01LF | D5: PwrBlade+ RAH STB | E5: 792 | F5: 219970.55 | G5: 2.4996653 | H5: 0.0031561431 | I5: 396 | K5: =VLOOKUP(C5,'[4]PB Order'!$C$11:$G$120,5,0) -> 0.003 | L5: =VLOOKUP(C5,'[4]PB Order'!$C$11:$F$120,4,0) -> 0.025 | M5: =I5*K5 -> 1.188 | N5: =I5*L5 -> 9.9
A6: 346 | B6: 346PB+RH | C6: 10106116-8005K01LF | D6: PwrBlade+ RAH STB | E6: 132 | F6: 75981.84 | G6: 0.86343 | H6: 0.0065411364 | I6: 132 | K6: 0.0033 | L6: 0.003 | M6: =I6*K6 -> 0.4356 | N6: =I6*L6 -> 0.396
A7: 552 | B7: 552PB+VR | C7: 10106122-5004001LF | D7: PwrBlade+ VTR | E7: 5472 | F7: 1265680.9 | G7: 14.382737 | H7: 0.0026284242 | I7: 5472 | K7: =VLOOKUP(C7,'[4]PB Order'!$C$11:$G$120,5,0) -> 0.005 | L7: =VLOOKUP(C7,'[4]PB Order'!$C$11:$F$120,4,0) -> 0.019875 | M7: =I7*K7 -> 27.36 | N7: =I7*L7 -> 108.756
A8: 552 | B8: 552PB+RH | C8: 10106124-4006005LF | D8: PB+ RAH STB | E8: 792 | F8: 117591.15 | G8: 1.3362631 | H8: 0.0016872008 | I8: 792 | K8: =VLOOKUP(C8,'[4]PB Order'!$C$11:$G$120,5,0) -> 0.0033 | L8: =VLOOKUP(C8,'[4]PB Order'!$C$11:$F$120,4,0) -> 0.027 | M8: =I8*K8 -> 2.6136 | N8: =I8*L8 -> 21.384
A9: 346 | B9: 346PB+RH | C9: 10106124-8005003LF | D9: PwrBlade+ RAH | E9: 69216 | F9: 13288484 | G9: 151.0055 | H9: 0.002181656 | I9: 40656 | K9: =VLOOKUP(C9,'[4]PB Order'!$C$11:$G$120,5,0) -> 0.002181 | L9: =VLOOKUP(C9,'[4]PB Order'!$C$11:$F$120,4,0) -> 0.013086 | M9: =I9*K9 -> 88.670736 | N9: =I9*L9 -> 532.02442
A10: 346 | B10: 346PB+RH | C10: 10106124-9000002LF | D10: PwrBlade+ RAH STB | E10: 264 | F10: 71614.71 | G10: 0.81380352 | H10: 0.0030825891 | I10: 264 | K10: 0.0033 | L10: 0.003 | M10: =I10*K10 -> 0.8712 | N10: =I10*L10 -> 0.792
A11: 346 | B11: 346PB+RH | C11: 10106124-E000K01LF | D11: Connector,PB+RH | E11: 1056 | F11: 405242.79 | G11: 4.6050317 | H11: 0.0043608255 | I11: 1056 | K11: 0.0033 | L11: 0.003 | M11: =I11*K11 -> 3.4848 | N11: =I11*L11 -> 3.168
A12: 346 | B12: 346PB+RH | C12: 10106124-E008001LF | D12: PwrBlade+ RAH | E12: 22044 | F12: 3209253 | G12: 36.468785 | H12: 0.0016543633 | I12: 10032 | K12: =VLOOKUP(C12,'[4]PB Order'!$C$11:$G$120,5,0) -> 0.002 | L12: =VLOOKUP(C12,'[4]PB Order'!$C$11:$F$120,4,0) -> 0.018 | M12: =I12*K12 -> 20.064 | N12: =I12*L12 -> 180.576
A13: 346 | B13: 346PB+RH | C13: 10106124-F005K01LF | D13: PwrBlade+ RAH STB | E13: 5280 | F13: 1880791.6 | G13: 21.372632 | H13: 0.004047847 | I13: 1716 | K13: =VLOOKUP(C13,'[4]PB Order'!$C$11:$G$120,5,0) -> 0.003 | L13: =VLOOKUP(C13,'[4]PB Order'!$C$11:$F$120,4,0) -> 0.035 | M13: =I13*K13 -> 5.148 | N13: =I13*L13 -> 60.06
A14: 346 | B14: 346PB+VR | C14: 10106131-2202001LF | D14: PwrBlade+ VR PF | E14: 6264 | F14: 436377.06 | G14: 4.9588302 | H14: 0.00079163956 | I14: 6264 | K14: 0.0033 | L14: 0.003 | M14: =I14*K14 -> 20.6712 | N14: =I14*L14 -> 18.792
A15: 346 | B15: 346PB+VR | C15: 10106131-4004001LF | D15: PwrBlade+ VR PF | E15: 13320 | F15: 1257764.9 | G15: 14.292783 | H15: 0.0010730317 | I15: 11160 | K15: =VLOOKUP(C15,'[4]PB Order'!$C$11:$G$120,5,0) -> 0.0033 | L15: =VLOOKUP(C15,'[4]PB Order'!$C$11:$F$120,4,0) -> 0.0144175 | M15: =I15*K15 -> 36.828 | N15: =I15*L15 -> 160.8993
A16: 346 | B16: 346PB+VR | C16: 10106131-4006005LF | D16: PwrBlade+ VR PF | E16: 576 | F16: 82301.74 | G16: 0.93524705 | H16: 0.0016236928 | I16: 288 | K16: =VLOOKUP(C16,'[4]PB Order'!$C$11:$G$120,5,0) -> 0.021 | L16: =VLOOKUP(C16,'[4]PB Order'!$C$11:$F$120,4,0) -> 0.0262758 | M16: =I16*K16 -> 6.048 | N16: =I16*L16 -> 7.5674304
A17: 346 | B17: 346PB+VR | C17: 10106131-5005002LF | D17: PwrBlade+ VR PF | E17: 576 | F17: 161624.59 | G17: 1.8366431 | H17: 0.0031886164 | I17: 576 | K17: 0.0033 | L17: 0.003 | M17: =I17*K17 -> 1.9008 | N17: =I17*L17 -> 1.728
A18: 346 | B18: 346PB+VR | C18: 10106131-9014001LF | D18: PwrBlade+ VR PF | E18: 2288 | F18: 516075.64 | G18: 5.8644959 | H18: 0.0025631538 | I18: 2288 | K18: =VLOOKUP(C18,'[4]PB Order'!$C$11:$G$120,5,0) -> 0.012 | L18: =VLOOKUP(C18,'[4]PB Order'!$C$11:$F$120,4,0) -> 0.028 | M18: =I18*K18 -> 27.456 | N18: =I18*L18 -> 64.064
A19: 552 | B19: 552PB+VR | C19: 10106139-4009101LF | D19: PwrBlade+ VTR | E19: 6048 | F19: 832534.36 | G19: 9.4606177 | H19: 0.0015642556 | I19: 6048 | K19: =VLOOKUP(C19,'[4]PB Order'!$C$11:$G$120,5,0) -> 0.01 | L19: =VLOOKUP(C19,'[4]PB Order'!$C$11:$F$120,4,0) -> 0.02895 | M19: =I19*K19 -> 60.48 | N19: =I19*L19 -> 175.0896
A20: 346 | B20: 346PB+VR | C20: 10106139-4027101LF | D20: PwrBlade+ VR PF | E20: 144 | F20: 46607.4 | G20: 0.52962955 | H20: 0.003677983 | I20: 144 | K20: =VLOOKUP(C20,'[4]PB Order'!$C$11:$G$120,5,0) -> 0.03 | L20: =VLOOKUP(C20,'[4]PB Order'!$C$11:$F$120,4,0) -> 0.029 | M20: =I20*K20 -> 4.32 | N20: =I20*L20 -> 4.176
A21: 552 | B21: 552PB+RH | C21: 10106262-0002002LF | D21: PB+ RAH STB | E21: 924 | F21: 118223.37 | G21: 1.3434474 | H21: 0.0014539474 | I21: 924 | K21: 0.0033 | L21: 0.003 | M21: =I21*K21 -> 3.0492 | N21: =I21*L21 -> 2.772
A22: 346 | B22: 346PB+RH | C22: 10106262-0006001LF | D22: PwrBlade+ RAH STB | E22: 2640 | F22: 280487.17 | G22: 3.1873542 | H22: 0.0012073311 | I22: 2640 | K22: 0.0033 | L22: 0.003 | M22: =I22*K22 -> 8.712 | N22: =I22*L22 -> 7.92
A23: 346 | B23: 346PB+RH | C23: 10106262-0009K01LF | D23: PwrBlade+ RAH STB | E23: 2772 | F23: 446437.9 | G23: 5.073158 | H23: 0.0018301436 | I23: 2772 | K23: 0.0033 | L23: =VLOOKUP(C23,'[4]PB Order'!$C$11:$F$120,4,0) -> 0.028 | M23: =I23*K23 -> 9.1476 | N23: =I23*L23 -> 77.616
A24: 346 | B24: 346PBRAH | C24: 10106262-0602K02LF | D24: PwrBlade+ RAH STB | E24: 1584 | F24: 287559.1 | G24: 3.267717 | H24: 0.0020629527 | I24: 1584 | K24: 0.0033 | L24: 0.003 | M24: =I24*K24 -> 5.2272 | N24: =I24*L24 -> 4.752
A25: 346 | B25: 552PB+RH | C25: 10106262-0F08001LF | D25: PwrBlade+ RAH | E25: 49401 | F25: 12489500 | G25: 141.92614 | H25: 0.0028729405 | I25: 49401 | K25: =VLOOKUP(C25,'[4]PB Order'!$C$11:$G$120,5,0) -> 0.0025 | L25: =VLOOKUP(C25,'[4]PB Order'!$C$11:$F$120,4,0) -> 0.017 | M25: =I25*K25 -> 123.5025 | N25: =I25*L25 -> 839.817
A26: 552 | B26: 552PB+RH | C26: 10106262-1C03012LF | D26: PwrBlade+ RAH | E26: 19206 | F26: 3092779.9 | G26: 35.145226 | H26: 0.0018299087 | I26: 7524 | K26: =VLOOKUP(C26,'[4]PB Order'!$C$11:$G$120,5,0) -> 0.00279 | L26: =VLOOKUP(C26,'[4]PB Order'!$C$11:$F$120,4,0) -> 0.02976 | M26: =I26*K26 -> 20.99196 | N26: =I26*L26 -> 223.91424
A27: 346 | B27: 346PB+RH | C27: 10106262-2600004LF | D27: PwrBlade+ RAH STB | E27: 2640 | F27: 453315.8 | G27: 5.1513159 | H27: 0.001951256 | I27: 1320 | K27: =VLOOKUP(C27,'[4]PB Order'!$C$11:$G$120,5,0) -> 0.0082 | L27: =VLOOKUP(C27,'[4]PB Order'!$C$11:$F$120,4,0) -> 0.0195 | M27: =I27*K27 -> 10.824 | N27: =I27*L27 -> 25.74
A28: 346 | B28: 346PB+RH | C28: 10106262-3037K01LF | D28: PwrBlade+ RAH STB | E28: 198 | F28: 232536.32 | G28: 2.6424582 | H28: 0.013345748 | I28: 198 | K28: 0.0033 | L28: 0.003 | M28: =I28*K28 -> 0.6534 | N28: =I28*L28 -> 0.594
A29: 346 | B29: 346PB+RH | C29: 10106262-5203001LF | D29: PwrBlade+ RAH STB | E29: 198 | F29: 64618.79 | G29: 0.73430443 | H29: 0.0037086082 | I29: 198 | K29: 0.0033 | L29: 0.003 | M29: =I29*K29 -> 0.6534 | N29: =I29*L29 -> 0.594
A30: 346 | B30: 346PB+RH | C30: 10106262-F000003LF | D30: PwrBlade+ RAH STB | E30: 1122 | F30: 341157.83 | G30: 3.8767935 | H30: 0.0034552527 | I30: 1122 | K30: =VLOOKUP(C30,'[4]PB Order'!$C$11:$G$120,5,0) -> 0.0033 | L30: 0.003 | M30: =I30*K30 -> 3.7026 | N30: =I30*L30 -> 3.366
A31: 552 | B31: 552PB+RH | C31: 10106262-T006001LF | D31: PB+ RAH STB | E31: 2046 | F31: 1197514.8 | G31: 13.608123 | H31: 0.0066510864 | I31: 1848 | K31: 0.0033 | L31: 0.003 | M31: =I31*K31 -> 6.0984 | N31: =I31*L31 -> 5.544
A32: 346 | B32: 346PB+VR | C32: 10106268-0017101LF | D32: PwrBlade+ VR STB | E32: 576 | F32: 111385.16 | G32: 1.2657405 | H32: 0.0021974661 | I32: 288 | K32: =VLOOKUP(C32,'[4]PB Order'!$C$11:$G$120,5,0) -> 0.019 | L32: 0.003 | M32: =I32*K32 -> 5.472 | N32: =I32*L32 -> 0.864
A33: 346 | B33: 346PB+VR | C33: 10106268-0527101LF | D33: PwrBlade+ VR STB | E33: 576 | F33: 188247 | G33: 2.1391705 | H33: 0.0037138376 | I33: 576 | K33: 0.0033 | L33: 0.003 | M33: =I33*K33 -> 1.9008 | N33: =I33*L33 -> 1.728
A34: 346 | B34: 552PB+VR | C34: 10106268-0F08001LF | D34: PwrBlade+ VTR | E34: 44604 | F34: 9563675.7 | G34: 108.67813 | H34: 0.0024365109 | I34: 38988 | K34: 0.0033 | L34: 0.003 | M34: =I34*K34 -> 128.6604 | N34: =I34*L34 -> 116.964
A35: 552 | B35: 552PB+VR | C35: 10106268-9001001LF | D35: PwrBlade+ VTR | E35: 2160 | F35: 658509.65 | G35: 7.4830642 | H35: 0.0034643816 | I35: 2160 | K35: 0.0033 | L35: 0.003 | M35: =I35*K35 -> 7.128 | N35: =I35*L35 -> 6.48
A36: 346 | B36: 346PB+VR | C36: 10106269-0402006LF | D36: Connector,PB+VR | E36: 1408 | F36: 220168.45 | G36: 2.5019142 | H36: 0.0017769277 | I36: 1408 | K36: 0.0033 | L36: 0.003 | M36: =I36*K36 -> 4.6464 | N36: =I36*L36 -> 4.224
A37: 346 | B37: 346PB+VR | C37: 10106269-2005K02LF | D37: Connector,PB+VR | E37: 3168 | F37: 532899.69 | G37: 6.0556783 | H37: 0.0019115146 | I37: 1056 | K37: =VLOOKUP(C37,'[4]PB Order'!$C$11:$G$120,5,0) -> 0.005 | L37: 0.003 | M37: =I37*K37 -> 5.28 | N37: =I37*L37 -> 3.168
A38: 346 | B38: 346PB+VR | C38: 10106269-5203001LF | D38: PwrBlade+ VR PF | E38: 216 | F38: 46569.41 | G38: 0.52919784 | H38: 0.00244999 | I38: 216 | K38: 0.0033 | L38: 0.003 | M38: =I38*K38 -> 0.7128 | N38: =I38*L38 -> 0.648
A39: 552 | B39: 552PB+VR | C39: 10106269-B010001LF | D39: PwrBlade+ VTR | E39: 1440 | F39: 659384.97 | G39: 7.493011 | H39: 0.0052034799 | I39: 1440 | K39: =VLOOKUP(C39,'[4]PB Order'!$C$11:$G$120,5,0) -> 0.011 | L39: =VLOOKUP(C39,'[4]PB Order'!$C$11:$F$120,4,0) -> 0.0383 | M39: =I39*K39 -> 15.84 | N39: =I39*L39 -> 55.152
A40: 346 | B40: 346PB+VR | C40: 10106269-C002001LF | D40: PwrBlade+ VR PF | E40: 432 | F40: 116972.87 | G40: 1.3292372 | H40: 0.0030769379 | I40: 432 | K40: 0.0033 | L40: 0.003 | M40: =I40*K40 -> 1.4256 | N40: =I40*L40 -> 1.296
A41: 347 | B41: 347PBTML | C41: 10125942-GC13LF | D41: POWER CONTACT RH | E41: 2000 | F41: 11464285 | G41: 130.27597 | H41: 0.065137984 | I41: 200 | K41: 0.0033 | L41: 0.003 | M41: =I41*K41 -> 0.66 | N41: =I41*L41 -> 0.6
A42: 347 | B42: 347PBTML | C42: 10125942-GC23LF | D42: POWER CONTACT LH | E42: 1400 | F42: 7874999.6 | G42: 89.488632 | H42: 0.063920451 | I42: 200 | K42: 0.0033 | L42: 0.003 | M42: =I42*K42 -> 0.66 | N42: =I42*L42 -> 0.6
A43: 347 | B43: 347PBTML | C43: 10126183-GC321LF | D43: POWER CONTACT RECR/A PBU | E43: 600 | F43: 3637499.8 | G43: 41.335225 | H43: 0.068892042 | I43: 100 | K43: 0.0033 | L43: 0.003 | M43: =I43*K43 -> 0.33 | N43: =I43*L43 -> 0.3
A44: 347 | B44: 347PBTML | C44: 10126183-GC322LF | D44: POWER CONTACT RECR/A PBU | E44: 600 | F44: 3557142.7 | G44: 40.422076 | H44: 0.067370127 | I44: 100 | K44: 0.0033 | L44: 0.003 | M44: =I44*K44 -> 0.33 | N44: =I44*L44 -> 0.3
A45: 347 | B45: 347PBTML | C45: 10126183-GC421LF | D45: POWER CONTACT RECR/A PBU | E45: 1000 | F45: 6080356.9 | G45: 69.094964 | H45: 0.069094964 | I45: 200 | K45: 0.0033 | L45: 0.003 | M45: =I45*K45 -> 0.66 | N45: =I45*L45 -> 0.6
A46: 347 | B46: 347PBTML | C46: 10126183-GC422LF | D46: POWER CONTACT RECR/A PBU | E46: 1200 | F46: 7135713.9 | G46: 81.087658 | H46: 0.067573049 | I46: 200 | K46: 0.0033 | L46: 0.003 | M46: =I46*K46 -> 0.66 | N46: =I46*L46 -> 0.6
A47: 347 | B47: 347PBURH | C47: 10127396-01U1520LF | D47: PBU RAH STB CONN | E47: 18432 | F47: 7323428.2 | G47: 83.220775 | H47: 0.004515016 | I47: 18432 | K47: 0.0033 | L47: 0.003 | M47: =I47*K47 -> 60.8256 | N47: =I47*L47 -> 55.296
A48: 347 | B48: 347PBURR | C48: 10127400-01U1520LF | D48: PBU RAR CONNECTOR | E48: 104934 | F48: 19292732 | G48: 219.23559 | H48: 0.0020892713 | I48: 98022 | K48: =VLOOKUP(C48,'[4]PB Order'!$C$11:$G$120,5,0) -> 0.011 | L48: =VLOOKUP(C48,'[4]PB Order'!$C$11:$F$120,4,0) -> 0.030028125 | M48: =I48*K48 -> 1078.242 | N48: =I48*L48 -> 2943.4169
A49: 355 | B49: 355METCA | C49: 10130664-9B0319HLF | D49: BARKLIP CABLE ASSEMBLY | E49: 2000 | F49: 3975504.6 | G49: 45.176189 | H49: 0.022588095 | I49: 2000
A50: 355 | B50: 355METCA | C50: 10130664-9C0151QLF | D50: BARKLIP CABLEASSEMBLY-24 | E50: 19340 | F50: 12252695 | G50: 139.23517 | H50: 0.0071993367 | I50: 13120
A51: 355 | B51: 355TSLCA | C51: 10130664-9D0354LF | D51: BARKLIP CABLE ASSY-196MM | E51: 6480 | F51: 3562492 | G51: 40.482864 | H51: 0.0062473555 | I51: 1454
A52: 355 | B52: 355TSLCA | C52: 10130664-9D0355LF | D52: BARKLIP CABLE ASSY-135MM | E52: 9360 | F52: 5018989.6 | G52: 57.033973 | H52: 0.0060933732 | I52: 7200
A53: 355 | B53: 355TSLCA | C53: 10130664-9D0356LF | D53: BARKLIP CABLE ASSY-82MM | E53: 5760 | F53: 2945659.1 | G53: 33.473399 | H53: 0.0058113539 | I53: 4320
A54: 355 | B54: 355METCA | C54: 10130664-9RF438LF | D54: BK200 I/O Cable Assembly | E54: 21220 | F54: 23545024 | G54: 267.55709 | H54: 0.012608722 | I54: 29820
A55: 355 | B55: 355BK100 | C55: 10146534-1EP059LF | D55: BK100 Cable Assembly | E55: 4950 | F55: 5531842.2 | G55: 62.861843 | H55: 0.012699362 | I55: 700
A56: 355 | B56: 355BK100 | C56: 10146534-1EP061LF | D56: BK100 Cable Assembly | E56: 2100 | F56: 2004374.9 | G56: 22.776988 | H56: 0.010846185 | I56: 3100
A57: 355 | B57: 355BK100 | C57: 10146534-1EP062LF | D57: BK100 Cable Assembly | E57: 1025 | F57: 1328839.2 | G57: 15.100446 | H57: 0.014732142 | I57: 1025
A58: 355 | B58: 355BK100 | C58: 10146534-1EP063LF | D58: BK100 Cable Assembly | E58: 11250 | F58: 10657366 | G58: 121.10643 | H58: 0.010765016 | I58: 23375
A59: 355 | B59: 355BK100 | C59: 10146534-1EP064LF | D59: BK100 Cable Assembly | E59: 5000 | F59: 4303571.2 | G59: 48.904218 | H59: 0.0097808437 | I59: 5000
A60: 552 | B60: 552PBAMX | C60: 10147785-001LF | D60: AIRMAX CONNECTOR | E60: 12450 | F60: 3845224 | G60: 43.695727 | H60: 0.003509697 | I60: 4800 | K60: 0.0033 | L60: 0.003 | M60: =I60*K60 -> 15.84 | N60: =I60*L60 -> 14.4
A61: 503 | B61: 503BKACC | C61: 10150562-001 | D61: HOUSING RPS04HBR01F | E61: 20170 | F61: 471420.55 | G61: 5.3570517 | H61: 0.00026559503 | I61: 39000
A62: 503 | B62: 503BKACC | C62: 10150562-002 | D62: TERMINAL RPS04C1392F | E62: 157503 | F62: 4195667.9 | G62: 47.678044 | H62: 0.00030271198 | I62: 223653
A63: 612 | B63: 612ET20H | C63: 10153920-001 | D63: ET20 Receptacle assy | E63: 35000 | F63: 775375.93 | G63: 8.8110901 | H63: 0.00025174543 | J63: 35000
A64: 355 | B64: 355BK300 | C64: 10158287-1RF057HF | D64: BK300 I/O Cable Assembly | E64: 48580 | F64: 55718746 | G64: 633.16756 | H64: 0.013033503 | I64: 40680
A65: 355 | B65: 355BK50C | C65: 10162405-1S2009LF | D65: BARKLIP CABLE ASSEMBLY | E65: 45150 | F65: 42147694 | G65: 478.95107 | H65: 0.010607997 | I65: 32000
A66: 519 | B66: 519B5080 | C66: 10162456-001 | D66: RPS04B036 HSG | E66: 79760 | F66: 2664972.3 | G66: 30.283776 | H66: 0.00037968626 | I66: 40000
A67: 519 | B67: 519B5080 | C67: 10162456-002 | D67: RPS04B037 LOCK | E67: 160000 | F67: 640141.62 | G67: 7.2743366 | H67: 4.5464604e-05 | I67: 80000
A68: 519 | B68: 519B5080 | C68: 10162457-001 | D68: RPS04S125-0011_Contact | E68: 81250 | F68: 1759436.3 | G68: 19.993594 | H68: 0.00024607501 | I68: 40000
A69: 519 | B69: 519B5080 | C69: 10162457-003 | D69: RPS04S125-0021_Contact | E69: 9000 | F69: 196837.04 | G69: 2.2367845 | H69: 0.00024853162 | I69: 9000
A70: 519 | B70: 519B5080 | C70: 10162457-004 | D70: RPS04S124-0021_Contact | E70: 9725 | F70: 217188.68 | G70: 2.4680532 | H70: 0.00025378439 | I70: 9725
A71: 519 | B71: 519B5080 | C71: 10162457-005 | D71: RPS04S124-0011_Contact | E71: 190460 | F71: 4119105.1 | G71: 46.808013 | H71: 0.00024576296 | I71: 80000
A72: 519 | B72: 519B5080 | C72: 10162457-008 | D72: RPS04S124-0031_Contact | E72: 6000 | F72: 131548.54 | G72: 1.4948698 | H72: 0.00024914496 | I72: 6000
A73: 355 | B73: 355BK100 | C73: 10165117-001 | D73: BK100 BarKlip TPA ENHNCD | E73: 249000 | F73: 1546902.7 | G73: 17.57844 | H73: 7.0596143e-05 | I73: 210000
A74: 520 | B74: 520RLKT | C74: 10166013-101LF | D74: RapidLockPin CNR KitAssy | E74: 28000 | F74: 3976619.7 | G74: 45.18886 | H74: 0.0016138879 | I74: 10000
A75: 520 | B75: 520RLKT | C75: 10167397-101LF | D75: Rapid Lock Pin Kit,2.45 | E75: 1900 | F75: 275599.22 | G75: 3.1318093 | H75: 0.0016483207 | I75: 1900
A76: 520 | B76: 520RLKT | C76: 10168675-001LF | D76: Rapid Lock Pin Conn Kit | E76: 428000 | F76: 66131685 | G76: 751.49642 | H76: 0.0017558328 | I76: 320000
A77: 352 | B77: 352ACIPC | C77: 10170775-170501 | D77: OCP AC_IN RKEY R-MALE | E77: 3472 | F77: 3319261.5 | G77: 37.71888 | H77: 0.010863733 | I77: 3472 | J77: 2240
A78: 352 | B78: 352ACIPC | C78: 10170775-170502 | D78: OCP AC_IN RKEY L-MALE | E78: 3920 | F78: 3752905.3 | G78: 42.646651 | H78: 0.010879248 | I78: 3920 | J78: 2240
A79: 329 | B79: 329IPC | C79: 10170818-S01LF | D79: IPC-S75/M50 10/12HDCT | E79: 93200 | F79: 3542452.8 | G79: 40.255145 | H79: 0.00043192216 | I79: 60000
A80: 329 | B80: 329IPC | C80: 10170820-001LF | D80: IPC-M50 Gray Connector | E80: 46000 | F80: 2024000 | G80: 23 | H80: 0.0005 | I80: 30000
A81: 520 | B81: 356ACICB | C81: 10170827-07P002 | D81: AC 6P+1W CBL ASY RHT 90D | E81: 4 | F81: 8278.56 | G81: 0.094074545 | H81: 0.023518636 | J81: 5000
A82: 520 | B82: 356ACICB | C82: 10170827-07P003 | D82: AC 6P+1W CBL ASY LFT 90D | E82: 864 | F82: 1826450.2 | G82: 20.755116 | H82: 0.024022125 | J82: 5000
A83: 329 | B83: 329IPC | C83: 10171423-S02LF | D83: IPC-S175/M180 4CT | E83: 1000 | F83: 136767.85 | G83: 1.5541801 | H83: 0.0015541801 | I83: 1000
A84: 329 | B84: 329IPC | C84: 10171423-S05LF | D84: IPC-S175/M180 1/0CT | E84: 600 | F84: 76497.35 | G84: 0.86928807 | H84: 0.0014488134 | I84: 600
A85: 329 | B85: 329IPC | C85: 10171426-001LF | D85: IPC-M175 Gray Connector | E85: 1000 | F85: 123522.13 | G85: 1.4036606 | H85: 0.0014036606 | I85: 1000
A86: 329 | B86: 329IPC | C86: 10171426-003LF | D86: IPC-M175 Red Connector | E86: 1000 | F86: 123522.13 | G86: 1.4036606 | H86: 0.0014036606 | I86: 1000
A87: 613 | B87: 61348VCA | C87: 10172495-1F0139LF | D87: 48V busbar cable assy | E87: 2412 | F87: 64523042 | G87: 733.21639 | H87: 0.30398689 | I87: 1920
A88: 519 | B88: 519BK25 | C88: 10172541-001LF | D88: BK25 BUSBAR WITH FERRITE | E88: 20970 | F88: 6985471.4 | G88: 79.380357 | H88: 0.0037854247 | I88: 20970
A89: 613 | B89: 61348HDR | C89: 10173947-100012LF | D89: Header assembly 4 key | E89: 18176 | F89: 10815094 | G89: 122.8988 | H89: 0.0067615977 | I89: 20800
A90: 613 | B90: 61348HDR | C90: 10173947-100015LF | D90: Header assembly 2 key | E90: 18176 | F90: 10845565 | G90: 123.24506 | H90: 0.0067806481 | I90: 20800
A91: 355 | B91: 355NVICA | C91: 10174690-1UF011LF | D91: BK220 I/O Cable Assembly | E91: 40000 | F91: 1.6781934e+08 | G91: 1907.0379 | H91: 0.047675948 | I91: 24000
A92: 520 | B92: 520ET30H | C92: 10174780-001LF | D92: ET30 ELCON 3POS HDR CONN | E92: 22400 | F92: 2058199.2 | G92: 23.388627 | H92: 0.0010441351 | I92: 16200
A93: 520 | B93: 520ET30H | C93: 10174781-001LF | D93: ET30 ELCON 6POS HDR CONN | E93: 14040 | F93: 1811717.4 | G93: 20.587698 | H93: 0.0014663603 | I93: 10140
A94: 520 | B94: 520RLKT | C94: 10174922-001LF | D94: SZ4 CNR KIT RPD LK | E94: 46600 | F94: 11435558 | G94: 129.94952 | H94: 0.0027886164 | I94: 4000 | J94: 26600
A95: 520 | B95: 520RLKT | C95: 10174923-001LF | D95: SZ2 CNR KIT RPD LK | E95: 46900 | F95: 13422162 | G95: 152.52457 | H95: 0.003252123 | I95: 4000 | J95: 26400
A96: 147 | B96: 147ENGP | C96: 10176857-001LF | D96: EP 200 SOC CNR BK | E96: 40 | F96: 7997.14 | G96: 0.090876591 | H96: 0.0022719148 | J96: 40
A97: 147 | B97: 147ENGP | C97: 10176857-002LF | D97: EP 200 SOC CNR OR | E97: 40 | F97: 7997.14 | G97: 0.090876591 | H97: 0.0022719148 | J97: 40
A98: 613 | B98: 613ENGP | C98: 10176859-001LF | D98: Socket Connector-EP250A | E98: 20 | F98: 4680 | G98: 0.053181818 | H98: 0.0026590909 | J98: 6740
A99: 147 | B99: 147ENGP | C99: 10176859-002LF | D99: EP 250 SOC CNR OR | E99: 20 | F99: 4680 | G99: 0.053181818 | H99: 0.0026590909 | J99: 5040
A100: 356 | B100: 356EC60A | C100: 10176873-18-F126LF | D100: 60A 7P AC-IP WHIP ASSY | E100: 1400 | F100: 54770976 | G100: 622.39746 | H100: 0.44456961 | I100: 700
...

Sheet Forecast Vs Earned Hrs
C3: Assembly hrs
C4: Assembly Lines | D4: Semi-Auto | E4: Manual-Hrs | F4: Insp. & Pack-Hrs | G4: Total | H4: Achieved Hrs (W1'26) | I4: Utilization
C5: BK Cable Assembly Line | E5: 18758.07 | F5: 3989.0466 | G5: =SUM(E5:F5) -> 22747.116 | H5: 8088 | I5: =H5/G5 -> 0.35556155
C6: ACWHIP Line | E6: 50549.831 | F6: 14647.535 | G6: =SUM(E6:F6) -> 65197.366 | H6: 17580 | I6: =H6/G6 -> 0.26964279
C7: Legacy Power-Cable | E7: 21649 | F7: 3410 | G7: =SUM(D7:F7) -> 25059 | H7: 7890 | I7: =H7/G7 -> 0.31485694
C9: Cable Total | G9: =SUM(G5:G8) -> 113003.48 | H9: =SUM(H5:H8) -> 33558 | I9: =H9/G9 -> 0.2969643
C10: Legacy Power-Connector | D10: 2094 | E10: 4751 | F10: 940 | G10: =SUM(D10:F10) -> 7785 | H10: 2335 | I10: =H10/G10 -> 0.29993577
C11: Connector Assembly | D11: 2686 | E11: 12256.74 | F11: 10987.92 | G11: =SUM(D11:F11) -> 25930.66 | H11: 4051 | I11: =H11/G11 -> 0.15622433
C13: Connector Total | G13: =SUM(G10:G12) -> 33715.66 | H13: =SUM(H10:H12) -> 6386 | I13: =H13/G13 -> 0.18940753
C15: Total Hrs | D15: =G13+G9 -> 146719.14 | H15: =H9+H13 -> 39944 | I15: =H15/D15 -> 0.27224805

Sheet Nov Plan
E1: 1808181 | G1: 9820.4235
A2: HPL | B2: item group | C2: Row Labels | D2: Desc | E2: Nov plan | F2: Add. Qty. | G2: Nov K $ | H2: PACKING | I2: AUTO
A3: 613 | B3: 61348VCA | C3: 10172495-1F0139LF | D3: 48V busbar cable assy | E3: 2500 | G3: 755.0482
A4: 347 | B4: 347PBURR | C4: 10127400-01U1520LF | D4: PBU RAR CONNECTOR | E4: 98688 | G4: 212.86034 | H4: 0.020617046 | I4: 0.0019 | J4: =E4*H4 -> 2034.655 | K4: =E4*I4 -> 187.5072
A5: 552 | B5: 552PBRAH | C5: 51730-145LF | D5: PwrBlade RAH STB | E5: 33528 | G5: 76.898836 | H5: =VLOOKUP(C5,[5]MasterS.F!$A$5:$G$4349,7,0) -> 0.020617046 | I5: =VLOOKUP(C5,[5]MasterS.F!$A$5:$W$4350,23,0) -> 0.0019 | J5: =E5*H5 -> 691.24832 | K5: =E5*I5 -> 63.7032
A6: 356 | B6: 356ORV3E | C6: 10180876-E7C01 | D6: AC WHIP IEC 32A STRAIGHT | E6: 655 | G6: 129.40458
A7: 613 | B7: 61348VCA | C7: 10173947-100015LF | D7: Header assembly 2 key | E7: 5120 | F7: 8000 | G7: 34.651651
A8: 613 | B8: 61348VCA | C8: 10173947-100012LF | D8: Header assembly 4 key | E8: 5120 | F8: 8000 | G8: 34.548674
A9: 552 | B9: 552PBRAH | C9: 51939-163LF | D9: Connector,PBRAH | E9: 33000 | G9: 38.10375 | H9: =VLOOKUP(C9,[5]MasterS.F!$A$5:$G$4349,7,0) -> 0.0071 | I9: =VLOOKUP(C9,[5]MasterS.F!$A$5:$W$4350,23,0) -> 0.0016 | J9: =E9*H9 -> 234.3 | K9: =E9*I9 -> 52.8
A10: 519 | B10: 519BK25 | C10: 10172541-001LF | D10: BK25 BUSBAR WITH FERRITE | E10: 18000 | F10: 15030 | G10: 67.823152
A11: 356 | B11: 356EC100 | C11: 10188304-054F01 | D11: 100A AC WHIP IEC C/A | E11: 0 | F11: 500 | G11: 0
A12: 346 | B12: 346PB+RH | C12: 10106124-8005003LF | D12: PwrBlade+ RAH | E12: 27552 | F12: 30000 | G12: 59.83675 | H12: =VLOOKUP(C12,[5]MasterS.F!$A$5:$G$4349,7,0) -> 0.013086 | I12: =VLOOKUP(C12,[5]MasterS.F!$A$5:$W$4350,23,0) -> 0.002181 | J12: =(E12+F12)*H12 -> 753.12547 | K12: =(E12+F12)*I12 -> 125.52091
A13: 552 | B13: 552PB+RH | C13: 10106262-1C03012LF | D13: PwrBlade+ RAH | E13: 17820 | G13: 33.697627 | H13: =VLOOKUP(C13,[5]MasterS.F!$A$5:$G$4349,7,0) -> 0.02976 | I13: =VLOOKUP(C13,[5]MasterS.F!$A$5:$W$4350,23,0) -> 0.00279 | J13: =E13*H13 -> 530.3232 | K13: =E13*I13 -> 49.7178
A14: 552 | B14: 552PBRAR | C14: 51921-008LF | D14: PwrBlade RAR | E14: 15120 | G14: 23.894755 | H14: 0.02976 | I14: 0.00279 | J14: =E14*H14 -> 449.9712 | K14: =E14*I14 -> 42.1848
A15: 347 | B15: 347PBURH | C15: 10127396-01U1520LF | D15: PBU RAH STB CONN | E15: 8640 | G15: 22.478469 | H15: 0.02976 | I15: 0.00279 | J15: =E15*H15 -> 257.1264 | K15: =E15*I15 -> 24.1056
A16: 552 | B16: 552PB+RH | C16: 10106132-4009101LF | D16: PB+ RAH STB | E16: 7920 | G16: 14.932464 | H16: =VLOOKUP(C16,[5]MasterS.F!$A$5:$G$4349,7,0) -> 0.028 | I16: =VLOOKUP(C16,[5]MasterS.F!$A$5:$W$4350,23,0) -> 0.0033 | J16: =E16*H16 -> 221.76 | K16: =E16*I16 -> 26.136
A17: 552 | B17: 552PBRAH | C17: 51939-234LF | D17: PwrBlade RAH | E17: 7874 | G17: 9.6910774 | H17: =VLOOKUP(C17,[5]MasterS.F!$A$5:$G$4349,7,0) -> 0.014097426 | I17: =VLOOKUP(C17,[5]MasterS.F!$A$5:$W$4350,23,0) -> 0.0019 | J17: =E17*H17 -> 111.00313 | K17: =E17*I17 -> 14.9606
A18: 520 | B18: 612ET20H | C18: PWRMRA028 | D18: ET20 2P RA PWR Connector | E18: 21600 | G18: 0
A19: 552 | B19: 552PBRAH | C19: 51939-1222LHLF | D19: PwrBlade RAH | E19: 5016 | G19: 6.8456002 | H19: =VLOOKUP(C19,[5]MasterS.F!$A$5:$G$4349,7,0) -> 0.026621 | I19: =VLOOKUP(C19,[5]MasterS.F!$A$5:$W$4350,23,0) -> 0.0033 | J19: =E19*H19 -> 133.53094 | K19: =E19*I19 -> 16.5528
A20: 552 | B20: 552PB+VR | C20: 10106139-4009101LF | D20: PwrBlade+ VTR | E20: 4032 | G20: 6.2699762 | H20: =VLOOKUP(C20,[5]MasterS.F!$A$5:$G$4349,7,0) -> 0.02895 | I20: =VLOOKUP(C20,[5]MasterS.F!$A$5:$W$4350,23,0) -> 0.01 | J20: =E20*H20 -> 116.7264 | K20: =E20*I20 -> 40.32
A21: 612 | B21: 612FIT30 | C21: PWRFST026 | D21: DC-C CALE RECE CONN | E21: 480 | G21: 3.3827752
A22: 552 | B22: 552PBRAH | C22: 51939-927LF | D22: PwrBlade RAH STB | E22: 3300 | G22: 4.0585953 | H22: =VLOOKUP(C22,[5]MasterS.F!$A$5:$G$4349,7,0) -> 0.0238 | I22: =VLOOKUP(C22,[5]MasterS.F!$A$5:$W$4350,23,0) -> 0.002 | J22: =E22*H22 -> 78.54 | K22: =E22*I22 -> 6.6
A23: 520 | B23: 520ET30H | C23: 10174780-001LF | D23: ET30 ELCON 3POS HDR CONN | E23: 10800 | G23: 9.5654997
A24: 552 | B24: 552PB+RH | C24: 10106124-4006005LF | D24: PB+ RAH STB | E24: 2904 | G24: 4.7592882 | H24: =VLOOKUP(C24,[5]MasterS.F!$A$5:$G$4349,7,0) -> 0.027 | I24: =VLOOKUP(C24,[5]MasterS.F!$A$5:$W$4350,23,0) -> 0.0033 | J24: =E24*H24 -> 78.408 | K24: =E24*I24 -> 9.5832
A25: 552 | B25: 552PBRAH | C25: 51939-834LF | D25: PwrBlade RAH | E25: 2846 | G25: 6.7564801 | H25: =VLOOKUP(C25,[5]MasterS.F!$A$5:$G$4349,7,0) -> 0.02198412 | I25: =VLOOKUP(C25,[5]MasterS.F!$A$5:$W$4350,23,0) -> 0.005 | J25: =E25*H25 -> 62.566806 | K25: =E25*I25 -> 14.23
A26: 552 | B26: 552PWBVR | C26: 51741-10002805AALF | D26: PwrBlade VR STB | E26: 2640 | G26: 5.5761437 | H26: =VLOOKUP(C26,[5]MasterS.F!$A$5:$G$4349,7,0) -> 0.0198 | I26: =VLOOKUP(C26,[5]MasterS.F!$A$5:$W$4350,23,0) -> 0.0111 | J26: =E26*H26 -> 52.272 | K26: =E26*I26 -> 29.304
A27: 552 | B27: 552PBRAH | C27: 51939-299LF | D27: PwrBlade RAH STB | E27: 1980 | G27: 8.5203949 | H27: =VLOOKUP(C27,[5]MasterS.F!$A$5:$G$4349,7,0) -> 0.0274 | I27: =VLOOKUP(C27,[5]MasterS.F!$A$5:$W$4350,23,0) -> 0.0037 | J27: =E27*H27 -> 54.252 | K27: =E27*I27 -> 7.326
A28: 552 | B28: 552PB+VR | C28: 10106269-3606001LF | D28: PwrBlade+ VTR | E28: 1728 | G28: 5.7222432 | H28: =VLOOKUP(C28,[5]MasterS.F!$A$5:$G$4349,7,0) -> 0.0365454 | I28: 0.0037 | J28: =E28*H28 -> 63.150451 | K28: =E28*I28 -> 6.3936
A29: 347 | B29: 347PBURR | C29: 10127401-06H1510LF | D29: PBU RAR CONNECTOR | E29: 1440 | G29: 4.4290911 | H29: 0.0274 | I29: 0.0037 | J29: =E29*H29 -> 39.456 | K29: =E29*I29 -> 5.328
A30: 612 | B30: 612ET20H | C30: PWRMRA025 | D30: ET20-RA HDR CNR | E30: 6000 | G30: 0
A31: 552 | B31: 552PB+RH | C31: 10106132-4027101LF | D31: PB+ RAH STB | E31: 1320 | G31: 5.2481936 | H31: =VLOOKUP(C31,[5]MasterS.F!$A$5:$G$4349,7,0) -> 0.051 | I31: =VLOOKUP(C31,[5]MasterS.F!$A$5:$W$4350,23,0) -> 0.01 | J31: =E31*H31 -> 67.32 | K31: =E31*I31 -> 13.2
A32: 346 | B32: 346PB+RH | C32: 10106262-2600004LF | D32: PwrBlade+ RAH STB | E32: 1320 | G32: 2.5096156 | H32: =VLOOKUP(C32,[5]MasterS.F!$A$5:$G$4349,7,0) -> 0.0195 | I32: =VLOOKUP(C32,[5]MasterS.F!$A$5:$W$4350,23,0) -> 0.0082 | J32: =E32*H32 -> 25.74 | K32: =E32*I32 -> 10.824
A33: 346 | B33: 346PB+VR | C33: 10106268-2002008LF | D33: Connector,PB+VR | E33: 1200 | G33: 2.8446891 | H33: =VLOOKUP(C33,[5]MasterS.F!$A$5:$G$4349,7,0) -> 0.035 | I33: =VLOOKUP(C33,[5]MasterS.F!$A$5:$W$4350,23,0) -> 0.004 | J33: =E33*H33 -> 42 | K33: =E33*I33 -> 4.8
A34: 346 | B34: 346PB+RH | C34: 10106124-8000K01LF | D34: Connector,PB+RH | E34: 1188 | G34: 3.7614553 | H34: =VLOOKUP(C34,[5]MasterS.F!$A$5:$G$4349,7,0) -> 0.028 | I34: =VLOOKUP(C34,[5]MasterS.F!$A$5:$W$4350,23,0) -> 0.004 | J34: =E34*H34 -> 33.264 | K34: =E34*I34 -> 4.752
A35: 346 | B35: 346PB+VR | C35: 10106268-0402005LF | D35: PwrBlade+ VR STB | E35: 1100 | G35: 1.3754425 | H35: =VLOOKUP(C35,[5]MasterS.F!$A$5:$G$4349,7,0) -> 0.0358 | I35: =VLOOKUP(C35,[5]MasterS.F!$A$5:$W$4350,23,0) -> 0.006 | J35: =E35*H35 -> 39.38 | K35: =E35*I35 -> 6.6
A36: 552 | B36: 552PB+VR | C36: 10106268-9001001LF | D36: PwrBlade+ VTR | E36: 1080 | G36: 3.7249033 | H36: =VLOOKUP(C36,[5]MasterS.F!$A$5:$G$4349,7,0) -> 0.025017307 | I36: =VLOOKUP(C36,[5]MasterS.F!$A$5:$W$4350,23,0) -> 0.0033 | J36: =E36*H36 -> 27.018692 | K36: =E36*I36 -> 3.564
A37: 346 | B37: 346PB+RH | C37: 10106124-E000K01LF | D37: Connector,PB+RH | E37: 1056 | G37: 4.6049369 | H37: =VLOOKUP(C37,[5]MasterS.F!$A$5:$G$4349,7,0) -> 0.032 | I37: =VLOOKUP(C37,[5]MasterS.F!$A$5:$W$4350,23,0) -> 0.005 | J37: =E37*H37 -> 33.792 | K37: =E37*I37 -> 5.28
A38: 346 | B38: 346PB+RH | C38: 10106262-F000003LF | D38: PwrBlade+ RAH STB | E38: 1056 | G38: 3.6410975 | H38: =VLOOKUP(C38,[5]MasterS.F!$A$5:$G$4349,7,0) -> 0.036 | I38: =VLOOKUP(C38,[5]MasterS.F!$A$5:$W$4350,23,0) -> 0.0033 | J38: =E38*H38 -> 38.016 | K38: =E38*I38 -> 3.4848
A39: 552 | B39: 552PBRAH | C39: 51939-1006LF | D39: PwrBlade RAH STB | E39: 1056 | G39: 3.0674737 | H39: =VLOOKUP(C39,[5]MasterS.F!$A$5:$G$4349,7,0) -> 0.045 | I39: =VLOOKUP(C39,[5]MasterS.F!$A$5:$W$4350,23,0) -> 0.0067 | J39: =E39*H39 -> 47.52 | K39: =E39*I39 -> 7.0752
A40: 552 | B40: 552PBRAH | C40: 51939-103LF | D40: PwrBlade RAH | E40: 1056 | G40: 2.4133807 | H40: =VLOOKUP(C40,[5]MasterS.F!$A$5:$G$4349,7,0) -> 0.015 | I40: =VLOOKUP(C40,[5]MasterS.F!$A$5:$W$4350,23,0) -> 0.0019 | J40: =E40*H40 -> 15.84 | K40: =E40*I40 -> 2.0064
A41: 612 | B41: 612ET20H | C41: 10153920-001 | D41: ET20 Receptacle assy | E41: 15000 | G41: 0
A42: 552 | B42: 552PBRAH | C42: 51415-001LF | D42: PwrBlade RAH | E42: 1056 | G42: 1.732158 | H42: =VLOOKUP(C42,[5]MasterS.F!$A$5:$G$4349,7,0) -> 0.010688068 | I42: =VLOOKUP(C42,[5]MasterS.F!$A$5:$W$4350,23,0) -> 0.0019 | J42: =E42*H42 -> 11.2866 | K42: =E42*I42 -> 2.0064
A43: 552 | B43: 552PBRAH | C43: 51939-389LF | D43: PwrBlade RAH | E43: 1056 | G43: 1.090407 | H43: =VLOOKUP(C43,[5]MasterS.F!$A$5:$G$4349,7,0) -> 0.01700424 | I43: =VLOOKUP(C43,[5]MasterS.F!$A$5:$W$4350,23,0) -> 0 | J43: =E43*H43 -> 17.956477 | K43: =E43*I43 -> 0
A44: 552 | B44: 552PB+RH | C44: 10106262-0002002LF | D44: PB+ RAH STB | E44: 924 | G44: 1.3034534 | H44: =VLOOKUP(C44,[5]MasterS.F!$A$5:$G$4349,7,0) -> 0.016935 | I44: =VLOOKUP(C44,[5]MasterS.F!$A$5:$W$4350,23,0) -> 0.0033 | J44: =E44*H44 -> 15.64794 | K44: =E44*I44 -> 3.0492
A45: 552 | B45: 552PBRAH | C45: 51966-10006400AALF | D45: Connector,PBRAH | E45: 792 | G45: 1.8384237 | H45: =VLOOKUP(C45,[5]MasterS.F!$A$5:$G$4349,7,0) -> 0.022 | I45: =VLOOKUP(C45,[5]MasterS.F!$A$5:$W$4350,23,0) -> 0.002 | J45: =E45*H45 -> 17.424 | K45: =E45*I45 -> 1.584
A46: 346 | B46: 346PB+RH | C46: 10106124-4000001LF | D46: PwrBlade+ RAH STB | E46: 792 | G46: 1.6211922 | H46: =VLOOKUP(C46,[5]MasterS.F!$A$5:$G$4349,7,0) -> 0.031 | I46: =VLOOKUP(C46,[5]MasterS.F!$A$5:$W$4350,23,0) -> 0.0061 | J46: =E46*H46 -> 24.552 | K46: =E46*I46 -> 4.8312
A47: 346 | B47: 346PB+VR | C47: 10106139-4027101LF | D47: PwrBlade+ VR PF | E47: 720 | G47: 2.624713 | H47: =VLOOKUP(C47,[5]MasterS.F!$A$5:$G$4349,7,0) -> 0.029 | I47: =VLOOKUP(C47,[5]MasterS.F!$A$5:$W$4350,23,0) -> 0.03 | J47: =E47*H47 -> 20.88 | K47: =E47*I47 -> 21.6
A48: 552 | B48: 552PWBVR | C48: 51940-535LF | D48: PwrBlade VTR | E48: 720 | G48: 1.1120974 | H48: =VLOOKUP(C48,[5]MasterS.F!$A$5:$G$4349,7,0) -> 0.02 | I48: =VLOOKUP(C48,[5]MasterS.F!$A$5:$W$4350,23,0) -> 0.003 | J48: =E48*H48 -> 14.4 | K48: =E48*I48 -> 2.16
A49: 552 | B49: 552PBRAH | C49: 51939-907LF | D49: PwrBlade RAH STB | E49: 660 | G49: 1.6830461 | H49: =VLOOKUP(C49,[5]MasterS.F!$A$5:$G$4349,7,0) -> 0.056 | I49: =VLOOKUP(C49,[5]MasterS.F!$A$5:$W$4350,23,0) -> 0.003 | J49: =E49*H49 -> 36.96 | K49: =E49*I49 -> 1.98
A50: 346 | B50: 346PB+RH | C50: 10106116-4000002LF | D50: Connector,PB+RH | E50: 660 | G50: 1.5640724 | H50: =VLOOKUP(C50,[5]MasterS.F!$A$5:$G$4349,7,0) -> 0.003 | I50: =VLOOKUP(C50,[5]MasterS.F!$A$5:$W$4350,23,0) -> 0.0017 | J50: =E50*H50 -> 1.98 | K50: =E50*I50 -> 1.122
A51: 552 | B51: 552PBRAH | C51: 51733-004LF | D51: PwrBlade RAH | E51: 660 | G51: 1.5555731 | H51: =VLOOKUP(C51,[5]MasterS.F!$A$5:$G$4349,7,0) -> 0.0215 | I51: =VLOOKUP(C51,[5]MasterS.F!$A$5:$W$4350,23,0) -> 0.0061 | J51: =E51*H51 -> 14.19 | K51: =E51*I51 -> 4.026
A52: 346 | B52: 346PB+RH | C52: 10106124-6006010LF | D52: Connector,PB+RH | E52: 594 | G52: 2.8402986 | H52: =VLOOKUP(C52,[5]MasterS.F!$A$5:$G$4349,7,0) -> 0.038 | I52: =VLOOKUP(C52,[5]MasterS.F!$A$5:$W$4350,23,0) -> 0.0033 | J52: =E52*H52 -> 22.572 | K52: =E52*I52 -> 1.9602
A53: 552 | B53: 552PBRAH | C53: 51721-10002406AALF | D53: PwrBlade RAH | E53: 594 | G53: 1.3797658 | H53: =VLOOKUP(C53,[5]MasterS.F!$A$5:$G$4349,7,0) -> 0.014404348 | I53: =VLOOKUP(C53,[5]MasterS.F!$A$5:$W$4350,23,0) -> 0.0019 | J53: =E53*H53 -> 8.5561827 | K53: =E53*I53 -> 1.1286
... A78: 552 | B78: 552PBRAH | C78: 51966-10008000AALF | D78: PwrBlade RAH STB | E78: 30 | G78: 0.19716295 | H78: =VLOOKUP(C78,[5]MasterS.F!$A$5:$G$4349,7,0) -> 0.022 | I78: =VLOOKUP(C78,[5]MasterS.F!$A$5:$W$4350,23,0) -> 0.002 | J78: =E78*H78 -> 0.66 | K78: =E78*I78 -> 0.06
A79: 355 | B79: 355BK50C | C79: 10162405-1S2009LF | D79: BARKLIP CABLE ASSEMBLY | E79: 59250 | G79: 630.22661
A80: 355 | B80: 355METCA | C80: 10130664-9B0319HLF | D80: BARKLIP CABLE ASSEMBLY | E80: 2000 | G80: 44.779905
A81: 355 | B81: 355BRKCA | C81: 10130664-9C0151QLF | D81: BARKLIP CABLEASSEMBLY-24 | E81: 2620 | G81: 18.862262
A82: 355 | B82: 355TSLCA | C82: 10130664-9D0354LF | D82: BARKLIP CABLE ASSY-196MM | E82: 0 | F82: 3000 | G82: 0
A83: 355 | B83: 355TSLCA | C83: 10130664-9D0355LF | D83: BARKLIP CABLE ASSY-135MM | E83: 19500 | G83: 115.65424
A84: 355 | B84: 355TSLCA | C84: 10130664-9D0356LF | D84: BARKLIP CABLE ASSY-82MM | E84: 23820 | G84: 135.09839
A85: 355 | B85: 355BRKCA | C85: 10130664-9RF438LF | D85: BK200 I/O Cable Assembly | E85: 9600 | F85: 12000 | G85: 118.8981
A86: 355 | B86: 355BK100 | C86: 10146534-1EP059LF | D86: BK100 Cable Assembly | E86: 10000 | G86: 126.99362
A87: 355 | B87: 355BK100 | C87: 10146534-1EP063LF | D87: BK100 Cable Assembly | E87: 5000 | G87: 55.970894
A88: 355 | B88: 355BK100 | C88: 10146534-1EP065LF | D88: BK100 Cable Assembly | E88: 200 | G88: 2.0534997
A89: 503 | B89: 503BKACC | C89: 10150562-001 | D89: HOUSING RPS04HBR01F | E89: 79800 | G89: 21.008491
A90: 503 | B90: 503BKACC | C90: 10150562-002 | D90: TERMINAL RPS04C1392F | E90: 455000 | G90: 136.5734
A91: 519 | B91: 519BBINC | C91: 10157266-001LF | D91: Bk200 connector | E91: 50000 | G91: 84.728869
A92: 355 | B92: 355BK300 | C92: 10158287-1RF057HF | D92: BK300 I/O Cable Assembly | E92: 38820 | G92: 516.52635
A93: 519 | B93: 519B5080 | C93: 10162456-001 | D93: RPS04B036 HSG | E93: 42120 | G93: 15.852101
A94: 519 | B94: 519B5080 | C94: 10162456-002 | D94: RPS04B037 LOCK | E94: 6000 | F94: 4000 | G94: 0.27039475
A95: 519 | B95: 519B5080 | C95: 10162457-001 | D95: RPS04S125-0011_Contact | E95: 39100 | G95: 9.5384202
A96: 519 | B96: 519B5080 | C96: 10162457-003 | D96: RPS04S125-0021_Contact | E96: 5000 | G96: 1.2256778
A97: 519 | B97: 519B5080 | C97: 10162457-004 | D97: RPS04S124-0021_Contact | E97: 5000 | G97: 1.2520435
A98: 519 | B98: 519B5080 | C98: 10162457-005 | D98: RPS04S124-0011_Contact | E98: 120000 | G98: 29.273924
A99: 355 | B99: 355BRKCA | C99: 10165116-001 | D99: BK100 SCRW MNT HSG ENHCD | E99: 8064 | F99: 10000 | G99: 3.4059535
A100: 355 | B100: 355BRKCA | C100: 10165117-001 | D100: BK100 BarKlip TPA ENHNCD | E100: 70000 | G100: 4.8995366
A101: 355 | B101: 355BRKCA | C101: 10165118-S01LF | D101: BK100 CONTACT | E101: 13000 | F101: 7000 | G101: 3.6082061
A102: 503 | B102: 5031ASM | C102: 10165987-101LF | D102: 2POS RAPID LOCK CNR KIT | E102: 130000 | G102: 583.50507
A103: 520 | B103: 520RLKT | C103: 10166013-101LF | D103: RapidLockPin CNR KitAssy | E103: 4000 | G103: 6.9904746
A104: 520 | B104: 520RLKT | C104: 10168675-001LF | D104: Rapid Lock Pin Conn Kit | E104: 105000 | F104: 300000 | G104: 182.89624
A105: 352 | B105: 352ACIPC | C105: 10170775-170501 | D105: OCP AC_IN RKEY R-MALE | E105: 2128 | G105: 22.804154
A106: 352 | B106: 352ACIPC | C106: 10170775-170502 | D106: OCP AC_IN RKEY L-MALE | E106: 2016 | G106: 21.603935
A107: 520 | B107: 356ACICB | C107: 10170827-07P002 | D107: AC 6P+1W CBL ASY RHT 90D | E107: 11556 | G107: 269.69623
A108: 520 | B108: 356ACICB | C108: 10170827-07P003 | D108: AC 6P+1W CBL ASY LFT 90D | E108: 26811 | G108: 639.66153
A109: 355 | B109: 355BRKCA | C109: 10174690-1UF026LF | D109: BK220 CABLE ASSY | E109: 0 | F109: 3500 | G109: 0
A110: 356 | B110: 356EC60A | C110: 10176873-37-F246LF | D110: 60A 7P AC-IP WHIP ASSY | E110: 274 | F110: 1000 | G110: 87.855666
A111: 356 | B111: 356EC60A | C111: 10176873-37-F247LF | D111: 60A 7P AC-IP WHIP ASSY | E111: 279 | F111: 1000 | G111: 102.31083
A112: 356 | B112: 356ORV3E | C112: 10178160-C7A302 | D112: OCP AC WHIP 78DEG 30A | E112: 0 | F112: 6375 | G112: 0
A113: 356 | B113: 356ORV3E | C113: 10178161-C7A302 | D113: OCP AC WHIP 35DEG 30A | E113: 9220 | F113: 3700 | G113: 948.43088
A114: 356 | B114: 356ORV3E | C114: 10178161-C7A303 | D114: OCP AC WHIP 35DEG 30A | E114: 45 | G114: 6.7941092
A115: 356 | B115: 356ORV3E | C115: 10178161-C7A304 | D115: OCP AC WHIP 35 ° 30A | E115: 10359 | F115: 3700 | G115: 1359.878
A116: 356 | B116: 356ORVM2 | C116: 10181064-K70002 | D116: ORV3 90-STRAIGHT 850mm | E116: 1100 | G116: 67.198296
A117: 356 | B117: 356ORVM2 | C117: 10181064-K70006 | D117: ORV3 90-STRAIGHT 2500mm | E117: 1100 | G117: 103.68855
A118: 356 | B118: 356ORVM2 | C118: 10181065-K70005 | D118: AC -AC WHIP STRAIGHT | E118: 2410 | F118: 2734 | G118: 204.53167
A119: 356 | B119: 356ORVM2 | C119: 10181065-K70007 | D119: AC -AC WHIP STRAIGHT | E119: 2420 | F119: 1252 | G119: 239.57907
A120: 503 | B120: 356ORV3I | C120: 10182476-71A801 | D120: ORV3AC INTERCONNECTEXCAB | E120: 3930 | G120: 122.53558
A121: 356 | B121: 356ORVM2 | C121: 10182948-Q50001 | D121: AC -AC WHIP FEMALE-MALE | E121: 2940 | G121: 153.06813
A122: 519 | B122: 519BK350 | C122: RPS0112002 | D122: BK350 Au PLATING | E122: 62468 | G122: 105.10035
A123: 356 | B123: 356ORV3E | C123: RPS0700749-004 | D123: ORv3 cable Assy -NEMA | E123: 13965 | F123: 1000 | G123: 785.22951
A124: 355 | B124: 355BK100 | C124: 10146534-1EP062LF | D124: BK100 Cable Assembly | E124: 3760 | G124: 54.902658
...

Sheet Sheet5
F2: PB+RAH | G2: 98 | H2: OK
F3: PB+VTR | G3: 26
F4: PBURAR | G4: 15 | H4: OK
F5: PBRAR | G5: 12
F6: PABRAH | G6: 118 | H6: OK
F7: PBVTR | G7: 75 | H7: OK
F8: PBU RAH | G8: 7
F27: PBRAR | G27: 26

Sheet Sheet3
E4: PBRAH | F4: 40 | G4: 1X2
E5: PB+RAH | F5: 70 | G5: 1X3
E6: PBRAR | F6: 20 | G6: 1X2
E7: PBVTR | F7: 89 | G7: 1X3
E8: PB+VTR | F8: 13 | G8: 1X2
E9: PBURAR | F9: 67 | G9: 1X3
E11: =73000/3000 -> 24.333333

Sheet Line efficiency
B3: Line | C3: Month | D3: DL | E3: Target-Output/Day | F3: Actual O/tper month | G3: Working days | H3: Actual O/tper day | I3: Efficiency
B5: Meta | C5: Dec | D5: 93 | E5: 2100 | F5: 39000 | G5: 24 | H5: 1980 | I5: =H5/E5 -> 0.94285714 | K5: =H5/D5 -> 21.290323 | L5: =H6/K5 -> 98.636364
C6: Jan | D6: 93 | E6: 2100 | F6: 54000 | G6: 27 | H6: 2100 | I6: =H6/2100 -> 1 | K6: =H6/D6 -> 22.580645 | L6: =H6/K6 -> 93 | M6: =(L5-L6)/L6 -> 0.060606061
B8: BK300 | C8: Dec | D8: 61 | E8: =30000/24 -> 1250 | F8: 30000 | G8: 24 | H8: 1200 | I8: =H8/E8 -> 0.96 | K8: =H8/D8 -> 19.672131 | L8: =H9/K8 -> 105.90278 | M8: =H9*0.3 -> 625
C9: Jan | D9: 92 | E9: 1645 | F9: 50000 | G9: 24 | H9: =F9/G9 -> 2083.3333 | I9: =H9/E9 -> 1.266464 | K9: =H9/D9 -> 22.644928 | L9: =H9/K9 -> 92 | M9: =M8/7.02 -> 89.031339
L10: =L8-L9 -> 13.902778
B11: BK50 | C11: Dec | D11: 17 | E11: 650 | F11: 14500 | G11: 24 | H11: =F11/G11 -> 604.16667 | I11: =H11/E11 -> 0.92948718
C12: Jan | D12: 37 | E12: 1388 | F12: 37500 | G12: 27 | H12: =F12/G12 -> 1388.8889 | I12: =H12/E12 -> 1.0006404
B14: ORV3 | C14: Dec | D14: 80 | E14: 600 | F14: 12500 | G14: 24 | H14: =F14/G14 -> 520.83333 | I14: =H14/E14 -> 0.86805556 | K14: =H14/D14 -> 6.5104167 | L14: =H15/K14 -> 107.52 | M14: =H15*0.3 -> 210
C15: Jan | D15: 80 | E15: 700 | F15: 12500 | G15: 27 | H15: 700 | I15: =H15/E15 -> 1 | K15: =H15/D15 -> 8.75 | L15: =H15/K15 -> 80 | M15: =M14/7.02 -> 29.91453
L16: =L14-L15 -> 27.52
B17: Tesla | C17: Dec | D17: 41 | E17: 1500 | F17: 30960 | G17: 24 | H17: =F17/G17 -> 1290 | I17: =H17/E17 -> 0.86
C18: Jan | D18: 48 | E18: 1500 | F18: 28000 | G18: 20 | H18: 1500 | I18: =H18/E18 -> 1
B21: BK 200XP | C21: Dec | D21: 0 | E21: 0 | F21: 0 | G21: 24 | H21: =F21/G21 -> 0
C22: Jan | D22: 13 | E22: 3100 | F22: 52000 | G22: 27 | H22: =F22/G22 -> 1925.9259 | I22: =H22/E22 -> 0.62126643

Sheet PB Billing
A1: Sl.No | B1: Item Number | C1: Unit Price | D1: Currency | E1: HPL | F1: Group | G1: Interco/ Trade | H1: Quantity Open | I1: Sales($) | J1: Sales $K | K1: Std Cost | L1: COGS $K | M1: Std Margin% | N1: Biz | O1: Remarks | R1: SA | S1: I&P | T1: SA | U1: I&P
B2: 10106132-4009101LF | C2: =J2/H2*1000 -> 1.7779699 | D2: $ | E2: 552 | F2: 552PB+RH | G2: FCI DEUTSCHLAND GmbH | H2: 1056 | I2: =H2*C2 -> 1877.5363 | J2: 1.8775363 | K2: 2.0074918 | L2: =(K2*H2)/1000 -> 2.1199114 | M2: =(J2-L2)/J2 -> -0.12909211 | N2: Trade | R2: =VLOOKUP(B2,'[6]Backup file'!$A:$F,3,FALSE) -> 0.0033 | S2: =VLOOKUP(B2,'[6]Backup file'!$A:$F,6,FALSE) -> 0.028 | T2: =R2*H2 -> 3.4848 | U2: =S2*H2 -> 29.568
B3: 10106132-4009101LF | C3: =J3/H3*1000 -> 1.7631536 | D3: $ | E3: 552 | F3: 552PB+RH | G3: FCI DEUTSCHLAND GmbH | H3: 3432 | I3: =H3*C3 -> 6051.1431 | J3: 6.0511431 | K3: 2.0074918 | L3: =(K3*H3)/1000 -> 6.889712 | M3: =(J3-L3)/J3 -> -0.13858024 | N3: Interco | R3: =VLOOKUP(B3,'[6]Backup file'!$A:$F,3,FALSE) -> 0.0033 | S3: =VLOOKUP(B3,'[6]Backup file'!$A:$F,6,FALSE) -> 0.028 | T3: =R3*H3 -> 11.3256 | U3: =S3*H3 -> 96.096
B4: 10106132-4009101LF | C4: =J4/H4*1000 -> 1.7631536 | D4: $ | E4: 552 | F4: 552PB+RH | G4: FCI DEUTSCHLAND GmbH | H4: 1584 | I4: =H4*C4 -> 2792.8353 | J4: 2.7928353 | K4: 2.0074918 | L4: =(K4*H4)/1000 -> 3.1798671 | M4: =(J4-L4)/J4 -> -0.13858025 | N4: Interco | R4: =VLOOKUP(B4,'[6]Backup file'!$A:$F,3,FALSE) -> 0.0033 | S4: =VLOOKUP(B4,'[6]Backup file'!$A:$F,6,FALSE) -> 0.028 | T4: =R4*H4 -> 5.2272 | U4: =S4*H4 -> 44.352
B5: 10106262-0010001LF | C5: =J5/H5*1000 -> 2.12184 | D5: $ | E5: 346 | F5: 346PB+RH | G5: FCI DEUTSCHLAND GmbH | H5: 3960 | I5: =H5*C5 -> 8402.4865 | J5: 8.4024865 | K5: 1.4211312 | L5: =(K5*H5)/1000 -> 5.6276796 | M5: =(J5-L5)/J5 -> 0.3302364 | R5: =VLOOKUP(B5,'[6]Backup file'!$A:$F,3,FALSE) -> 0.0033 | S5: =VLOOKUP(B5,'[6]Backup file'!$A:$F,6,FALSE) -> 0.028 | T5: =R5*H5 -> 13.068 | U5: =S5*H5 -> 110.88
B6: 10106262-0017101LF | C6: =J6/H6*1000 -> 2.26632 | D6: $ | E6: 346 | F6: 346PB+RH | G6: FCI DEUTSCHLAND GmbH | H6: 3960 | I6: =H6*C6 -> 8974.6272 | J6: 8.9746272 | K6: 1.4446804 | L6: =(K6*H6)/1000 -> 5.7209345 | M6: =(J6-L6)/J6 -> 0.3625435 | N6: Interco | R6: =VLOOKUP(B6,'[6]Backup file'!$A:$F,3,FALSE) -> 0.0033 | S6: =VLOOKUP(B6,'[6]Backup file'!$A:$F,6,FALSE) -> 0.044 | T6: =R6*H6 -> 13.068 | U6: =S6*H6 -> 174.24
B7: 10106116-4000002LF | C7: =J7/H7*1000 -> 2.25688 | D7: $ | E7: 346 | F7: 346PB+RH | G7: FCI DEUTSCHLAND GmbH | H7: 990 | I7: =H7*C7 -> 2234.3112 | J7: 2.2343112 | K7: 0.97377564 | L7: =(K7*H7)/1000 -> 0.96403788 | M7: =(J7-L7)/J7 -> 0.56853018 | N7: Trade | R7: =VLOOKUP(B7,'[6]Backup file'!$A:$F,3,FALSE) -> 0.0017 | S7: =VLOOKUP(B7,'[6]Backup file'!$A:$F,6,FALSE) -> 0.003 | T7: =R7*H7 -> 1.683 | U7: =S7*H7 -> 2.97
B8: 10106116-C009001LF | C8: =J8/H8*1000 -> 4.4960997 | D8: $ | E8: 346 | F8: 346PB+RH | G8: FCI JAPAN KK | H8: 132 | I8: =H8*C8 -> 593.48515 | J8: 0.59348515 | K8: 3.4168202 | L8: =(K8*H8)/1000 -> 0.45102026 | M8: =(J8-L8)/J8 -> 0.24004794 | N8: Trade | R8: =VLOOKUP(B8,'[6]Backup file'!$A:$F,3,FALSE) -> 0.0033 | S8: =VLOOKUP(B8,'[6]Backup file'!$A:$F,6,FALSE) -> 0.0428 | T8: =R8*H8 -> 0.4356 | U8: =S8*H8 -> 5.6496
B9: 10106124-4006005LF | C9: =J9/H9*1000 -> 1.6784951 | D9: $ | E9: 552 | F9: 552PB+RH | G9: FCI JAPAN KK | H9: 264 | I9: =H9*C9 -> 443.1227 | J9: 0.4431227 | K9: 1.9114091 | L9: =(K9*H9)/1000 -> 0.50461201 | M9: =(J9-L9)/J9 -> -0.13876362 | N9: Trade | R9: =VLOOKUP(B9,'[6]Backup file'!$A:$F,3,FALSE) -> 0.0033 | S9: =VLOOKUP(B9,'[6]Backup file'!$A:$F,6,FALSE) -> 0.027 | T9: =R9*H9 -> 0.8712 | U9: =S9*H9 -> 7.128
B10: 10106124-4006005LF | C10: =J10/H10*1000 -> 1.6784951 | D10: $ | E10: 552 | F10: 552PB+RH | G10: FCI JAPAN KK | H10: 264 | I10: =H10*C10 -> 443.1227 | J10: 0.4431227 | K10: 1.9114091 | L10: =(K10*H10)/1000 -> 0.50461201 | M10: =(J10-L10)/J10 -> -0.13876362 | N10: Trade | R10: =VLOOKUP(B10,'[6]Backup file'!$A:$F,3,FALSE) -> 0.0033 | S10: =VLOOKUP(B10,'[6]Backup file'!$A:$F,6,FALSE) -> 0.027 | T10: =R10*H10 -> 0.8712 | U10: =S10*H10 -> 7.128
B11: 10106124-4006005LF | C11: =J11/H11*1000 -> 1.6784951 | D11: $ | E11: 552 | F11: 552PB+RH | G11: FCI JAPAN KK | H11: 264 | I11: =H11*C11 -> 443.1227 | J11: 0.4431227 | K11: 1.9114091 | L11: =(K11*H11)/1000 -> 0.50461201 | M11: =(J11-L11)/J11 -> -0.13876362 | N11: Trade | R11: =VLOOKUP(B11,'[6]Backup file'!$A:$F,3,FALSE) -> 0.0033 | S11: =VLOOKUP(B11,'[6]Backup file'!$A:$F,6,FALSE) -> 0.027 | T11: =R11*H11 -> 0.8712 | U11: =S11*H11 -> 7.128
B12: 10106124-4006005LF | C12: =J12/H12*1000 -> 1.6784951 | D12: $ | E12: 552 | F12: 552PB+RH | G12: FCI JAPAN KK | H12: 264 | I12: =H12*C12 -> 443.1227 | J12: 0.4431227 | K12: 1.9114091 | L12: =(K12*H12)/1000 -> 0.50461201 | M12: =(J12-L12)/J12 -> -0.13876362 | N12: Trade | R12: =VLOOKUP(B12,'[6]Backup file'!$A:$F,3,FALSE) -> 0.0033 | S12: =VLOOKUP(B12,'[6]Backup file'!$A:$F,6,FALSE) -> 0.027 | T12: =R12*H12 -> 0.8712 | U12: =S12*H12 -> 7.128
B13: 10106124-4006005LF | C13: =J13/H13*1000 -> 1.6784951 | D13: $ | E13: 552 | F13: 552PB+RH | G13: FCI JAPAN KK | H13: 264 | I13: =H13*C13 -> 443.1227 | J13: 0.4431227 | K13: 1.9114091 | L13: =(K13*H13)/1000 -> 0.50461201 | M13: =(J13-L13)/J13 -> -0.13876362 | N13: Interco | R13: =VLOOKUP(B13,'[6]Backup file'!$A:$F,3,FALSE) -> 0.0033 | S13: =VLOOKUP(B13,'[6]Backup file'!$A:$F,6,FALSE) -> 0.027 | T13: =R13*H13 -> 0.8712 | U13: =S13*H13 -> 7.128
B14: 10106124-4006005LF | C14: =J14/H14*1000 -> 1.6784951 | D14: $ | E14: 552 | F14: 552PB+RH | G14: FCI JAPAN KK | H14: 264 | I14: =H14*C14 -> 443.1227 | J14: 0.4431227 | K14: 1.9114091 | L14: =(K14*H14)/1000 -> 0.50461201 | M14: =(J14-L14)/J14 -> -0.13876362 | N14: Interco | R14: =VLOOKUP(B14,'[6]Backup file'!$A:$F,3,FALSE) -> 0.0033 | S14: =VLOOKUP(B14,'[6]Backup file'!$A:$F,6,FALSE) -> 0.027 | T14: =R14*H14 -> 0.8712 | U14: =S14*H14 -> 7.128
B15: 10106124-4006005LF | C15: =J15/H15*1000 -> 1.6784951 | D15: $ | E15: 552 | F15: 552PB+RH | G15: FCI JAPAN KK | H15: 264 | I15: =H15*C15 -> 443.1227 | J15: 0.4431227 | K15: 1.9114091 | L15: =(K15*H15)/1000 -> 0.50461201 | M15: =(J15-L15)/J15 -> -0.13876362 | N15: Interco | R15: =VLOOKUP(B15,'[6]Backup file'!$A:$F,3,FALSE) -> 0.0033 | S15: =VLOOKUP(B15,'[6]Backup file'!$A:$F,6,FALSE) -> 0.027 | T15: =R15*H15 -> 0.8712 | U15: =S15*H15 -> 7.128
B16: 10106124-8005003LF | C16: =J16/H16*1000 -> 2.13486 | D16: $ | E16: 346 | F16: 346PB+RH | G16: FCI USA LLC | H16: 1008 | I16: =H16*C16 -> 2151.9388 | J16: 2.1519388 | K16: 2.1326551 | L16: =(K16*H16)/1000 -> 2.1497164 | M16: =(J16-L16)/J16 -> 0.0010327763 | N16: Interco | R16: =VLOOKUP(B16,'[6]Backup file'!$A:$F,3,FALSE) -> 0.002181 | S16: =VLOOKUP(B16,'[6]Backup file'!$A:$F,6,FALSE) -> 0.013086 | T16: =R16*H16 -> 2.198448 | U16: =S16*H16 -> 13.190688
B17: 10106124-E008001LF | C17: =J17/H17*1000 -> 1.4783271 | D17: $ | E17: 346 | F17: 346PB+RH | G17: AMPHENOL FCI ASIA PTE LT | H17: 8052 | I17: =H17*C17 -> 11903.49 | J17: 11.90349 | K17: 1.5405069 | L17: =(K17*H17)/1000 -> 12.404162 | M17: =(J17-L17)/J17 -> -0.042060958 | N17: Interco | R17: =VLOOKUP(B17,'[6]Backup file'!$A:$F,3,FALSE) -> 0.002 | S17: =VLOOKUP(B17,'[6]Backup file'!$A:$F,6,FALSE) -> 0.018 | T17: =R17*H17 -> 16.104 | U17: =S17*H17 -> 144.936
A18: NOV | B18: 10106124-F005K01LF | C18: =J18/H18*1000 -> 4.0608 | D18: $ | E18: 346 | F18: 346PB+RH | G18: FCI USA LLC | H18: 396 | I18: =H18*C18 -> 1608.0768 | J18: 1.6080768 | K18: 2.8765778 | L18: =(K18*H18)/1000 -> 1.1391248 | M18: =(J18-L18)/J18 -> 0.29162288 | N18: Interco | R18: =VLOOKUP(B18,'[6]Backup file'!$A:$F,3,FALSE) -> 0.003 | S18: =VLOOKUP(B18,'[6]Backup file'!$A:$F,6,FALSE) -> 0.035 | T18: =R18*H18 -> 1.188 | U18: =S18*H18 -> 13.86
B19: 10106124-F005K01LF | C19: =J19/H19*1000 -> 4.0608 | D19: $ | E19: 346 | F19: 346PB+RH | G19: FCI USA LLC | H19: 1320 | I19: =H19*C19 -> 5360.256 | J19: 5.360256 | K19: 2.8765778 | L19: =(K19*H19)/1000 -> 3.7970828 | M19: =(J19-L19)/J19 -> 0.29162287 | N19: Interco | R19: =VLOOKUP(B19,'[6]Backup file'!$A:$F,3,FALSE) -> 0.003 | S19: =VLOOKUP(B19,'[6]Backup file'!$A:$F,6,FALSE) -> 0.035 | T19: =R19*H19 -> 3.96 | U19: =S19*H19 -> 46.2
B20: 10106132-4009101LF | C20: =J20/H20*1000 -> 1.7779699 | D20: $ | E20: 552 | F20: 552PB+RH | G20: FCI DEUTSCHLAND GmbH | H20: 1056 | I20: =H20*C20 -> 1877.5363 | J20: 1.8775363 | K20: 2.0074918 | L20: =(K20*H20)/1000 -> 2.1199114 | M20: =(J20-L20)/J20 -> -0.12909211 | N20: Interco | R20: =VLOOKUP(B20,'[6]Backup file'!$A:$F,3,FALSE) -> 0.0033 | S20: =VLOOKUP(B20,'[6]Backup file'!$A:$F,6,FALSE) -> 0.028 | T20: =R20*H20 -> 3.4848 | U20: =S20*H20 -> 29.568
B21: 10106262-0002002LF | C21: =J21/H21*1000 -> 1.4464451 | D21: $ | E21: 552 | F21: 552PB+RH | G21: FCI JAPAN KK | H21: 924 | I21: =H21*C21 -> 1336.5152 | J21: 1.3365152 | K21: 0.64251853 | L21: =(K21*H21)/1000 -> 0.59368712 | M21: =(J21-L21)/J21 -> 0.55579472 | N21: Interco | R21: =VLOOKUP(B21,'[6]Backup file'!$A:$F,3,FALSE) -> 0.0033 | S21: =VLOOKUP(B21,'[6]Backup file'!$A:$F,6,FALSE) -> 0.016935 | T21: =R21*H21 -> 3.0492 | U21: =S21*H21 -> 15.64794
B22: 10106262-0002002LF | C22: =J22/H22*1000 -> 1.4464451 | D22: $ | E22: 552 | F22: 552PB+RH | G22: FCI JAPAN KK | H22: 924 | I22: =H22*C22 -> 1336.5152 | J22: 1.3365152 | K22: 0.64251853 | L22: =(K22*H22)/1000 -> 0.59368712 | M22: =(J22-L22)/J22 -> 0.55579472 | R22: =VLOOKUP(B22,'[6]Backup file'!$A:$F,3,FALSE) -> 0.0033 | S22: =VLOOKUP(B22,'[6]Backup file'!$A:$F,6,FALSE) -> 0.016935 | T22: =R22*H22 -> 3.0492 | U22: =S22*H22 -> 15.64794
B23: 10106262-0527102LF | C23: =J23/H23*1000 -> 4.74464 | D23: $ | E23: 552 | F23: 552PB+RH | G23: FCI DEUTSCHLAND GmbH | H23: 1056 | I23: =H23*C23 -> 5010.3398 | J23: 5.0103398 | K23: 3.0257158 | L23: =(K23*H23)/1000 -> 3.1951558 | M23: =(J23-L23)/J23 -> 0.36228759 | R23: =VLOOKUP(B23,'[6]Backup file'!$A:$F,3,FALSE) -> 0.0056 | S23: =VLOOKUP(B23,'[6]Backup file'!$A:$F,6,FALSE) -> 0.089 | T23: =R23*H23 -> 5.9136 | U23: =S23*H23 -> 93.984
B24: 10106262-1C03012LF | C24: =J24/H24*1000 -> 2.001 | D24: $ | E24: 552 | F24: 552PB+RH | G24: AMPHENOL FCI ASIA PTE LT | H24: 3366 | I24: =H24*C24 -> 6735.366 | J24: 6.735366 | K24: 3.1593212 | L24: =(K24*H24)/1000 -> 10.634275 | M24: =(J24-L24)/J24 -> -0.57887118 | R24: =VLOOKUP(B24,'[6]Backup file'!$A:$F,3,FALSE) -> 0.00279 | S24: =VLOOKUP(B24,'[6]Backup file'!$A:$F,6,FALSE) -> 0.02976 | T24: =R24*H24 -> 9.39114 | U24: =S24*H24 -> 100.17216
B25: 10106262-1C03012LF | C25: =J25/H25*1000 -> 2.001 | D25: $ | E25: 552 | F25: 552PB+RH | G25: AMPHENOL FCI ASIA PTE LT | H25: 9504 | I25: =H25*C25 -> 19017.504 | J25: 19.017504 | K25: 3.1593212 | L25: =(K25*H25)/1000 -> 30.026189 | M25: =(J25-L25)/J25 -> -0.57887119 | R25: =VLOOKUP(B25,'[6]Backup file'!$A:$F,3,FALSE) -> 0.00279 | S25: =VLOOKUP(B25,'[6]Backup file'!$A:$F,6,FALSE) -> 0.02976 | T25: =R25*H25 -> 26.51616 | U25: =S25*H25 -> 282.83904
B26: 10106262-1C03012LF | C26: =J26/H26*1000 -> 1.984325 | D26: $ | E26: 552 | F26: 552PB+RH | G26: AMPHENOL FCI ASIA PTE LT | H26: 9702 | I26: =H26*C26 -> 19251.921 | J26: 19.251921 | K26: 3.1593212 | L26: =(K26*H26)/1000 -> 30.651735 | M26: =(J26-L26)/J26 -> -0.592139 | R26: =VLOOKUP(B26,'[6]Backup file'!$A:$F,3,FALSE) -> 0.00279 | S26: =VLOOKUP(B26,'[6]Backup file'!$A:$F,6,FALSE) -> 0.02976 | T26: =R26*H26 -> 27.06858 | U26: =S26*H26 -> 288.73152
B27: 10106262-1C03012LF | C27: =J27/H27*1000 -> 1.984325 | D27: $ | E27: 552 | F27: 552PB+RH | G27: AMPHENOL FCI ASIA PTE LT | H27: 1188 | I27: =H27*C27 -> 2357.3781 | J27: 2.3573781 | K27: 3.1593212 | L27: =(K27*H27)/1000 -> 3.7532736 | M27: =(J27-L27)/J27 -> -0.59213902 | N27: Interco | R27: =VLOOKUP(B27,'[6]Backup file'!$A:$F,3,FALSE) -> 0.00279 | S27: =VLOOKUP(B27,'[6]Backup file'!$A:$F,6,FALSE) -> 0.02976 | T27: =R27*H27 -> 3.31452 | U27: =S27*H27 -> 35.35488
B28: 10106262-1C03012LF | C28: =J28/H28*1000 -> 1.872 | D28: $ | E28: 552 | F28: 552PB+RH | G28: FCI USA LLC | H28: 4950 | I28: =H28*C28 -> 9266.4 | J28: 9.2664 | K28: 3.1593212 | L28: =(K28*H28)/1000 -> 15.63864 | M28: =(J28-L28)/J28 -> -0.68767161 | N28: Interco | R28: =VLOOKUP(B28,'[6]Backup file'!$A:$F,3,FALSE) -> 0.00279 | S28: =VLOOKUP(B28,'[6]Backup file'!$A:$F,6,FALSE) -> 0.02976 | T28: =R28*H28 -> 13.8105 | U28: =S28*H28 -> 147.312
B29: 10106262-1C03012LF | C29: =J29/H29*1000 -> 2.001 | D29: $ | E29: 552 | F29: 552PB+RH | G29: AMPHENOL FCI ASIA PTE LT | H29: 8910 | I29: =H29*C29 -> 17828.91 | J29: 17.82891 | K29: 3.1593212 | L29: =(K29*H29)/1000 -> 28.149552 | M29: =(J29-L29)/J29 -> -0.57887118 | R29: =VLOOKUP(B29,'[6]Backup file'!$A:$F,3,FALSE) -> 0.00279 | S29: =VLOOKUP(B29,'[6]Backup file'!$A:$F,6,FALSE) -> 0.02976 | T29: =R29*H29 -> 24.8589 | U29: =S29*H29 -> 265.1616
B30: 10106262-1C03012LF | C30: =J30/H30*1000 -> 1.984325 | D30: $ | E30: 552 | F30: 552PB+RH | G30: AMPHENOL FCI ASIA PTE LT | H30: 9306 | I30: =H30*C30 -> 18466.128 | J30: 18.466128 | K30: 3.1593212 | L30: =(K30*H30)/1000 -> 29.400643 | M30: =(J30-L30)/J30 -> -0.592139 | R30: =VLOOKUP(B30,'[6]Backup file'!$A:$F,3,FALSE) -> 0.00279 | S30: =VLOOKUP(B30,'[6]Backup file'!$A:$F,6,FALSE) -> 0.02976 | T30: =R30*H30 -> 25.96374 | U30: =S30*H30 -> 276.94656
B31: 10106262-1C03012LF | C31: =J31/H31*1000 -> 1.984325 | D31: $ | E31: 552 | F31: 552PB+RH | G31: AMPHENOL FCI ASIA PTE LT | H31: 8514 | I31: =H31*C31 -> 16894.543 | J31: 16.894543 | K31: 3.1593212 | L31: =(K31*H31)/1000 -> 26.898461 | M31: =(J31-L31)/J31 -> -0.59213901 | R31: =VLOOKUP(B31,'[6]Backup file'!$A:$F,3,FALSE) -> 0.00279 | S31: =VLOOKUP(B31,'[6]Backup file'!$A:$F,6,FALSE) -> 0.02976 | T31: =R31*H31 -> 23.75406 | U31: =S31*H31 -> 253.37664
B32: 10106269-1C03005LF | C32: =J32/H32*1000 -> 1.5111111 | D32: $ | E32: 346 | F32: 346PB+VR | G32: AVNET ASIA PTE Ltd | H32: 90000 | I32: =H32*C32 -> 136000 | J32: 136 | K32: 1.9989734 | L32: =(K32*H32)/1000 -> 179.90761 | M32: =(J32-L32)/J32 -> -0.32285007 | R32: =VLOOKUP(B32,'[6]Backup file'!$A:$F,3,FALSE) -> 0.0041667 | S32: =VLOOKUP(B32,'[6]Backup file'!$A:$F,6,FALSE) -> 0.0377778 | T32: =R32*H32 -> 375.003 | U32: =S32*H32 -> 3400.002
B33: 51940-329LF | C33: =J33/H33*1000 -> 2.06727 | D33: $ | E33: 552 | F33: 552PWBVR | G33: FCI DEUTSCHLAND GmbH | H33: 1056 | I33: =H33*C33 -> 2183.0371 | J33: 2.1830371 | K33: 1.60162 | L33: =(K33*H33)/1000 -> 1.6913108 | M33: =(J33-L33)/J33 -> 0.22524874 | R33: =VLOOKUP(B33,'[6]Backup file'!$A:$F,3,FALSE) -> 0.003 | S33: =VLOOKUP(B33,'[6]Backup file'!$A:$F,6,FALSE) -> 0.028728 | T33: =R33*H33 -> 3.168 | U33: =S33*H33 -> 30.336768
B34: 51741-10002406CCLF | C34: =J34/H34*1000 -> 1.7719101 | D34: $ | E34: 552 | F34: 552PWBVR | G34: FCI USA LLC | H34: 264 | I34: =H34*C34 -> 467.78426 | J34: 0.46778426 | K34: 1.0555661 | L34: =(K34*H34)/1000 -> 0.27866945 | M34: =(J34-L34)/J34 -> 0.40427785 | R34: =VLOOKUP(B34,'[6]Backup file'!$A:$F,3,FALSE) -> 0.003 | S34: =VLOOKUP(B34,'[6]Backup file'!$A:$F,6,FALSE) -> 0.00825104 | T34: =R34*H34 -> 0.792 | U34: =S34*H34 -> 2.1782746
B35: 51740-10703206CCLF | C35: =J35/H35*1000 -> 2.1185768 | D35: $ | E35: 552 | F35: 552PWBVR | G35: FCI USA LLC | H35: 1056 | I35: =H35*C35 -> 2237.2171 | J35: 2.2372171 | K35: 2.241383 | L35: =(K35*H35)/1000 -> 2.3669004 | M35: =(J35-L35)/J35 -> -0.057966354 | R35: =VLOOKUP(B35,'[6]Backup file'!$A:$F,3,FALSE) -> 0.0061 | S35: =VLOOKUP(B35,'[6]Backup file'!$A:$F,6,FALSE) -> 0.0143181 | T35: =R35*H35 -> 6.4416 | U35: =S35*H35 -> 15.119914
B36: 51741-10002406CCLF | C36: =J36/H36*1000 -> 1.7719101 | D36: $ | E36: 552 | F36: 552PWBVR | G36: FCI USA LLC | H36: 264 | I36: =H36*C36 -> 467.78426 | J36: 0.46778426 | K36: 1.0555661 | L36: =(K36*H36)/1000 -> 0.27866945 | M36: =(J36-L36)/J36 -> 0.40427785 | R36: =VLOOKUP(B36,'[6]Backup file'!$A:$F,3,FALSE) -> 0.003 | S36: =VLOOKUP(B36,'[6]Backup file'!$A:$F,6,FALSE) -> 0.00825104 | T36: =R36*H36 -> 0.792 | U36: =S36*H36 -> 2.1782746
B37: 51751-018LF | C37: =J37/H37*1000 -> 2.61012 | D37: $ | E37: 552 | F37: 552PWBVR | G37: FCI DEUTSCHLAND GmbH | H37: 792 | I37: =H37*C37 -> 2067.215 | J37: 2.067215 | K37: 1.3973221 | L37: =(K37*H37)/1000 -> 1.1066791 | M37: =(J37-L37)/J37 -> 0.46465216 | R37: =VLOOKUP(B37,'[6]Backup file'!$A:$F,3,FALSE) -> 0.003 | S37: =VLOOKUP(B37,'[6]Backup file'!$A:$F,6,FALSE) -> 0.0087 | T37: =R37*H37 -> 2.376 | U37: =S37*H37 -> 6.8904
B38: 51940-329LF | C38: =J38/H38*1000 -> 2.06727 | D38: $ | E38: 552 | F38: 552PWBVR | G38: FCI DEUTSCHLAND GmbH | H38: 1056 | I38: =H38*C38 -> 2183.0371 | J38: 2.1830371 | K38: 1.60162 | L38: =(K38*H38)/1000 -> 1.6913108 | M38: =(J38-L38)/J38 -> 0.22524874 | R38: =VLOOKUP(B38,'[6]Backup file'!$A:$F,3,FALSE) -> 0.003 | S38: =VLOOKUP(B38,'[6]Backup file'!$A:$F,6,FALSE) -> 0.028728 | T38: =R38*H38 -> 3.168 | U38: =S38*H38 -> 30.336768
B39: 10106268-7006001LF | C39: =J39/H39*1000 -> 2.7951999 | D39: $ | E39: 552 | F39: 552PB+VR | G39: FCI USA LLC | H39: 648 | I39: =H39*C39 -> 1811.2896 | J39: 1.8112896 | K39: 1.8813354 | L39: =(K39*H39)/1000 -> 1.2191053 | M39: =(J39-L39)/J39 -> 0.32694067 | R39: =VLOOKUP(B39,'[6]Backup file'!$A:$F,3,FALSE) -> 0.0067 | S39: =VLOOKUP(B39,'[6]Backup file'!$A:$F,6,FALSE) -> 0.03024444 | T39: =R39*H39 -> 4.3416 | U39: =S39*H39 -> 19.598397
B40: 10106139-4009101LF | C40: =J40/H40*1000 -> 1.49389 | D40: $ | E40: 552 | F40: 552PB+VR | G40: FCI DEUTSCHLAND GmbH | H40: 2016 | I40: =H40*C40 -> 3011.6822 | J40: 3.0116822 | K40: 0.84788465 | L40: =(K40*H40)/1000 -> 1.7093355 | M40: =(J40-L40)/J40 -> 0.43243167 | R40: =VLOOKUP(B40,'[6]Backup file'!$A:$F,3,FALSE) -> 0.01 | S40: =VLOOKUP(B40,'[6]Backup file'!$A:$F,6,FALSE) -> 0.02895 | T40: =R40*H40 -> 20.16 | U40: =S40*H40 -> 58.3632
... B43: 10106131-9014001LF | C43: =J43/H43*1000 -> 2.5488001 | D43: $ | E43: 346 | F43: 346PB+VR | G43: FCI USA LLC | H43: 704 | I43: =H43*C43 -> 1794.3553 | J43: 1.7943553 | K43: 2.8054766 | L43: =(K43*H43)/1000 -> 1.9750555 | M43: =(J43-L43)/J43 -> -0.10070485 | R43: =VLOOKUP(B43,'[6]Backup file'!$A:$F,3,FALSE) -> 0.012 | S43: =VLOOKUP(B43,'[6]Backup file'!$A:$F,6,FALSE) -> 0.028 | T43: =R43*H43 -> 8.448 | U43: =S43*H43 -> 19.712
B44: 10106269-3606001LF | C44: =J44/H44*1000 -> 3.19054 | D44: $ | E44: 552 | F44: 552PB+VR | G44: FCI USA LLC | H44: 864 | I44: =H44*C44 -> 2756.6265 | J44: 2.7566265 | K44: 1.4898735 | L44: =(K44*H44)/1000 -> 1.2872507 | M44: =(J44-L44)/J44 -> 0.53303405 | N44: Interco | R44: 0.012 | S44: =VLOOKUP(B44,'[6]Backup file'!$A:$F,6,FALSE) -> 0.0365454 | T44: =R44*H44 -> 10.368 | U44: =S44*H44 -> 31.575226
B45: 10106139-4027101LF | C45: =J45/H45*1000 -> 3.49773 | D45: $ | E45: 346 | F45: 346PB+VR | G45: FCI DEUTSCHLAND GmbH | H45: 288 | I45: =H45*C45 -> 1007.3462 | J45: 1.0073462 | K45: 3.3336817 | L45: =(K45*H45)/1000 -> 0.96010033 | M45: =(J45-L45)/J45 -> 0.046901348 | R45: =VLOOKUP(B45,'[6]Backup file'!$A:$F,3,FALSE) -> 0.03 | S45: =VLOOKUP(B45,'[6]Backup file'!$A:$F,6,FALSE) -> 0.029 | T45: =R45*H45 -> 8.64 | U45: =S45*H45 -> 8.352
B46: 10106268-0527101LF | C46: =J46/H46*1000 -> 3.48744 | D46: $ | E46: 346 | F46: 346PB+VR | G46: FCI DEUTSCHLAND GmbH | H46: 2016 | I46: =H46*C46 -> 7030.679 | J46: 7.030679 | K46: 3.0958332 | L46: =(K46*H46)/1000 -> 6.2411998 | M46: =(J46-L46)/J46 -> 0.11229062 | R46: =VLOOKUP(B46,'[6]Backup file'!$A:$F,3,FALSE) -> 0.03 | S46: =VLOOKUP(B46,'[6]Backup file'!$A:$F,6,FALSE) -> 0.03935 | T46: =R46*H46 -> 60.48 | U46: =S46*H46 -> 79.3296
B47: 51940-549LF | C47: =J47/H47*1000 -> 1.88034 | D47: $ | E47: 552 | F47: 552PWBVR | G47: FCI DEUTSCHLAND GmbH | H47: 1152 | I47: =H47*C47 -> 2166.1517 | J47: 2.1661517 | K47: 1.1932896 | L47: =(K47*H47)/1000 -> 1.3746696 | M47: =(J47-L47)/J47 -> 0.36538628 | R47: =VLOOKUP(B47,'[6]Backup file'!$A:$F,3,FALSE) -> 0.015 | S47: =VLOOKUP(B47,'[6]Backup file'!$A:$F,6,FALSE) -> 0.025 | T47: =R47*H47 -> 17.28 | U47: =S47*H47 -> 28.8
B48: 51940-728FLF | C48: =J48/H48*1000 -> 2.43 | D48: $ | E48: 552 | F48: 552PWBVR | G48: FCI CONNECTORS KOREA LTD | H48: 1056 | I48: =H48*C48 -> 2566.08 | J48: 2.56608 | K48: 1.9148744 | L48: =(K48*H48)/1000 -> 2.0221073 | M48: =(J48-L48)/J48 -> 0.21198588 | R48: =VLOOKUP(B48,'[6]Backup file'!$A:$F,3,FALSE) -> 0.012 | S48: =VLOOKUP(B48,'[6]Backup file'!$A:$F,6,FALSE) -> 0.026 | T48: =R48*H48 -> 12.672 | U48: =S48*H48 -> 27.456
B49: 51966-10006400AALF | C49: =J49/H49*1000 -> 1.7296601 | D49: $ | E49: 552 | F49: 552PBRAH | G49: FCI DEUTSCHLAND GmbH | H49: 264 | I49: =H49*C49 -> 456.63027 | J49: 0.45663027 | K49: 1.1494446 | L49: =(K49*H49)/1000 -> 0.30345337 | M49: =(J49-L49)/J49 -> 0.33545061 | R49: =VLOOKUP(B49,'[6]Backup file'!$A:$F,3,FALSE) -> 0.002 | S49: =VLOOKUP(B49,'[6]Backup file'!$A:$F,6,FALSE) -> 0.022 | T49: =R49*H49 -> 0.528 | U49: =S49*H49 -> 5.808
B50: 51939-905LF | C50: =J50/H50*1000 -> 1.77933 | D50: $ | E50: 552 | F50: 552PBRAH | G50: FCI DEUTSCHLAND GmbH | H50: 2904 | I50: =H50*C50 -> 5167.1743 | J50: 5.1671743 | K50: 1.1540828 | L50: =(K50*H50)/1000 -> 3.3514566 | M50: =(J50-L50)/J50 -> 0.35139471 | R50: =VLOOKUP(B50,'[6]Backup file'!$A:$F,3,FALSE) -> 0.002 | S50: =VLOOKUP(B50,'[6]Backup file'!$A:$F,6,FALSE) -> 0.026 | T50: =R50*H50 -> 5.808 | U50: =S50*H50 -> 75.504
B51: 51939-902LF | C51: =J51/H51*1000 -> 2.63971 | D51: $ | E51: 552 | F51: 552PBRAH | G51: FCI DEUTSCHLAND GmbH | H51: 5478 | I51: =H51*C51 -> 14460.331 | J51: 14.460331 | K51: 2.1567894 | L51: =(K51*H51)/1000 -> 11.814892 | M51: =(J51-L51)/J51 -> 0.18294457 | N51: Interco | R51: =VLOOKUP(B51,'[6]Backup file'!$A:$F,3,FALSE) -> 0.003 | S51: =VLOOKUP(B51,'[6]Backup file'!$A:$F,6,FALSE) -> 0.055 | T51: =R51*H51 -> 16.434 | U51: =S51*H51 -> 301.29
B52: 51939-903LF | C52: =J52/H52*1000 -> 2.53899 | D52: $ | E52: 552 | F52: 552PBRAH | G52: FCI DEUTSCHLAND GmbH | H52: 1848 | I52: =H52*C52 -> 4692.0536 | J52: 4.6920536 | K52: 1.9335239 | L52: =(K52*H52)/1000 -> 3.5731522 | M52: =(J52-L52)/J52 -> 0.23846731 | R52: =VLOOKUP(B52,'[6]Backup file'!$A:$F,3,FALSE) -> 0.002 | S52: =VLOOKUP(B52,'[6]Backup file'!$A:$F,6,FALSE) -> 0.026 | T52: =R52*H52 -> 3.696 | U52: =S52*H52 -> 48.048
B53: 51939-906LF | C53: =J53/H53*1000 -> 1.21427 | D53: $ | E53: 552 | F53: 552PBRAH | G53: FCI DEUTSCHLAND GmbH | H53: 5148 | I53: =H53*C53 -> 6251.0619 | J53: 6.2510619 | K53: 0.98512999 | L53: =(K53*H53)/1000 -> 5.0714492 | M53: =(J53-L53)/J53 -> 0.18870598 | R53: =VLOOKUP(B53,'[6]Backup file'!$A:$F,3,FALSE) -> 0.002 | S53: =VLOOKUP(B53,'[6]Backup file'!$A:$F,6,FALSE) -> 0.026977273 | T53: =R53*H53 -> 10.296 | U53: =S53*H53 -> 138.879
B54: 51939-910LF | C54: =J54/H54*1000 -> 2.22812 | D54: $ | E54: 552 | F54: 552PBRAH | G54: FCI DEUTSCHLAND GmbH | H54: 1584 | I54: =H54*C54 -> 3529.3421 | J54: 3.5293421 | K54: 1.685436 | L54: =(K54*H54)/1000 -> 2.6697306 | M54: =(J54-L54)/J54 -> 0.24356139 | R54: =VLOOKUP(B54,'[6]Backup file'!$A:$F,3,FALSE) -> 0.002 | S54: =VLOOKUP(B54,'[6]Backup file'!$A:$F,6,FALSE) -> 0.022 | T54: =R54*H54 -> 3.168 | U54: =S54*H54 -> 34.848
B55: 51939-904LF | C55: =J55/H55*1000 -> 1.71116 | D55: $ | E55: 552 | F55: 552PBRAH | G55: FCI DEUTSCHLAND GmbH | H55: 1980 | I55: =H55*C55 -> 3388.0969 | J55: 3.3880969 | K55: 0.89965173 | L55: =(K55*H55)/1000 -> 1.7813104 | M55: =(J55-L55)/J55 -> 0.47424454 | N55: Interco | R55: =VLOOKUP(B55,'[6]Backup file'!$A:$F,3,FALSE) -> 0.003 | S55: =VLOOKUP(B55,'[6]Backup file'!$A:$F,6,FALSE) -> 0.05 | T55: =R55*H55 -> 5.94 | U55: =S55*H55 -> 99
B56: 51939-1257LF | C56: =J56/H56*1000 -> 3.21462 | D56: $ | E56: 552 | F56: 552PBRAH | G56: FCI DEUTSCHLAND GmbH | H56: 1056 | I56: =H56*C56 -> 3394.6388 | J56: 3.3946388 | K56: 1.3315705 | L56: =(K56*H56)/1000 -> 1.4061385 | M56: =(J56-L56)/J56 -> 0.5857767 | R56: =VLOOKUP(B56,'[6]Backup file'!$A:$F,3,FALSE) -> 0.006 | S56: =VLOOKUP(B56,'[6]Backup file'!$A:$F,6,FALSE) -> 0.029 | T56: =R56*H56 -> 6.336 | U56: =S56*H56 -> 30.624
B57: 51939-137LF | C57: =J57/H57*1000 -> 2.1260099 | D57: $ | E57: 552 | F57: 552PBRAH | G57: FCI DEUTSCHLAND GmbH | H57: 132 | I57: =H57*C57 -> 280.63331 | J57: 0.28063331 | K57: 1.3247009 | L57: =(K57*H57)/1000 -> 0.17486051 | M57: =(J57-L57)/J57 -> 0.37690749 | R57: =VLOOKUP(B57,'[6]Backup file'!$A:$F,3,FALSE) -> 0.0019 | S57: =VLOOKUP(B57,'[6]Backup file'!$A:$F,6,FALSE) -> 0.014668182 | T57: =R57*H57 -> 0.2508 | U57: =S57*H57 -> 1.9362
B58: 51736-004LF | C58: =J58/H58*1000 -> 2.22136 | D58: $ | E58: 552 | F58: 552PBRAH | G58: FCI DEUTSCHLAND GmbH | H58: 990 | I58: =H58*C58 -> 2199.1464 | J58: 2.1991464 | K58: 0.94533558 | L58: =(K58*H58)/1000 -> 0.93588222 | M58: =(J58-L58)/J58 -> 0.57443387 | N58: Interco | R58: =VLOOKUP(B58,'[6]Backup file'!$A:$F,3,FALSE) -> 0.0016 | S58: =VLOOKUP(B58,'[6]Backup file'!$A:$F,6,FALSE) -> 0.0197 | T58: =R58*H58 -> 1.584 | U58: =S58*H58 -> 19.503
B59: 51939-922LF | C59: =J59/H59*1000 -> 1.60636 | D59: $ | E59: 552 | F59: 552PBRAH | G59: FCI DEUTSCHLAND GmbH | H59: 1584 | I59: =H59*C59 -> 2544.4743 | J59: 2.5444743 | K59: 0.84290501 | L59: =(K59*H59)/1000 -> 1.3351615 | M59: =(J59-L59)/J59 -> 0.47527018 | R59: =VLOOKUP(B59,'[6]Backup file'!$A:$F,3,FALSE) -> 0.003 | S59: =VLOOKUP(B59,'[6]Backup file'!$A:$F,6,FALSE) -> 0.026 | T59: =R59*H59 -> 4.752 | U59: =S59*H59 -> 41.184
B60: 51939-906LF | C60: =J60/H60*1000 -> 1.21427 | D60: $ | E60: 552 | F60: 552PBRAH | G60: FCI DEUTSCHLAND GmbH | H60: 1980 | I60: =H60*C60 -> 2404.2546 | J60: 2.4042546 | K60: 0.98512999 | L60: =(K60*H60)/1000 -> 1.9505574 | M60: =(J60-L60)/J60 -> 0.18870597 | R60: =VLOOKUP(B60,'[6]Backup file'!$A:$F,3,FALSE) -> 0.002 | S60: =VLOOKUP(B60,'[6]Backup file'!$A:$F,6,FALSE) -> 0.026977273 | T60: =R60*H60 -> 3.96 | U60: =S60*H60 -> 53.415001
B61: 51939-234LF | C61: =J61/H61*1000 -> 1.2672 | D61: $ | E61: 552 | F61: 552PBRAH | G61: FCI USA LLC | H61: 2112 | I61: =H61*C61 -> 2676.3264 | J61: 2.6763264 | K61: 1.6658772 | L61: =(K61*H61)/1000 -> 3.5183327 | M61: =(J61-L61)/J61 -> -0.31461269 | R61: =VLOOKUP(B61,'[6]Backup file'!$A:$F,3,FALSE) -> 0.0019 | S61: =VLOOKUP(B61,'[6]Backup file'!$A:$F,6,FALSE) -> 0.014097426 | T61: =R61*H61 -> 4.0128 | U61: =S61*H61 -> 29.773764
B62: 51939-667LF | C62: =J62/H62*1000 -> 4.6667502 | D62: $ | E62: 552 | F62: 552PBRAH | G62: FCI USA LLC | H62: 264 | I62: =H62*C62 -> 1232.022 | J62: 1.232022 | K62: 1.6581732 | L62: =(K62*H62)/1000 -> 0.43775771 | M62: =(J62-L62)/J62 -> 0.64468354 | R62: =VLOOKUP(B62,'[6]Backup file'!$A:$F,3,FALSE) -> 0.002 | S62: =VLOOKUP(B62,'[6]Backup file'!$A:$F,6,FALSE) -> 0.039 | T62: =R62*H62 -> 0.528 | U62: =S62*H62 -> 10.296
B63: 51939-198LF | C63: =J63/H63*1000 -> 0.83647009 | D63: $ | E63: 552 | F63: 552PBRAH | G63: FCI USA LLC | H63: 462 | I63: =H63*C63 -> 386.44918 | J63: 0.38644918 | K63: 0.5736671 | L63: =(K63*H63)/1000 -> 0.2650342 | M63: =(J63-L63)/J63 -> 0.31418098 | R63: =VLOOKUP(B63,'[6]Backup file'!$A:$F,3,FALSE) -> 0.0061 | S63: =VLOOKUP(B63,'[6]Backup file'!$A:$F,6,FALSE) -> 0.01424 | T63: =R63*H63 -> 2.8182 | U63: =S63*H63 -> 6.57888
B64: 51939-927LF | C64: =J64/H64*1000 -> 1.22299 | D64: $ | E64: 552 | F64: 552PBRAH | G64: FCI USA LLC | H64: 4950 | I64: =H64*C64 -> 6053.8005 | J64: 6.0538005 | K64: 0.72867255 | L64: =(K64*H64)/1000 -> 3.6069291 | M64: =(J64-L64)/J64 -> 0.40418764 | R64: =VLOOKUP(B64,'[6]Backup file'!$A:$F,3,FALSE) -> 0.002 | S64: =VLOOKUP(B64,'[6]Backup file'!$A:$F,6,FALSE) -> 0.0238 | T64: =R64*H64 -> 9.9 | U64: =S64*H64 -> 117.81
B65: 51939-667LF | C65: =J65/H65*1000 -> 4.6667502 | D65: $ | E65: 552 | F65: 552PBRAH | G65: FCI USA LLC | H65: 264 | I65: =H65*C65 -> 1232.022 | J65: 1.232022 | K65: 1.6581732 | L65: =(K65*H65)/1000 -> 0.43775771 | M65: =(J65-L65)/J65 -> 0.64468354 | R65: =VLOOKUP(B65,'[6]Backup file'!$A:$F,3,FALSE) -> 0.002 | S65: =VLOOKUP(B65,'[6]Backup file'!$A:$F,6,FALSE) -> 0.039 | T65: =R65*H65 -> 0.528 | U65: =S65*H65 -> 10.296
B66: 51722-10802400ABLF | C66: =J66/H66*1000 -> 2.62602 | D66: $ | E66: 552 | F66: 552PBRAH | G66: FCI CONNECTORS KOREA LTD | H66: 264 | I66: =H66*C66 -> 693.26928 | J66: 0.69326928 | K66: 1.4685422 | L66: =(K66*H66)/1000 -> 0.38769515 | M66: =(J66-L66)/J66 -> 0.44077264 | R66: =VLOOKUP(B66,'[6]Backup file'!$A:$F,3,FALSE) -> 0.0019 | S66: =VLOOKUP(B66,'[6]Backup file'!$A:$F,6,FALSE) -> 0.029 | T66: =R66*H66 -> 0.5016 | U66: =S66*H66 -> 7.656
B67: 51939-030LF | C67: =J67/H67*1000 -> 1.98009 | D67: $ | E67: 552 | F67: 552PBRAH | G67: FCI CONNECTORS KOREA LTD | H67: 594 | I67: =H67*C67 -> 1176.1734 | J67: 1.1761734 | K67: 1.3262244 | L67: =(K67*H67)/1000 -> 0.78777732 | M67: =(J67-L67)/J67 -> 0.33022011 | R67: =VLOOKUP(B67,'[6]Backup file'!$A:$F,3,FALSE) -> 0.0016 | S67: =VLOOKUP(B67,'[6]Backup file'!$A:$F,6,FALSE) -> 0.028645 | T67: =R67*H67 -> 0.9504 | U67: =S67*H67 -> 17.01513
B68: 51939-030LF | C68: =J68/H68*1000 -> 1.9800901 | D68: $ | E68: 552 | F68: 552PBRAH | G68: FCI CONNECTORS KOREA LTD | H68: 396 | I68: =H68*C68 -> 784.11567 | J68: 0.78411567 | K68: 1.3262244 | L68: =(K68*H68)/1000 -> 0.52518488 | M68: =(J68-L68)/J68 -> 0.33022014 | R68: =VLOOKUP(B68,'[6]Backup file'!$A:$F,3,FALSE) -> 0.0016 | S68: =VLOOKUP(B68,'[6]Backup file'!$A:$F,6,FALSE) -> 0.028645 | T68: =R68*H68 -> 0.6336 | U68: =S68*H68 -> 11.34342
B69: 51730-145LF | C69: =J69/H69*1000 -> 2.75007 | D69: $ | E69: 552 | F69: 552PBRAH | G69: FCI DEUTSCHLAND GmbH | H69: 1320 | I69: =H69*C69 -> 3630.0924 | J69: 3.6300924 | K69: 0.96852796 | L69: =(K69*H69)/1000 -> 1.2784569 | M69: =(J69-L69)/J69 -> 0.64781698 | R69: =VLOOKUP(B69,'[6]Backup file'!$A:$F,3,FALSE) -> 0.0019 | S69: =VLOOKUP(B69,'[6]Backup file'!$A:$F,6,FALSE) -> 0.020617046 | T69: =R69*H69 -> 2.508 | U69: =S69*H69 -> 27.214501
B70: 51730-145LF | C70: =J70/H70*1000 -> 2.75007 | D70: $ | E70: 552 | F70: 552PBRAH | G70: FCI DEUTSCHLAND GmbH | H70: 1848 | I70: =H70*C70 -> 5082.1294 | J70: 5.0821294 | K70: 0.96852796 | L70: =(K70*H70)/1000 -> 1.7898397 | M70: =(J70-L70)/J70 -> 0.64781698 | R70: =VLOOKUP(B70,'[6]Backup file'!$A:$F,3,FALSE) -> 0.0019 | S70: =VLOOKUP(B70,'[6]Backup file'!$A:$F,6,FALSE) -> 0.020617046 | T70: =R70*H70 -> 3.5112 | U70: =S70*H70 -> 38.100301
I71: =H71*C71 -> 0 | J71: =I71/1000 -> 0 | L71: =(K71*H71)/1000 -> 0 | T71: =SUM(T2:T70) -> 884.51825 | U71: =SUM(U2:U70) -> 7469.0446
I72: =H72*C72 -> 0 | J72: =I72/1000 -> 0 | L72: =(K72*H72)/1000 -> 0 | T72: =SUM(T71:U71) -> 8353.5628
I73: =H73*C73 -> 0 | J73: =I73/1000 -> 0 | L73: =(K73*H73)/1000 -> 0
I74: =H74*C74 -> 0 | J74: =I74/1000 -> 0 | L74: =(K74*H74)/1000 -> 0
I75: =H75*C75 -> 0 | J75: =I75/1000 -> 0 | L75: =(K75*H75)/1000 -> 0
I76: =H76*C76 -> 0 | J76: =I76/1000 -> 0 | L76: =(K76*H76)/1000 -> 0
I77: =H77*C77 -> 0 | J77: =I77/1000 -> 0 | L77: =(K77*H77)/1000 -> 0 | N77: Interco
J78: =SUM(J2:J77) -> 417.69987 | L78: =SUM(L2:L77) -> 484.18091 | M78: =(J78-L78)/J78 -> -0.15915984
P87: Billing %K
O90: Europe | P90: 200 | Q90: 200
O91: VSELL | P91: 150 | Q91: 300
O92: AVNET | P92: 250 | Q92: 200
O93: FCI Taiwan | P93: 100 | Q93: 100
O94: FCI NT
P97: =SUM(P89:P96) -> 700
P98: =#REF!+#REF!+#REF! -> #REF!
P100: Sep
O101: FCI USA Pwr | P101: 3624
O102: Europe | P102: 400
O103: VSELL | P103: 150
O104: AVNET | P104: 350
O105: FCI Taiwan | P105: 100
O106: Flex
O107: FCI Asia Singapore | P107: 200
O108: FCI NT
O109: Others
P110: =SUM(P101:P109) -> 4824 | Q110: =SUM(Q101:Q109) -> 0
Q111: =#REF!-Q110 -> #REF!
